Workbook

Sheet Resumen
A1: Estado de avance de la digitalización de los censos históricos (1813–1982)
A2: Generado el 21-10-2026 con herramientas/resumen_avance.py. Conteos y niveles: fórmulas sobre las hojas Catálogo y Cifras. Columnas en azul: escritas a mano. Ver la hoja Notas.
A4: Censo | B4: Publicaciones | C4: Páginas del PDF | D4: Entradas en el catálogo | E4: Cuadros | F4: Bloques | G4: Textos | H4: Página del PDF verificada | I4: Página del PDF estimada | J4: Página sin ubicar o ausente | K4: Cuadros transcritos de la publicación | L4: Cifras digitalizadas del censo | M4: Total: transcrito | N4: Total: en los PDF | O4: Área: transcrito | P4: Área: en los PDF | Q4: Área × sexo: transcrito | R4: Área × sexo: en los PDF | S4: Sexo × edad: transcrito | T4: Sexo × edad: en los PDF | U4: Cifras inconsistentes anotadas | V4: Estado | W4: Pendiente / próximo paso | X4: Observaciones
A5: 1813 | B5: pub_1813 | C5: 263 | D5: =COUNTIFS(Catálogo!$B$2:$B$648,$A5) -> 31 | E5: =COUNTIFS(Catálogo!$B$2:$B$648,$A5,Catálogo!$F$2:$F$648,"cuadro") -> 15 | F5: =COUNTIFS(Catálogo!$B$2:$B$648,$A5,Catálogo!$F$2:$F$648,"bloque") -> 14 | G5: =COUNTIFS(Catálogo!$B$2:$B$648,$A5,Catálogo!$F$2:$F$648,"texto") -> 2 | H5: =COUNTIFS(Catálogo!$B$2:$B$648,$A5,Catálogo!$I$2:$I$648,"verificada") -> 31 | I5: =COUNTIFS(Catálogo!$B$2:$B$648,$A5,Catálogo!$I$2:$I$648,"estimada") -> 0 | J5: =COUNTIFS(Catálogo!$B$2:$B$648,$A5,Catálogo!$I$2:$I$648,"desconocida")+COUNTIFS(Catálogo!$B$2:$B$648,$A5,Catálogo!$I$2:$I$648,"ausente") -> 0 | K5: =COUNTIFS(Catálogo!$B$2:$B$648,$A5,Catálogo!$O$2:$O$648,"transcrito") -> 14 | L5: =SUMIFS(Cifras!$H$2:$H$399,Cifras!$A$2:$A$399,$A5) -> 596 | M5: =IF(COUNTIFS(Cifras!$A$2:$A$399,$A5,Cifras!$D$2:$D$399,"distrito")>0,"Distrito",IF(COUNTIFS(Cifras!$A$2:$A$399,$A5,Cifras!$D$2:$D$399,"comuna")>0,"Comuna",IF(COUNTIFS(Cifras!$A$2:$A$399,$A5,Cifras!$D$2:$D$399,"partido")>0,"Partido",IF(COUNTIFS(Cifras!$A$2:$A$399,$A5,Cifras!$D$2:$D$399,"departamento")>0,"Departamento",IF(COUNTIFS(Cifras!$A$2:$A$399,$A5,Cifras!$D$2:$D$399,"provincia")>0,"Provincia",IF(COUNTIFS(Cifras!$A$2:$A$399,$A5,Cifras!$D$2:$D$399,"region")>0,"Región",IF(COUNTIFS(Cifras!$A$2:$A$399,$A5,Cifras!$D$2:$D$399,"pais")>0,"País","—"))))))) -> Distrito | N5: =IF(IFERROR(MATCH(TRUE,COUNTIFS(Catálogo!$J$2:$J$648,"*"&$A5&"*",Catálogo!$I$2:$I$648,"<>ausente",Catálogo!$M$2:$M$648,"completa",Catálogo!$Q$2:$Q$648,{1,2,3,4,5,6,7,8,9})>0,0),0)>0,INDEX(Niveles!$C$2:$C$10,IFERROR(MATCH(TRUE,COUNTIFS(Catálogo!$J$2:$J$648,"*"&$A5&"*",Catálogo!$I$2:$I$648,"<>ausente",Catálogo!$M$2:$M$648,"completa",Catálogo!$Q$2:$Q$648,{1,2,3,4,5,6,7,8,9})>0,0),0))&IF(AND(IFERROR(MATCH(TRUE,COUNTIFS(Catálogo!$J$2:$J$648,"*"&$A5&"*",Catálogo!$I$2:$I$648,"<>ausente",Catálogo!$M$2:$M$648,"parcial",Catálogo!$Q$2:$Q$648,{1,2,3,4,5,6,7,8,9})>0,0),0)>0,IFERROR(MATCH(TRUE,COUNTIFS(Catálogo!$J$2:$J$648,"*"&$A5&"*",Catálogo!$I$2:$I$648,"<>ausente",Catálogo!$M$2:$M$648,"parcial",Catálogo!$Q$2:$Q$648,{1,2,3,4,5,6,7,8,9})>0,0),0)<IFERROR(MATCH(TRUE,COUNTIFS(Catálogo!$J$2:$J$648,"*"&$A5&"*",Catálogo!$I$2:$I$648,"<>ausente",Catálogo!$M$2:$M$648,"completa",Catálogo!$Q$2:$Q$648,{1,2,3,4,5,6,7,8,9})>0,0),0)),"; "&LOWER(INDEX(Niveles!$C$2:$C$10,IFERROR(MATCH(TRUE,COUNTIFS(Catálogo!$J$2:$J$648,"*"&$A5&"*",Catálogo!$I$2:$I$648,"<>ausente",Catálogo!$M$2:$M$648,"parcial",Catálogo!$Q$2:$Q$648,{1,2,3,4,5,6,7,8,9})>0,0),0)))&" (parcial)",""),IF(IFERROR(MATCH(TRUE,COUNTIFS(Catálogo!$J$2:$J$648,"*"&$A5&"*",Catálogo!$I$2:$I$648,"<>ausente",Catálogo!$M$2:$M$648,"parcial",Catálogo!$Q$2:$Q$648,{1,2,3,4,5,6,7,8,9})>0,0),0)>0,INDEX(Niveles!$C$2:$C$10,IFERROR(MATCH(TRUE,COUNTIFS(Catálogo!$J$2:$J$648,"*"&$A5&"*",Catálogo!$I$2:$I$648,"<>ausente",Catálogo!$M$2:$M$648,"parcial",Catálogo!$Q$2:$Q$648,{1,2,3,4,5,6,7,8,9})>0,0),0))&" (parcial)","—")) -> Distrito (parcial) | O5: =IF(COUNTIFS(Cifras!$A$2:$A$399,$A5,Cifras!$E$2:$E$399,"Sí",Cifras!$D$2:$D$399,"distrito")>0,"Distrito",IF(COUNTIFS(Cifras!$A$2:$A$399,$A5,Cifras!$E$2:$E$399,"Sí",Cifras!$D$2:$D$399,"comuna")>0,"Comuna",IF(COUNTIFS(Cifras!$A$2:$A$399,$A5,Cifras!$E$2:$E$399,"Sí",Cifras!$D$2:$D$399,"partido")>0,"Partido",IF(COUNTIFS(Cifras!$A$2:$A$399,$A5,Cifras!$E$2:$E$399,"Sí",Cifras!$D$2:$D$399,"departamento")>0,"Departamento",IF(COUNTIFS(Cifras!$A$2:$A$399,$A5,Cifras!$E$2:$E$399,"Sí",Cifras!$D$2:$D$399,"provincia")>0,"Provincia",IF(COUNTIFS(Cifras!$A$2:$A$399,$A5,Cifras!$E$2:$E$399,"Sí",Cifras!$D$2:$D$399,"region")>0,"Región",IF(COUNTIFS(Cifras!$A$2:$A$399,$A5,Cifras!$E$2:$E$399,"Sí",Cifras!$D$2:$D$399,"pais")>0,"País","—"))))))) -> — | P5: =IF(IFERROR(MATCH(TRUE,COUNTIFS(Catálogo!$J$2:$J$648,"*"&$A5&"*",Catálogo!$I$2:$I$648,"<>ausente",Catálogo!$M$2:$M$648,"completa",Catálogo!$L$2:$L$648,"*area*",Catálogo!$Q$2:$Q$648,{1,2,3,4,5,6,7,8,9})>0,0),0)>0,INDEX(Niveles!$C$2:$C$10,IFERROR(MATCH(TRUE,COUNTIFS(Catálogo!$J$2:$J$648,"*"&$A5&"*",Catálogo!$I$2:$I$648,"<>ausente",Catálogo!$M$2:$M$648,"completa",Catálogo!$L$2:$L$648,"*area*",Catálogo!$Q$2:$Q$648,{1,2,3,4,5,6,7,8,9})>0,0),0))&IF(AND(IFERROR(MATCH(TRUE,COUNTIFS(Catálogo!$J$2:$J$648,"*"&$A5&"*",Catálogo!$I$2:$I$648,"<>ausente",Catálogo!$M$2:$M$648,"parcial",Catálogo!$L$2:$L$648,"*area*",Catálogo!$Q$2:$Q$648,{1,2,3,4,5,6,7,8,9})>0,0),0)>0,IFERROR(MATCH(TRUE,COUNTIFS(Catálogo!$J$2:$J$648,"*"&$A5&"*",Catálogo!$I$2:$I$648,"<>ausente",Catálogo!$M$2:$M$648,"parcial",Catálogo!$L$2:$L$648,"*area*",Catálogo!$Q$2:$Q$648,{1,2,3,4,5,6,7,8,9})>0,0),0)<IFERROR(MATCH(TRUE,COUNTIFS(Catálogo!$J$2:$J$648,"*"&$A5&"*",Catálogo!$I$2:$I$648,"<>ausente",Catálogo!$M$2:$M$648,"completa",Catálogo!$L$2:$L$648,"*area*",Catálogo!$Q$2:$Q$648,{1,2,3,4,5,6,7,8,9})>0,0),0)),"; "&LOWER(INDEX(Niveles!$C$2:$C$10,IFERROR(MATCH(TRUE,COUNTIFS(Catálogo!$J$2:$J$648,"*"&$A5&"*",Catálogo!$I$2:$I$648,"<>ausente",Catálogo!$M$2:$M$648,"parcial",Catálogo!$L$2:$L$648,"*area*",Catálogo!$Q$2:$Q$648,{1,2,3,4,5,6,7,8,9})>0,0),0)))&" (parcial)",""),IF(IFERROR(MATCH(TRUE,COUNTIFS(Catálogo!$J$2:$J$648,"*"&$A5&"*",Catálogo!$I$2:$I$648,"<>ausente",Catálogo!$M$2:$M$648,"parcial",Catálogo!$L$2:$L$648,"*area*",Catálogo!$Q$2:$Q$648,{1,2,3,4,5,6,7,8,9})>0,0),0)>0,INDEX(Niveles!$C$2:$C$10,IFERROR(MATCH(TRUE,COUNTIFS(Catálogo!$J$2:$J$648,"*"&$A5&"*",Catálogo!$I$2:$I$648,"<>ausente",Catálogo!$M$2:$M$648,"parcial",Catálogo!$L$2:$L$648,"*area*",Catálogo!$Q$2:$Q$648,{1,2,3,4,5,6,7,8,9})>0,0),0))&" (parcial)","—")) -> — | Q5: =IF(COUNTIFS(Cifras!$A$2:$A$399,$A5,Cifras!$E$2:$E$399,"Sí",Cifras!$F$2:$F$399,"Sí",Cifras!$D$2:$D$399,"distrito")>0,"Distrito",IF(COUNTIFS(Cifras!$A$2:$A$399,$A5,Cifras!$E$2:$E$399,"Sí",Cifras!$F$2:$F$399,"Sí",Cifras!$D$2:$D$399,"comuna")>0,"Comuna",IF(COUNTIFS(Cifras!$A$2:$A$399,$A5,Cifras!$E$2:$E$399,"Sí",Cifras!$F$2:$F$399,"Sí",Cifras!$D$2:$D$399,"partido")>0,"Partido",IF(COUNTIFS(Cifras!$A$2:$A$399,$A5,Cifras!$E$2:$E$399,"Sí",Cifras!$F$2:$F$399,"Sí",Cifras!$D$2:$D$399,"departamento")>0,"Departamento",IF(COUNTIFS(Cifras!$A$2:$A$399,$A5,Cifras!$E$2:$E$399,"Sí",Cifras!$F$2:$F$399,"Sí",Cifras!$D$2:$D$399,"provincia")>0,"Provincia",IF(COUNTIFS(Cifras!$A$2:$A$399,$A5,Cifras!$E$2:$E$399,"Sí",Cifras!$F$2:$F$399,"Sí",Cifras!$D$2:$D$399,"region")>0,"Región",IF(COUNTIFS(Cifras!$A$2:$A$399,$A5,Cifras!$E$2:$E$399,"Sí",Cifras!$F$2:$F$399,"Sí",Cifras!$D$2:$D$399,"pais")>0,"País","—"))))))) -> — | R5: =IF(IFERROR(MATCH(TRUE,COUNTIFS(Catálogo!$J$2:$J$648,"*"&$A5&"*",Catálogo!$I$2:$I$648,"<>ausente",Catálogo!$M$2:$M$648,"completa",Catálogo!$L$2:$L$648,"*area*",Catálogo!$L$2:$L$648,"*sexo*",Catálogo!$Q$2:$Q$648,{1,2,3,4,5,6,7,8,9})>0,0),0)>0,INDEX(Niveles!$C$2:$C$10,IFERROR(MATCH(TRUE,COUNTIFS(Catálogo!$J$2:$J$648,"*"&$A5&"*",Catálogo!$I$2:$I$648,"<>ausente",Catálogo!$M$2:$M$648,"completa",Catálogo!$L$2:$L$648,"*area*",Catálogo!$L$2:$L$648,"*sexo*",Catálogo!$Q$2:$Q$648,{1,2,3,4,5,6,7,8,9})>0,0),0))&IF(AND(IFERROR(MATCH(TRUE,COUNTIFS(Catálogo!$J$2:$J$648,"*"&$A5&"*",Catálogo!$I$2:$I$648,"<>ausente",Catálogo!$M$2:$M$648,"parcial",Catálogo!$L$2:$L$648,"*area*",Catálogo!$L$2:$L$648,"*sexo*",Catálogo!$Q$2:$Q$648,{1,2,3,4,5,6,7,8,9})>0,0),0)>0,IFERROR(MATCH(TRUE,COUNTIFS(Catálogo!$J$2:$J$648,"*"&$A5&"*",Catálogo!$I$2:$I$648,"<>ausente",Catálogo!$M$2:$M$648,"parcial",Catálogo!$L$2:$L$648,"*area*",Catálogo!$L$2:$L$648,"*sexo*",Catálogo!$Q$2:$Q$648,{1,2,3,4,5,6,7,8,9})>0,0),0)<IFERROR(MATCH(TRUE,COUNTIFS(Catálogo!$J$2:$J$648,"*"&$A5&"*",Catálogo!$I$2:$I$648,"<>ausente",Catálogo!$M$2:$M$648,"completa",Catálogo!$L$2:$L$648,"*area*",Catálogo!$L$2:$L$648,"*sexo*",Catálogo!$Q$2:$Q$648,{1,2,3,4,5,6,7,8,9})>0,0),0)),"; "&LOWER(INDEX(Niveles!$C$2:$C$10,IFERROR(MATCH(TRUE,COUNTIFS(Catálogo!$J$2:$J$648,"*"&$A5&"*",Catálogo!$I$2:$I$648,"<>ausente",Catálogo!$M$2:$M$648,"parcial",Catálogo!$L$2:$L$648,"*area*",Catálogo!$L$2:$L$648,"*sexo*",Catálogo!$Q$2:$Q$648,{1,2,3,4,5,6,7,8,9})>0,0),0)))&" (parcial)",""),IF(IFERROR(MATCH(TRUE,COUNTIFS(Catálogo!$J$2:$J$648,"*"&$A5&"*",Catálogo!$I$2:$I$648,"<>ausente",Catálogo!$M$2:$M$648,"parcial",Catálogo!$L$2:$L$648,"*area*",Catálogo!$L$2:$L$648,"*sexo*",Catálogo!$Q$2:$Q$648,{1,2,3,4,5,6,7,8,9})>0,0),0)>0,INDEX(Niveles!$C$2:$C$10,IFERROR(MATCH(TRUE,COUNTIFS(Catálogo!$J$2:$J$648,"*"&$A5&"*",Catálogo!$I$2:$I$648,"<>ausente",Catálogo!$M$2:$M$648,"parcial",Catálogo!$L$2:$L$648,"*area*",Catálogo!$L$2:$L$648,"*sexo*",Catálogo!$Q$2:$Q$648,{1,2,3,4,5,6,7,8,9})>0,0),0))&" (parcial)","—")) -> — | S5: =IF(COUNTIFS(Cifras!$A$2:$A$399,$A5,Cifras!$F$2:$F$399,"Sí",Cifras!$G$2:$G$399,"Sí",Cifras!$D$2:$D$399,"distrito")>0,"Distrito",IF(COUNTIFS(Cifras!$A$2:$A$399,$A5,Cifras!$F$2:$F$399,"Sí",Cifras!$G$2:$G$399,"Sí",Cifras!$D$2:$D$399,"comuna")>0,"Comuna",IF(COUNTIFS(Cifras!$A$2:$A$399,$A5,Cifras!$F$2:$F$399,"Sí",Cifras!$G$2:$G$399,"Sí",Cifras!$D$2:$D$399,"partido")>0,"Partido",IF(COUNTIFS(Cifras!$A$2:$A$399,$A5,Cifras!$F$2:$F$399,"Sí",Cifras!$G$2:$G$399,"Sí",Cifras!$D$2:$D$399,"departamento")>0,"Departamento",IF(COUNTIFS(Cifras!$A$2:$A$399,$A5,Cifras!$F$2:$F$399,"Sí",Cifras!$G$2:$G$399,"Sí",Cifras!$D$2:$D$399,"provincia")>0,"Provincia",IF(COUNTIFS(Cifras!$A$2:$A$399,$A5,Cifras!$F$2:$F$399,"Sí",Cifras!$G$2:$G$399,"Sí",Cifras!$D$2:$D$399,"region")>0,"Región",IF(COUNTIFS(Cifras!$A$2:$A$399,$A5,Cifras!$F$2:$F$399,"Sí",Cifras!$G$2:$G$399,"Sí",Cifras!$D$2:$D$399,"pais")>0,"País","—"))))))) -> Partido | T5: =IF(IFERROR(MATCH(TRUE,COUNTIFS(Catálogo!$J$2:$J$648,"*"&$A5&"*",Catálogo!$I$2:$I$648,"<>ausente",Catálogo!$M$2:$M$648,"completa",Catálogo!$L$2:$L$648,"*sexo*",Catálogo!$L$2:$L$648,"*edad*",Catálogo!$Q$2:$Q$648,{1,2,3,4,5,6,7,8,9})>0,0),0)>0,INDEX(Niveles!$C$2:$C$10,IFERROR(MATCH(TRUE,COUNTIFS(Catálogo!$J$2:$J$648,"*"&$A5&"*",Catálogo!$I$2:$I$648,"<>ausente",Catálogo!$M$2:$M$648,"completa",Catálogo!$L$2:$L$648,"*sexo*",Catálogo!$L$2:$L$648,"*edad*",Catálogo!$Q$2:$Q$648,{1,2,3,4,5,6,7,8,9})>0,0),0))&IF(AND(IFERROR(MATCH(TRUE,COUNTIFS(Catálogo!$J$2:$J$648,"*"&$A5&"*",Catálogo!$I$2:$I$648,"<>ausente",Catálogo!$M$2:$M$648,"parcial",Catálogo!$L$2:$L$648,"*sexo*",Catálogo!$L$2:$L$648,"*edad*",Catálogo!$Q$2:$Q$648,{1,2,3,4,5,6,7,8,9})>0,0),0)>0,IFERROR(MATCH(TRUE,COUNTIFS(Catálogo!$J$2:$J$648,"*"&$A5&"*",Catálogo!$I$2:$I$648,"<>ausente",Catálogo!$M$2:$M$648,"parcial",Catálogo!$L$2:$L$648,"*sexo*",Catálogo!$L$2:$L$648,"*edad*",Catálogo!$Q$2:$Q$648,{1,2,3,4,5,6,7,8,9})>0,0),0)<IFERROR(MATCH(TRUE,COUNTIFS(Catálogo!$J$2:$J$648,"*"&$A5&"*",Catálogo!$I$2:$I$648,"<>ausente",Catálogo!$M$2:$M$648,"completa",Catálogo!$L$2:$L$648,"*sexo*",Catálogo!$L$2:$L$648,"*edad*",Catálogo!$Q$2:$Q$648,{1,2,3,4,5,6,7,8,9})>0,0),0)),"; "&LOWER(INDEX(Niveles!$C$2:$C$10,IFERROR(MATCH(TRUE,COUNTIFS(Catálogo!$J$2:$J$648,"*"&$A5&"*",Catálogo!$I$2:$I$648,"<>ausente",Catálogo!$M$2:$M$648,"parcial",Catálogo!$L$2:$L$648,"*sexo*",Catálogo!$L$2:$L$648,"*edad*",Catálogo!$Q$2:$Q$648,{1,2,3,4,5,6,7,8,9})>0,0),0)))&" (parcial)",""),IF(IFERROR(MATCH(TRUE,COUNTIFS(Catálogo!$J$2:$J$648,"*"&$A5&"*",Catálogo!$I$2:$I$648,"<>ausente",Catálogo!$M$2:$M$648,"parcial",Catálogo!$L$2:$L$648,"*sexo*",Catálogo!$L$2:$L$648,"*edad*",Catálogo!$Q$2:$Q$648,{1,2,3,4,5,6,7,8,9})>0,0),0)>0,INDEX(Niveles!$C$2:$C$10,IFERROR(MATCH(TRUE,COUNTIFS(Catálogo!$J$2:$J$648,"*"&$A5&"*",Catálogo!$I$2:$I$648,"<>ausente",Catálogo!$M$2:$M$648,"parcial",Catálogo!$L$2:$L$648,"*sexo*",Catálogo!$L$2:$L$648,"*edad*",Catálogo!$Q$2:$Q$648,{1,2,3,4,5,6,7,8,9})>0,0),0))&" (parcial)","—")) -> Distrito (parcial) | U5: =SUMIFS(Cifras!$J$2:$J$399,Cifras!$A$2:$A$399,$A5) -> 0 | V5: Parcial | W5: Opcional: edades por distrito desde los «Censo de territorio» (bloques). Santiago no está en la edición; Concepción solo con matrículas de 1812. | X5: Partido × sexo × edad (5 tramos) y × estado civil, y distrito × sexo, de los 14 partidos de Copiapó a Talca (cobertura parcial del país). Totales validados con el estado civil; en 8 partidos las edades no suman el total y en 4 los distritos tampoco (impreso así).
A6: 1835 | B6: pub_1835 | C6: 117 | D6: =COUNTIFS(Catálogo!$B$2:$B$648,$A6) -> 15 | E6: =COUNTIFS(Catálogo!$B$2:$B$648,$A6,Catálogo!$F$2:$F$648,"cuadro") -> 10 | F6: =COUNTIFS(Catálogo!$B$2:$B$648,$A6,Catálogo!$F$2:$F$648,"bloque") -> 0 | G6: =COUNTIFS(Catálogo!$B$2:$B$648,$A6,Catálogo!$F$2:$F$648,"texto") -> 5 | H6: =COUNTIFS(Catálogo!$B$2:$B$648,$A6,Catálogo!$I$2:$I$648,"verificada") -> 1 | I6: =COUNTIFS(Catálogo!$B$2:$B$648,$A6,Catálogo!$I$2:$I$648,"estimada") -> 14 | J6: =COUNTIFS(Catálogo!$B$2:$B$648,$A6,Catálogo!$I$2:$I$648,"desconocida")+COUNTIFS(Catálogo!$B$2:$B$648,$A6,Catálogo!$I$2:$I$648,"ausente") -> 0 | K6: =COUNTIFS(Catálogo!$B$2:$B$648,$A6,Catálogo!$O$2:$O$648,"transcrito") -> 9 | L6: =SUMIFS(Cifras!$H$2:$H$399,Cifras!$A$2:$A$399,$A6) -> 430 | M6: =IF(COUNTIFS(Cifras!$A$2:$A$399,$A6,Cifras!$D$2:$D$399,"distrito")>0,"Distrito",IF(COUNTIFS(Cifras!$A$2:$A$399,$A6,Cifras!$D$2:$D$399,"comuna")>0,"Comuna",IF(COUNTIFS(Cifras!$A$2:$A$399,$A6,Cifras!$D$2:$D$399,"partido")>0,"Partido",IF(COUNTIFS(Cifras!$A$2:$A$399,$A6,Cifras!$D$2:$D$399,"departamento")>0,"Departamento",IF(COUNTIFS(Cifras!$A$2:$A$399,$A6,Cifras!$D$2:$D$399,"provincia")>0,"Provincia",IF(COUNTIFS(Cifras!$A$2:$A$399,$A6,Cifras!$D$2:$D$399,"region")>0,"Región",IF(COUNTIFS(Cifras!$A$2:$A$399,$A6,Cifras!$D$2:$D$399,"pais")>0,"País","—"))))))) -> Departamento | N6: =IF(IFERROR(MATCH(TRUE,COUNTIFS(Catálogo!$J$2:$J$648,"*"&$A6&"*",Catálogo!$I$2:$I$648,"<>ausente",Catálogo!$M$2:$M$648,"completa",Catálogo!$Q$2:$Q$648,{1,2,3,4,5,6,7,8,9})>0,0),0)>0,INDEX(Niveles!$C$2:$C$10,IFERROR(MATCH(TRUE,COUNTIFS(Catálogo!$J$2:$J$648,"*"&$A6&"*",Catálogo!$I$2:$I$648,"<>ausente",Catálogo!$M$2:$M$648,"completa",Catálogo!$Q$2:$Q$648,{1,2,3,4,5,6,7,8,9})>0,0),0))&IF(AND(IFERROR(MATCH(TRUE,COUNTIFS(Catálogo!$J$2:$J$648,"*"&$A6&"*",Catálogo!$I$2:$I$648,"<>ausente",Catálogo!$M$2:$M$648,"parcial",Catálogo!$Q$2:$Q$648,{1,2,3,4,5,6,7,8,9})>0,0),0)>0,IFERROR(MATCH(TRUE,COUNTIFS(Catálogo!$J$2:$J$648,"*"&$A6&"*",Catálogo!$I$2:$I$648,"<>ausente",Catálogo!$M$2:$M$648,"parcial",Catálogo!$Q$2:$Q$648,{1,2,3,4,5,6,7,8,9})>0,0),0)<IFERROR(MATCH(TRUE,COUNTIFS(Catálogo!$J$2:$J$648,"*"&$A6&"*",Catálogo!$I$2:$I$648,"<>ausente",Catálogo!$M$2:$M$648,"completa",Catálogo!$Q$2:$Q$648,{1,2,3,4,5,6,7,8,9})>0,0),0)),"; "&LOWER(INDEX(Niveles!$C$2:$C$10,IFERROR(MATCH(TRUE,COUNTIFS(Catálogo!$J$2:$J$648,"*"&$A6&"*",Catálogo!$I$2:$I$648,"<>ausente",Catálogo!$M$2:$M$648,"parcial",Catálogo!$Q$2:$Q$648,{1,2,3,4,5,6,7,8,9})>0,0),0)))&" (parcial)",""),IF(IFERROR(MATCH(TRUE,COUNTIFS(Catálogo!$J$2:$J$648,"*"&$A6&"*",Catálogo!$I$2:$I$648,"<>ausente",Catálogo!$M$2:$M$648,"parcial",Catálogo!$Q$2:$Q$648,{1,2,3,4,5,6,7,8,9})>0,0),0)>0,INDEX(Niveles!$C$2:$C$10,IFERROR(MATCH(TRUE,COUNTIFS(Catálogo!$J$2:$J$648,"*"&$A6&"*",Catálogo!$I$2:$I$648,"<>ausente",Catálogo!$M$2:$M$648,"parcial",Catálogo!$Q$2:$Q$648,{1,2,3,4,5,6,7,8,9})>0,0),0))&" (parcial)","—")) -> Departamento | O6: =IF(COUNTIFS(Cifras!$A$2:$A$399,$A6,Cifras!$E$2:$E$399,"Sí",Cifras!$D$2:$D$399,"distrito")>0,"Distrito",IF(COUNTIFS(Cifras!$A$2:$A$399,$A6,Cifras!$E$2:$E$399,"Sí",Cifras!$D$2:$D$399,"comuna")>0,"Comuna",IF(COUNTIFS(Cifras!$A$2:$A$399,$A6,Cifras!$E$2:$E$399,"Sí",Cifras!$D$2:$D$399,"partido")>0,"Partido",IF(COUNTIFS(Cifras!$A$2:$A$399,$A6,Cifras!$E$2:$E$399,"Sí",Cifras!$D$2:$D$399,"departamento")>0,"Departamento",IF(COUNTIFS(Cifras!$A$2:$A$399,$A6,Cifras!$E$2:$E$399,"Sí",Cifras!$D$2:$D$399,"provincia")>0,"Provincia",IF(COUNTIFS(Cifras!$A$2:$A$399,$A6,Cifras!$E$2:$E$399,"Sí",Cifras!$D$2:$D$399,"region")>0,"Región",IF(COUNTIFS(Cifras!$A$2:$A$399,$A6,Cifras!$E$2:$E$399,"Sí",Cifras!$D$2:$D$399,"pais")>0,"País","—"))))))) -> — | P6: =IF(IFERROR(MATCH(TRUE,COUNTIFS(Catálogo!$J$2:$J$648,"*"&$A6&"*",Catálogo!$I$2:$I$648,"<>ausente",Catálogo!$M$2:$M$648,"completa",Catálogo!$L$2:$L$648,"*area*",Catálogo!$Q$2:$Q$648,{1,2,3,4,5,6,7,8,9})>0,0),0)>0,INDEX(Niveles!$C$2:$C$10,IFERROR(MATCH(TRUE,COUNTIFS(Catálogo!$J$2:$J$648,"*"&$A6&"*",Catálogo!$I$2:$I$648,"<>ausente",Catálogo!$M$2:$M$648,"completa",Catálogo!$L$2:$L$648,"*area*",Catálogo!$Q$2:$Q$648,{1,2,3,4,5,6,7,8,9})>0,0),0))&IF(AND(IFERROR(MATCH(TRUE,COUNTIFS(Catálogo!$J$2:$J$648,"*"&$A6&"*",Catálogo!$I$2:$I$648,"<>ausente",Catálogo!$M$2:$M$648,"parcial",Catálogo!$L$2:$L$648,"*area*",Catálogo!$Q$2:$Q$648,{1,2,3,4,5,6,7,8,9})>0,0),0)>0,IFERROR(MATCH(TRUE,COUNTIFS(Catálogo!$J$2:$J$648,"*"&$A6&"*",Catálogo!$I$2:$I$648,"<>ausente",Catálogo!$M$2:$M$648,"parcial",Catálogo!$L$2:$L$648,"*area*",Catálogo!$Q$2:$Q$648,{1,2,3,4,5,6,7,8,9})>0,0),0)<IFERROR(MATCH(TRUE,COUNTIFS(Catálogo!$J$2:$J$648,"*"&$A6&"*",Catálogo!$I$2:$I$648,"<>ausente",Catálogo!$M$2:$M$648,"completa",Catálogo!$L$2:$L$648,"*area*",Catálogo!$Q$2:$Q$648,{1,2,3,4,5,6,7,8,9})>0,0),0)),"; "&LOWER(INDEX(Niveles!$C$2:$C$10,IFERROR(MATCH(TRUE,COUNTIFS(Catálogo!$J$2:$J$648,"*"&$A6&"*",Catálogo!$I$2:$I$648,"<>ausente",Catálogo!$M$2:$M$648,"parcial",Catálogo!$L$2:$L$648,"*area*",Catálogo!$Q$2:$Q$648,{1,2,3,4,5,6,7,8,9})>0,0),0)))&" (parcial)",""),IF(IFERROR(MATCH(TRUE,COUNTIFS(Catálogo!$J$2:$J$648,"*"&$A6&"*",Catálogo!$I$2:$I$648,"<>ausente",Catálogo!$M$2:$M$648,"parcial",Catálogo!$L$2:$L$648,"*area*",Catálogo!$Q$2:$Q$648,{1,2,3,4,5,6,7,8,9})>0,0),0)>0,INDEX(Niveles!$C$2:$C$10,IFERROR(MATCH(TRUE,COUNTIFS(Catálogo!$J$2:$J$648,"*"&$A6&"*",Catálogo!$I$2:$I$648,"<>ausente",Catálogo!$M$2:$M$648,"parcial",Catálogo!$L$2:$L$648,"*area*",Catálogo!$Q$2:$Q$648,{1,2,3,4,5,6,7,8,9})>0,0),0))&" (parcial)","—")) -> — | Q6: =IF(COUNTIFS(Cifras!$A$2:$A$399,$A6,Cifras!$E$2:$E$399,"Sí",Cifras!$F$2:$F$399,"Sí",Cifras!$D$2:$D$399,"distrito")>0,"Distrito",IF(COUNTIFS(Cifras!$A$2:$A$399,$A6,Cifras!$E$2:$E$399,"Sí",Cifras!$F$2:$F$399,"Sí",Cifras!$D$2:$D$399,"comuna")>0,"Comuna",IF(COUNTIFS(Cifras!$A$2:$A$399,$A6,Cifras!$E$2:$E$399,"Sí",Cifras!$F$2:$F$399,"Sí",Cifras!$D$2:$D$399,"partido")>0,"Partido",IF(COUNTIFS(Cifras!$A$2:$A$399,$A6,Cifras!$E$2:$E$399,"Sí",Cifras!$F$2:$F$399,"Sí",Cifras!$D$2:$D$399,"departamento")>0,"Departamento",IF(COUNTIFS(Cifras!$A$2:$A$399,$A6,Cifras!$E$2:$E$399,"Sí",Cifras!$F$2:$F$399,"Sí",Cifras!$D$2:$D$399,"provincia")>0,"Provincia",IF(COUNTIFS(Cifras!$A$2:$A$399,$A6,Cifras!$E$2:$E$399,"Sí",Cifras!$F$2:$F$399,"Sí",Cifras!$D$2:$D$399,"region")>0,"Región",IF(COUNTIFS(Cifras!$A$2:$A$399,$A6,Cifras!$E$2:$E$399,"Sí",Cifras!$F$2:$F$399,"Sí",Cifras!$D$2:$D$399,"pais")>0,"País","—"))))))) -> — | R6: =IF(IFERROR(MATCH(TRUE,COUNTIFS(Catálogo!$J$2:$J$648,"*"&$A6&"*",Catálogo!$I$2:$I$648,"<>ausente",Catálogo!$M$2:$M$648,"completa",Catálogo!$L$2:$L$648,"*area*",Catálogo!$L$2:$L$648,"*sexo*",Catálogo!$Q$2:$Q$648,{1,2,3,4,5,6,7,8,9})>0,0),0)>0,INDEX(Niveles!$C$2:$C$10,IFERROR(MATCH(TRUE,COUNTIFS(Catálogo!$J$2:$J$648,"*"&$A6&"*",Catálogo!$I$2:$I$648,"<>ausente",Catálogo!$M$2:$M$648,"completa",Catálogo!$L$2:$L$648,"*area*",Catálogo!$L$2:$L$648,"*sexo*",Catálogo!$Q$2:$Q$648,{1,2,3,4,5,6,7,8,9})>0,0),0))&IF(AND(IFERROR(MATCH(TRUE,COUNTIFS(Catálogo!$J$2:$J$648,"*"&$A6&"*",Catálogo!$I$2:$I$648,"<>ausente",Catálogo!$M$2:$M$648,"parcial",Catálogo!$L$2:$L$648,"*area*",Catálogo!$L$2:$L$648,"*sexo*",Catálogo!$Q$2:$Q$648,{1,2,3,4,5,6,7,8,9})>0,0),0)>0,IFERROR(MATCH(TRUE,COUNTIFS(Catálogo!$J$2:$J$648,"*"&$A6&"*",Catálogo!$I$2:$I$648,"<>ausente",Catálogo!$M$2:$M$648,"parcial",Catálogo!$L$2:$L$648,"*area*",Catálogo!$L$2:$L$648,"*sexo*",Catálogo!$Q$2:$Q$648,{1,2,3,4,5,6,7,8,9})>0,0),0)<IFERROR(MATCH(TRUE,COUNTIFS(Catálogo!$J$2:$J$648,"*"&$A6&"*",Catálogo!$I$2:$I$648,"<>ausente",Catálogo!$M$2:$M$648,"completa",Catálogo!$L$2:$L$648,"*area*",Catálogo!$L$2:$L$648,"*sexo*",Catálogo!$Q$2:$Q$648,{1,2,3,4,5,6,7,8,9})>0,0),0)),"; "&LOWER(INDEX(Niveles!$C$2:$C$10,IFERROR(MATCH(TRUE,COUNTIFS(Catálogo!$J$2:$J$648,"*"&$A6&"*",Catálogo!$I$2:$I$648,"<>ausente",Catálogo!$M$2:$M$648,"parcial",Catálogo!$L$2:$L$648,"*area*",Catálogo!$L$2:$L$648,"*sexo*",Catálogo!$Q$2:$Q$648,{1,2,3,4,5,6,7,8,9})>0,0),0)))&" (parcial)",""),IF(IFERROR(MATCH(TRUE,COUNTIFS(Catálogo!$J$2:$J$648,"*"&$A6&"*",Catálogo!$I$2:$I$648,"<>ausente",Catálogo!$M$2:$M$648,"parcial",Catálogo!$L$2:$L$648,"*area*",Catálogo!$L$2:$L$648,"*sexo*",Catálogo!$Q$2:$Q$648,{1,2,3,4,5,6,7,8,9})>0,0),0)>0,INDEX(Niveles!$C$2:$C$10,IFERROR(MATCH(TRUE,COUNTIFS(Catálogo!$J$2:$J$648,"*"&$A6&"*",Catálogo!$I$2:$I$648,"<>ausente",Catálogo!$M$2:$M$648,"parcial",Catálogo!$L$2:$L$648,"*area*",Catálogo!$L$2:$L$648,"*sexo*",Catálogo!$Q$2:$Q$648,{1,2,3,4,5,6,7,8,9})>0,0),0))&" (parcial)","—")) -> — | S6: =IF(COUNTIFS(Cifras!$A$2:$A$399,$A6,Cifras!$F$2:$F$399,"Sí",Cifras!$G$2:$G$399,"Sí",Cifras!$D$2:$D$399,"distrito")>0,"Distrito",IF(COUNTIFS(Cifras!$A$2:$A$399,$A6,Cifras!$F$2:$F$399,"Sí",Cifras!$G$2:$G$399,"Sí",Cifras!$D$2:$D$399,"comuna")>0,"Comuna",IF(COUNTIFS(Cifras!$A$2:$A$399,$A6,Cifras!$F$2:$F$399,"Sí",Cifras!$G$2:$G$399,"Sí",Cifras!$D$2:$D$399,"partido")>0,"Partido",IF(COUNTIFS(Cifras!$A$2:$A$399,$A6,Cifras!$F$2:$F$399,"Sí",Cifras!$G$2:$G$399,"Sí",Cifras!$D$2:$D$399,"departamento")>0,"Departamento",IF(COUNTIFS(Cifras!$A$2:$A$399,$A6,Cifras!$F$2:$F$399,"Sí",Cifras!$G$2:$G$399,"Sí",Cifras!$D$2:$D$399,"provincia")>0,"Provincia",IF(COUNTIFS(Cifras!$A$2:$A$399,$A6,Cifras!$F$2:$F$399,"Sí",Cifras!$G$2:$G$399,"Sí",Cifras!$D$2:$D$399,"region")>0,"Región",IF(COUNTIFS(Cifras!$A$2:$A$399,$A6,Cifras!$F$2:$F$399,"Sí",Cifras!$G$2:$G$399,"Sí",Cifras!$D$2:$D$399,"pais")>0,"País","—"))))))) -> — | T6: =IF(IFERROR(MATCH(TRUE,COUNTIFS(Catálogo!$J$2:$J$648,"*"&$A6&"*",Catálogo!$I$2:$I$648,"<>ausente",Catálogo!$M$2:$M$648,"completa",Catálogo!$L$2:$L$648,"*sexo*",Catálogo!$L$2:$L$648,"*edad*",Catálogo!$Q$2:$Q$648,{1,2,3,4,5,6,7,8,9})>0,0),0)>0,INDEX(Niveles!$C$2:$C$10,IFERROR(MATCH(TRUE,COUNTIFS(Catálogo!$J$2:$J$648,"*"&$A6&"*",Catálogo!$I$2:$I$648,"<>ausente",Catálogo!$M$2:$M$648,"completa",Catálogo!$L$2:$L$648,"*sexo*",Catálogo!$L$2:$L$648,"*edad*",Catálogo!$Q$2:$Q$648,{1,2,3,4,5,6,7,8,9})>0,0),0))&IF(AND(IFERROR(MATCH(TRUE,COUNTIFS(Catálogo!$J$2:$J$648,"*"&$A6&"*",Catálogo!$I$2:$I$648,"<>ausente",Catálogo!$M$2:$M$648,"parcial",Catálogo!$L$2:$L$648,"*sexo*",Catálogo!$L$2:$L$648,"*edad*",Catálogo!$Q$2:$Q$648,{1,2,3,4,5,6,7,8,9})>0,0),0)>0,IFERROR(MATCH(TRUE,COUNTIFS(Catálogo!$J$2:$J$648,"*"&$A6&"*",Catálogo!$I$2:$I$648,"<>ausente",Catálogo!$M$2:$M$648,"parcial",Catálogo!$L$2:$L$648,"*sexo*",Catálogo!$L$2:$L$648,"*edad*",Catálogo!$Q$2:$Q$648,{1,2,3,4,5,6,7,8,9})>0,0),0)<IFERROR(MATCH(TRUE,COUNTIFS(Catálogo!$J$2:$J$648,"*"&$A6&"*",Catálogo!$I$2:$I$648,"<>ausente",Catálogo!$M$2:$M$648,"completa",Catálogo!$L$2:$L$648,"*sexo*",Catálogo!$L$2:$L$648,"*edad*",Catálogo!$Q$2:$Q$648,{1,2,3,4,5,6,7,8,9})>0,0),0)),"; "&LOWER(INDEX(Niveles!$C$2:$C$10,IFERROR(MATCH(TRUE,COUNTIFS(Catálogo!$J$2:$J$648,"*"&$A6&"*",Catálogo!$I$2:$I$648,"<>ausente",Catálogo!$M$2:$M$648,"parcial",Catálogo!$L$2:$L$648,"*sexo*",Catálogo!$L$2:$L$648,"*edad*",Catálogo!$Q$2:$Q$648,{1,2,3,4,5,6,7,8,9})>0,0),0)))&" (parcial)",""),IF(IFERROR(MATCH(TRUE,COUNTIFS(Catálogo!$J$2:$J$648,"*"&$A6&"*",Catálogo!$I$2:$I$648,"<>ausente",Catálogo!$M$2:$M$648,"parcial",Catálogo!$L$2:$L$648,"*sexo*",Catálogo!$L$2:$L$648,"*edad*",Catálogo!$Q$2:$Q$648,{1,2,3,4,5,6,7,8,9})>0,0),0)>0,INDEX(Niveles!$C$2:$C$10,IFERROR(MATCH(TRUE,COUNTIFS(Catálogo!$J$2:$J$648,"*"&$A6&"*",Catálogo!$I$2:$I$648,"<>ausente",Catálogo!$M$2:$M$648,"parcial",Catálogo!$L$2:$L$648,"*sexo*",Catálogo!$L$2:$L$648,"*edad*",Catálogo!$Q$2:$Q$648,{1,2,3,4,5,6,7,8,9})>0,0),0))&" (parcial)","—")) -> — | U6: =SUMIFS(Cifras!$J$2:$J$399,Cifras!$A$2:$A$399,$A6) -> 2 | V6: Parcial | W6: Nada más en el PDF para el núcleo: no trae edad ni área. Opcional: subdelegaciones de Santiago (PDF 93). | X6: Departamento × sexo × estado (solteros/casados) desde la propia publicación (arts. 34–42), validado con los sinópticos de 1865 y 1875 (salvo Cauquenes, +2). Sin edad en la publicación.
A7: 1843 | B7: — | D7: =COUNTIFS(Catálogo!$B$2:$B$648,$A7) -> 0 | E7: =COUNTIFS(Catálogo!$B$2:$B$648,$A7,Catálogo!$F$2:$F$648,"cuadro") -> 0 | F7: =COUNTIFS(Catálogo!$B$2:$B$648,$A7,Catálogo!$F$2:$F$648,"bloque") -> 0 | G7: =COUNTIFS(Catálogo!$B$2:$B$648,$A7,Catálogo!$F$2:$F$648,"texto") -> 0 | H7: =COUNTIFS(Catálogo!$B$2:$B$648,$A7,Catálogo!$I$2:$I$648,"verificada") -> 0 | I7: =COUNTIFS(Catálogo!$B$2:$B$648,$A7,Catálogo!$I$2:$I$648,"estimada") -> 0 | J7: =COUNTIFS(Catálogo!$B$2:$B$648,$A7,Catálogo!$I$2:$I$648,"desconocida")+COUNTIFS(Catálogo!$B$2:$B$648,$A7,Catálogo!$I$2:$I$648,"ausente") -> 0 | K7: =COUNTIFS(Catálogo!$B$2:$B$648,$A7,Catálogo!$O$2:$O$648,"transcrito") -> 0 | L7: =SUMIFS(Cifras!$H$2:$H$399,Cifras!$A$2:$A$399,$A7) -> 137 | M7: =IF(COUNTIFS(Cifras!$A$2:$A$399,$A7,Cifras!$D$2:$D$399,"distrito")>0,"Distrito",IF(COUNTIFS(Cifras!$A$2:$A$399,$A7,Cifras!$D$2:$D$399,"comuna")>0,"Comuna",IF(COUNTIFS(Cifras!$A$2:$A$399,$A7,Cifras!$D$2:$D$399,"partido")>0,"Partido",IF(COUNTIFS(Cifras!$A$2:$A$399,$A7,Cifras!$D$2:$D$399,"departamento")>0,"Departamento",IF(COUNTIFS(Cifras!$A$2:$A$399,$A7,Cifras!$D$2:$D$399,"provincia")>0,"Provincia",IF(COUNTIFS(Cifras!$A$2:$A$399,$A7,Cifras!$D$2:$D$399,"region")>0,"Región",IF(COUNTIFS(Cifras!$A$2:$A$399,$A7,Cifras!$D$2:$D$399,"pais")>0,"País","—"))))))) -> Departamento | N7: =IF(IFERROR(MATCH(TRUE,COUNTIFS(Catálogo!$J$2:$J$648,"*"&$A7&"*",Catálogo!$I$2:$I$648,"<>ausente",Catálogo!$M$2:$M$648,"completa",Catálogo!$Q$2:$Q$648,{1,2,3,4,5,6,7,8,9})>0,0),0)>0,INDEX(Niveles!$C$2:$C$10,IFERROR(MATCH(TRUE,COUNTIFS(Catálogo!$J$2:$J$648,"*"&$A7&"*",Catálogo!$I$2:$I$648,"<>ausente",Catálogo!$M$2:$M$648,"completa",Catálogo!$Q$2:$Q$648,{1,2,3,4,5,6,7,8,9})>0,0),0))&IF(AND(IFERROR(MATCH(TRUE,COUNTIFS(Catálogo!$J$2:$J$648,"*"&$A7&"*",Catálogo!$I$2:$I$648,"<>ausente",Catálogo!$M$2:$M$648,"parcial",Catálogo!$Q$2:$Q$648,{1,2,3,4,5,6,7,8,9})>0,0),0)>0,IFERROR(MATCH(TRUE,COUNTIFS(Catálogo!$J$2:$J$648,"*"&$A7&"*",Catálogo!$I$2:$I$648,"<>ausente",Catálogo!$M$2:$M$648,"parcial",Catálogo!$Q$2:$Q$648,{1,2,3,4,5,6,7,8,9})>0,0),0)<IFERROR(MATCH(TRUE,COUNTIFS(Catálogo!$J$2:$J$648,"*"&$A7&"*",Catálogo!$I$2:$I$648,"<>ausente",Catálogo!$M$2:$M$648,"completa",Catálogo!$Q$2:$Q$648,{1,2,3,4,5,6,7,8,9})>0,0),0)),"; "&LOWER(INDEX(Niveles!$C$2:$C$10,IFERROR(MATCH(TRUE,COUNTIFS(Catálogo!$J$2:$J$648,"*"&$A7&"*",Catálogo!$I$2:$I$648,"<>ausente",Catálogo!$M$2:$M$648,"parcial",Catálogo!$Q$2:$Q$648,{1,2,3,4,5,6,7,8,9})>0,0),0)))&" (parcial)",""),IF(IFERROR(MATCH(TRUE,COUNTIFS(Catálogo!$J$2:$J$648,"*"&$A7&"*",Catálogo!$I$2:$I$648,"<>ausente",Catálogo!$M$2:$M$648,"parcial",Catálogo!$Q$2:$Q$648,{1,2,3,4,5,6,7,8,9})>0,0),0)>0,INDEX(Niveles!$C$2:$C$10,IFERROR(MATCH(TRUE,COUNTIFS(Catálogo!$J$2:$J$648,"*"&$A7&"*",Catálogo!$I$2:$I$648,"<>ausente",Catálogo!$M$2:$M$648,"parcial",Catálogo!$Q$2:$Q$648,{1,2,3,4,5,6,7,8,9})>0,0),0))&" (parcial)","—")) -> Departamento | O7: =IF(COUNTIFS(Cifras!$A$2:$A$399,$A7,Cifras!$E$2:$E$399,"Sí",Cifras!$D$2:$D$399,"distrito")>0,"Distrito",IF(COUNTIFS(Cifras!$A$2:$A$399,$A7,Cifras!$E$2:$E$399,"Sí",Cifras!$D$2:$D$399,"comuna")>0,"Comuna",IF(COUNTIFS(Cifras!$A$2:$A$399,$A7,Cifras!$E$2:$E$399,"Sí",Cifras!$D$2:$D$399,"partido")>0,"Partido",IF(COUNTIFS(Cifras!$A$2:$A$399,$A7,Cifras!$E$2:$E$399,"Sí",Cifras!$D$2:$D$399,"departamento")>0,"Departamento",IF(COUNTIFS(Cifras!$A$2:$A$399,$A7,Cifras!$E$2:$E$399,"Sí",Cifras!$D$2:$D$399,"provincia")>0,"Provincia",IF(COUNTIFS(Cifras!$A$2:$A$399,$A7,Cifras!$E$2:$E$399,"Sí",Cifras!$D$2:$D$399,"region")>0,"Región",IF(COUNTIFS(Cifras!$A$2:$A$399,$A7,Cifras!$E$2:$E$399,"Sí",Cifras!$D$2:$D$399,"pais")>0,"País","—"))))))) -> — | P7: =IF(IFERROR(MATCH(TRUE,COUNTIFS(Catálogo!$J$2:$J$648,"*"&$A7&"*",Catálogo!$I$2:$I$648,"<>ausente",Catálogo!$M$2:$M$648,"completa",Catálogo!$L$2:$L$648,"*area*",Catálogo!$Q$2:$Q$648,{1,2,3,4,5,6,7,8,9})>0,0),0)>0,INDEX(Niveles!$C$2:$C$10,IFERROR(MATCH(TRUE,COUNTIFS(Catálogo!$J$2:$J$648,"*"&$A7&"*",Catálogo!$I$2:$I$648,"<>ausente",Catálogo!$M$2:$M$648,"completa",Catálogo!$L$2:$L$648,"*area*",Catálogo!$Q$2:$Q$648,{1,2,3,4,5,6,7,8,9})>0,0),0))&IF(AND(IFERROR(MATCH(TRUE,COUNTIFS(Catálogo!$J$2:$J$648,"*"&$A7&"*",Catálogo!$I$2:$I$648,"<>ausente",Catálogo!$M$2:$M$648,"parcial",Catálogo!$L$2:$L$648,"*area*",Catálogo!$Q$2:$Q$648,{1,2,3,4,5,6,7,8,9})>0,0),0)>0,IFERROR(MATCH(TRUE,COUNTIFS(Catálogo!$J$2:$J$648,"*"&$A7&"*",Catálogo!$I$2:$I$648,"<>ausente",Catálogo!$M$2:$M$648,"parcial",Catálogo!$L$2:$L$648,"*area*",Catálogo!$Q$2:$Q$648,{1,2,3,4,5,6,7,8,9})>0,0),0)<IFERROR(MATCH(TRUE,COUNTIFS(Catálogo!$J$2:$J$648,"*"&$A7&"*",Catálogo!$I$2:$I$648,"<>ausente",Catálogo!$M$2:$M$648,"completa",Catálogo!$L$2:$L$648,"*area*",Catálogo!$Q$2:$Q$648,{1,2,3,4,5,6,7,8,9})>0,0),0)),"; "&LOWER(INDEX(Niveles!$C$2:$C$10,IFERROR(MATCH(TRUE,COUNTIFS(Catálogo!$J$2:$J$648,"*"&$A7&"*",Catálogo!$I$2:$I$648,"<>ausente",Catálogo!$M$2:$M$648,"parcial",Catálogo!$L$2:$L$648,"*area*",Catálogo!$Q$2:$Q$648,{1,2,3,4,5,6,7,8,9})>0,0),0)))&" (parcial)",""),IF(IFERROR(MATCH(TRUE,COUNTIFS(Catálogo!$J$2:$J$648,"*"&$A7&"*",Catálogo!$I$2:$I$648,"<>ausente",Catálogo!$M$2:$M$648,"parcial",Catálogo!$L$2:$L$648,"*area*",Catálogo!$Q$2:$Q$648,{1,2,3,4,5,6,7,8,9})>0,0),0)>0,INDEX(Niveles!$C$2:$C$10,IFERROR(MATCH(TRUE,COUNTIFS(Catálogo!$J$2:$J$648,"*"&$A7&"*",Catálogo!$I$2:$I$648,"<>ausente",Catálogo!$M$2:$M$648,"parcial",Catálogo!$L$2:$L$648,"*area*",Catálogo!$Q$2:$Q$648,{1,2,3,4,5,6,7,8,9})>0,0),0))&" (parcial)","—")) -> — | Q7: =IF(COUNTIFS(Cifras!$A$2:$A$399,$A7,Cifras!$E$2:$E$399,"Sí",Cifras!$F$2:$F$399,"Sí",Cifras!$D$2:$D$399,"distrito")>0,"Distrito",IF(COUNTIFS(Cifras!$A$2:$A$399,$A7,Cifras!$E$2:$E$399,"Sí",Cifras!$F$2:$F$399,"Sí",Cifras!$D$2:$D$399,"comuna")>0,"Comuna",IF(COUNTIFS(Cifras!$A$2:$A$399,$A7,Cifras!$E$2:$E$399,"Sí",Cifras!$F$2:$F$399,"Sí",Cifras!$D$2:$D$399,"partido")>0,"Partido",IF(COUNTIFS(Cifras!$A$2:$A$399,$A7,Cifras!$E$2:$E$399,"Sí",Cifras!$F$2:$F$399,"Sí",Cifras!$D$2:$D$399,"departamento")>0,"Departamento",IF(COUNTIFS(Cifras!$A$2:$A$399,$A7,Cifras!$E$2:$E$399,"Sí",Cifras!$F$2:$F$399,"Sí",Cifras!$D$2:$D$399,"provincia")>0,"Provincia",IF(COUNTIFS(Cifras!$A$2:$A$399,$A7,Cifras!$E$2:$E$399,"Sí",Cifras!$F$2:$F$399,"Sí",Cifras!$D$2:$D$399,"region")>0,"Región",IF(COUNTIFS(Cifras!$A$2:$A$399,$A7,Cifras!$E$2:$E$399,"Sí",Cifras!$F$2:$F$399,"Sí",Cifras!$D$2:$D$399,"pais")>0,"País","—"))))))) -> — | R7: =IF(IFERROR(MATCH(TRUE,COUNTIFS(Catálogo!$J$2:$J$648,"*"&$A7&"*",Catálogo!$I$2:$I$648,"<>ausente",Catálogo!$M$2:$M$648,"completa",Catálogo!$L$2:$L$648,"*area*",Catálogo!$L$2:$L$648,"*sexo*",Catálogo!$Q$2:$Q$648,{1,2,3,4,5,6,7,8,9})>0,0),0)>0,INDEX(Niveles!$C$2:$C$10,IFERROR(MATCH(TRUE,COUNTIFS(Catálogo!$J$2:$J$648,"*"&$A7&"*",Catálogo!$I$2:$I$648,"<>ausente",Catálogo!$M$2:$M$648,"completa",Catálogo!$L$2:$L$648,"*area*",Catálogo!$L$2:$L$648,"*sexo*",Catálogo!$Q$2:$Q$648,{1,2,3,4,5,6,7,8,9})>0,0),0))&IF(AND(IFERROR(MATCH(TRUE,COUNTIFS(Catálogo!$J$2:$J$648,"*"&$A7&"*",Catálogo!$I$2:$I$648,"<>ausente",Catálogo!$M$2:$M$648,"parcial",Catálogo!$L$2:$L$648,"*area*",Catálogo!$L$2:$L$648,"*sexo*",Catálogo!$Q$2:$Q$648,{1,2,3,4,5,6,7,8,9})>0,0),0)>0,IFERROR(MATCH(TRUE,COUNTIFS(Catálogo!$J$2:$J$648,"*"&$A7&"*",Catálogo!$I$2:$I$648,"<>ausente",Catálogo!$M$2:$M$648,"parcial",Catálogo!$L$2:$L$648,"*area*",Catálogo!$L$2:$L$648,"*sexo*",Catálogo!$Q$2:$Q$648,{1,2,3,4,5,6,7,8,9})>0,0),0)<IFERROR(MATCH(TRUE,COUNTIFS(Catálogo!$J$2:$J$648,"*"&$A7&"*",Catálogo!$I$2:$I$648,"<>ausente",Catálogo!$M$2:$M$648,"completa",Catálogo!$L$2:$L$648,"*area*",Catálogo!$L$2:$L$648,"*sexo*",Catálogo!$Q$2:$Q$648,{1,2,3,4,5,6,7,8,9})>0,0),0)),"; "&LOWER(INDEX(Niveles!$C$2:$C$10,IFERROR(MATCH(TRUE,COUNTIFS(Catálogo!$J$2:$J$648,"*"&$A7&"*",Catálogo!$I$2:$I$648,"<>ausente",Catálogo!$M$2:$M$648,"parcial",Catálogo!$L$2:$L$648,"*area*",Catálogo!$L$2:$L$648,"*sexo*",Catálogo!$Q$2:$Q$648,{1,2,3,4,5,6,7,8,9})>0,0),0)))&" (parcial)",""),IF(IFERROR(MATCH(TRUE,COUNTIFS(Catálogo!$J$2:$J$648,"*"&$A7&"*",Catálogo!$I$2:$I$648,"<>ausente",Catálogo!$M$2:$M$648,"parcial",Catálogo!$L$2:$L$648,"*area*",Catálogo!$L$2:$L$648,"*sexo*",Catálogo!$Q$2:$Q$648,{1,2,3,4,5,6,7,8,9})>0,0),0)>0,INDEX(Niveles!$C$2:$C$10,IFERROR(MATCH(TRUE,COUNTIFS(Catálogo!$J$2:$J$648,"*"&$A7&"*",Catálogo!$I$2:$I$648,"<>ausente",Catálogo!$M$2:$M$648,"parcial",Catálogo!$L$2:$L$648,"*area*",Catálogo!$L$2:$L$648,"*sexo*",Catálogo!$Q$2:$Q$648,{1,2,3,4,5,6,7,8,9})>0,0),0))&" (parcial)","—")) -> — | S7: =IF(COUNTIFS(Cifras!$A$2:$A$399,$A7,Cifras!$F$2:$F$399,"Sí",Cifras!$G$2:$G$399,"Sí",Cifras!$D$2:$D$399,"distrito")>0,"Distrito",IF(COUNTIFS(Cifras!$A$2:$A$399,$A7,Cifras!$F$2:$F$399,"Sí",Cifras!$G$2:$G$399,"Sí",Cifras!$D$2:$D$399,"comuna")>0,"Comuna",IF(COUNTIFS(Cifras!$A$2:$A$399,$A7,Cifras!$F$2:$F$399,"Sí",Cifras!$G$2:$G$399,"Sí",Cifras!$D$2:$D$399,"partido")>0,"Partido",IF(COUNTIFS(Cifras!$A$2:$A$399,$A7,Cifras!$F$2:$F$399,"Sí",Cifras!$G$2:$G$399,"Sí",Cifras!$D$2:$D$399,"departamento")>0,"Departamento",IF(COUNTIFS(Cifras!$A$2:$A$399,$A7,Cifras!$F$2:$F$399,"Sí",Cifras!$G$2:$G$399,"Sí",Cifras!$D$2:$D$399,"provincia")>0,"Provincia",IF(COUNTIFS(Cifras!$A$2:$A$399,$A7,Cifras!$F$2:$F$399,"Sí",Cifras!$G$2:$G$399,"Sí",Cifras!$D$2:$D$399,"region")>0,"Región",IF(COUNTIFS(Cifras!$A$2:$A$399,$A7,Cifras!$F$2:$F$399,"Sí",Cifras!$G$2:$G$399,"Sí",Cifras!$D$2:$D$399,"pais")>0,"País","—"))))))) -> — | T7: =IF(IFERROR(MATCH(TRUE,COUNTIFS(Catálogo!$J$2:$J$648,"*"&$A7&"*",Catálogo!$I$2:$I$648,"<>ausente",Catálogo!$M$2:$M$648,"completa",Catálogo!$L$2:$L$648,"*sexo*",Catálogo!$L$2:$L$648,"*edad*",Catálogo!$Q$2:$Q$648,{1,2,3,4,5,6,7,8,9})>0,0),0)>0,INDEX(Niveles!$C$2:$C$10,IFERROR(MATCH(TRUE,COUNTIFS(Catálogo!$J$2:$J$648,"*"&$A7&"*",Catálogo!$I$2:$I$648,"<>ausente",Catálogo!$M$2:$M$648,"completa",Catálogo!$L$2:$L$648,"*sexo*",Catálogo!$L$2:$L$648,"*edad*",Catálogo!$Q$2:$Q$648,{1,2,3,4,5,6,7,8,9})>0,0),0))&IF(AND(IFERROR(MATCH(TRUE,COUNTIFS(Catálogo!$J$2:$J$648,"*"&$A7&"*",Catálogo!$I$2:$I$648,"<>ausente",Catálogo!$M$2:$M$648,"parcial",Catálogo!$L$2:$L$648,"*sexo*",Catálogo!$L$2:$L$648,"*edad*",Catálogo!$Q$2:$Q$648,{1,2,3,4,5,6,7,8,9})>0,0),0)>0,IFERROR(MATCH(TRUE,COUNTIFS(Catálogo!$J$2:$J$648,"*"&$A7&"*",Catálogo!$I$2:$I$648,"<>ausente",Catálogo!$M$2:$M$648,"parcial",Catálogo!$L$2:$L$648,"*sexo*",Catálogo!$L$2:$L$648,"*edad*",Catálogo!$Q$2:$Q$648,{1,2,3,4,5,6,7,8,9})>0,0),0)<IFERROR(MATCH(TRUE,COUNTIFS(Catálogo!$J$2:$J$648,"*"&$A7&"*",Catálogo!$I$2:$I$648,"<>ausente",Catálogo!$M$2:$M$648,"completa",Catálogo!$L$2:$L$648,"*sexo*",Catálogo!$L$2:$L$648,"*edad*",Catálogo!$Q$2:$Q$648,{1,2,3,4,5,6,7,8,9})>0,0),0)),"; "&LOWER(INDEX(Niveles!$C$2:$C$10,IFERROR(MATCH(TRUE,COUNTIFS(Catálogo!$J$2:$J$648,"*"&$A7&"*",Catálogo!$I$2:$I$648,"<>ausente",Catálogo!$M$2:$M$648,"parcial",Catálogo!$L$2:$L$648,"*sexo*",Catálogo!$L$2:$L$648,"*edad*",Catálogo!$Q$2:$Q$648,{1,2,3,4,5,6,7,8,9})>0,0),0)))&" (parcial)",""),IF(IFERROR(MATCH(TRUE,COUNTIFS(Catálogo!$J$2:$J$648,"*"&$A7&"*",Catálogo!$I$2:$I$648,"<>ausente",Catálogo!$M$2:$M$648,"parcial",Catálogo!$L$2:$L$648,"*sexo*",Catálogo!$L$2:$L$648,"*edad*",Catálogo!$Q$2:$Q$648,{1,2,3,4,5,6,7,8,9})>0,0),0)>0,INDEX(Niveles!$C$2:$C$10,IFERROR(MATCH(TRUE,COUNTIFS(Catálogo!$J$2:$J$648,"*"&$A7&"*",Catálogo!$I$2:$I$648,"<>ausente",Catálogo!$M$2:$M$648,"parcial",Catálogo!$L$2:$L$648,"*sexo*",Catálogo!$L$2:$L$648,"*edad*",Catálogo!$Q$2:$Q$648,{1,2,3,4,5,6,7,8,9})>0,0),0))&" (parcial)","—")) -> — | U7: =SUMIFS(Cifras!$J$2:$J$399,Cifras!$A$2:$A$399,$A7) -> 0 | V7: Sin publicación | W7: Transcribir la provincia del Maule (departamento y subdelegación × sexo × edad; copia de Memoria Chilena mc_1843_maule, PDF 72–98). Revisar la población por subdelegación del Repertorio nacional de 1850 (mc_1843_repertorio). | X7: Solo se publicó la provincia del Maule (Memoria Chilena), sin transcribir. Departamento y provincia (totales) desde los sinópticos de 1865 y 1875, que coinciden entre sí.
A8: 1854 | B8: — | D8: =COUNTIFS(Catálogo!$B$2:$B$648,$A8) -> 0 | E8: =COUNTIFS(Catálogo!$B$2:$B$648,$A8,Catálogo!$F$2:$F$648,"cuadro") -> 0 | F8: =COUNTIFS(Catálogo!$B$2:$B$648,$A8,Catálogo!$F$2:$F$648,"bloque") -> 0 | G8: =COUNTIFS(Catálogo!$B$2:$B$648,$A8,Catálogo!$F$2:$F$648,"texto") -> 0 | H8: =COUNTIFS(Catálogo!$B$2:$B$648,$A8,Catálogo!$I$2:$I$648,"verificada") -> 0 | I8: =COUNTIFS(Catálogo!$B$2:$B$648,$A8,Catálogo!$I$2:$I$648,"estimada") -> 0 | J8: =COUNTIFS(Catálogo!$B$2:$B$648,$A8,Catálogo!$I$2:$I$648,"desconocida")+COUNTIFS(Catálogo!$B$2:$B$648,$A8,Catálogo!$I$2:$I$648,"ausente") -> 0 | K8: =COUNTIFS(Catálogo!$B$2:$B$648,$A8,Catálogo!$O$2:$O$648,"transcrito") -> 0 | L8: =SUMIFS(Cifras!$H$2:$H$399,Cifras!$A$2:$A$399,$A8) -> 147 | M8: =IF(COUNTIFS(Cifras!$A$2:$A$399,$A8,Cifras!$D$2:$D$399,"distrito")>0,"Distrito",IF(COUNTIFS(Cifras!$A$2:$A$399,$A8,Cifras!$D$2:$D$399,"comuna")>0,"Comuna",IF(COUNTIFS(Cifras!$A$2:$A$399,$A8,Cifras!$D$2:$D$399,"partido")>0,"Partido",IF(COUNTIFS(Cifras!$A$2:$A$399,$A8,Cifras!$D$2:$D$399,"departamento")>0,"Departamento",IF(COUNTIFS(Cifras!$A$2:$A$399,$A8,Cifras!$D$2:$D$399,"provincia")>0,"Provincia",IF(COUNTIFS(Cifras!$A$2:$A$399,$A8,Cifras!$D$2:$D$399,"region")>0,"Región",IF(COUNTIFS(Cifras!$A$2:$A$399,$A8,Cifras!$D$2:$D$399,"pais")>0,"País","—"))))))) -> Departamento | N8: =IF(IFERROR(MATCH(TRUE,COUNTIFS(Catálogo!$J$2:$J$648,"*"&$A8&"*",Catálogo!$I$2:$I$648,"<>ausente",Catálogo!$M$2:$M$648,"completa",Catálogo!$Q$2:$Q$648,{1,2,3,4,5,6,7,8,9})>0,0),0)>0,INDEX(Niveles!$C$2:$C$10,IFERROR(MATCH(TRUE,COUNTIFS(Catálogo!$J$2:$J$648,"*"&$A8&"*",Catálogo!$I$2:$I$648,"<>ausente",Catálogo!$M$2:$M$648,"completa",Catálogo!$Q$2:$Q$648,{1,2,3,4,5,6,7,8,9})>0,0),0))&IF(AND(IFERROR(MATCH(TRUE,COUNTIFS(Catálogo!$J$2:$J$648,"*"&$A8&"*",Catálogo!$I$2:$I$648,"<>ausente",Catálogo!$M$2:$M$648,"parcial",Catálogo!$Q$2:$Q$648,{1,2,3,4,5,6,7,8,9})>0,0),0)>0,IFERROR(MATCH(TRUE,COUNTIFS(Catálogo!$J$2:$J$648,"*"&$A8&"*",Catálogo!$I$2:$I$648,"<>ausente",Catálogo!$M$2:$M$648,"parcial",Catálogo!$Q$2:$Q$648,{1,2,3,4,5,6,7,8,9})>0,0),0)<IFERROR(MATCH(TRUE,COUNTIFS(Catálogo!$J$2:$J$648,"*"&$A8&"*",Catálogo!$I$2:$I$648,"<>ausente",Catálogo!$M$2:$M$648,"completa",Catálogo!$Q$2:$Q$648,{1,2,3,4,5,6,7,8,9})>0,0),0)),"; "&LOWER(INDEX(Niveles!$C$2:$C$10,IFERROR(MATCH(TRUE,COUNTIFS(Catálogo!$J$2:$J$648,"*"&$A8&"*",Catálogo!$I$2:$I$648,"<>ausente",Catálogo!$M$2:$M$648,"parcial",Catálogo!$Q$2:$Q$648,{1,2,3,4,5,6,7,8,9})>0,0),0)))&" (parcial)",""),IF(IFERROR(MATCH(TRUE,COUNTIFS(Catálogo!$J$2:$J$648,"*"&$A8&"*",Catálogo!$I$2:$I$648,"<>ausente",Catálogo!$M$2:$M$648,"parcial",Catálogo!$Q$2:$Q$648,{1,2,3,4,5,6,7,8,9})>0,0),0)>0,INDEX(Niveles!$C$2:$C$10,IFERROR(MATCH(TRUE,COUNTIFS(Catálogo!$J$2:$J$648,"*"&$A8&"*",Catálogo!$I$2:$I$648,"<>ausente",Catálogo!$M$2:$M$648,"parcial",Catálogo!$Q$2:$Q$648,{1,2,3,4,5,6,7,8,9})>0,0),0))&" (parcial)","—")) -> Departamento | O8: =IF(COUNTIFS(Cifras!$A$2:$A$399,$A8,Cifras!$E$2:$E$399,"Sí",Cifras!$D$2:$D$399,"distrito")>0,"Distrito",IF(COUNTIFS(Cifras!$A$2:$A$399,$A8,Cifras!$E$2:$E$399,"Sí",Cifras!$D$2:$D$399,"comuna")>0,"Comuna",IF(COUNTIFS(Cifras!$A$2:$A$399,$A8,Cifras!$E$2:$E$399,"Sí",Cifras!$D$2:$D$399,"partido")>0,"Partido",IF(COUNTIFS(Cifras!$A$2:$A$399,$A8,Cifras!$E$2:$E$399,"Sí",Cifras!$D$2:$D$399,"departamento")>0,"Departamento",IF(COUNTIFS(Cifras!$A$2:$A$399,$A8,Cifras!$E$2:$E$399,"Sí",Cifras!$D$2:$D$399,"provincia")>0,"Provincia",IF(COUNTIFS(Cifras!$A$2:$A$399,$A8,Cifras!$E$2:$E$399,"Sí",Cifras!$D$2:$D$399,"region")>0,"Región",IF(COUNTIFS(Cifras!$A$2:$A$399,$A8,Cifras!$E$2:$E$399,"Sí",Cifras!$D$2:$D$399,"pais")>0,"País","—"))))))) -> — | P8: =IF(IFERROR(MATCH(TRUE,COUNTIFS(Catálogo!$J$2:$J$648,"*"&$A8&"*",Catálogo!$I$2:$I$648,"<>ausente",Catálogo!$M$2:$M$648,"completa",Catálogo!$L$2:$L$648,"*area*",Catálogo!$Q$2:$Q$648,{1,2,3,4,5,6,7,8,9})>0,0),0)>0,INDEX(Niveles!$C$2:$C$10,IFERROR(MATCH(TRUE,COUNTIFS(Catálogo!$J$2:$J$648,"*"&$A8&"*",Catálogo!$I$2:$I$648,"<>ausente",Catálogo!$M$2:$M$648,"completa",Catálogo!$L$2:$L$648,"*area*",Catálogo!$Q$2:$Q$648,{1,2,3,4,5,6,7,8,9})>0,0),0))&IF(AND(IFERROR(MATCH(TRUE,COUNTIFS(Catálogo!$J$2:$J$648,"*"&$A8&"*",Catálogo!$I$2:$I$648,"<>ausente",Catálogo!$M$2:$M$648,"parcial",Catálogo!$L$2:$L$648,"*area*",Catálogo!$Q$2:$Q$648,{1,2,3,4,5,6,7,8,9})>0,0),0)>0,IFERROR(MATCH(TRUE,COUNTIFS(Catálogo!$J$2:$J$648,"*"&$A8&"*",Catálogo!$I$2:$I$648,"<>ausente",Catálogo!$M$2:$M$648,"parcial",Catálogo!$L$2:$L$648,"*area*",Catálogo!$Q$2:$Q$648,{1,2,3,4,5,6,7,8,9})>0,0),0)<IFERROR(MATCH(TRUE,COUNTIFS(Catálogo!$J$2:$J$648,"*"&$A8&"*",Catálogo!$I$2:$I$648,"<>ausente",Catálogo!$M$2:$M$648,"completa",Catálogo!$L$2:$L$648,"*area*",Catálogo!$Q$2:$Q$648,{1,2,3,4,5,6,7,8,9})>0,0),0)),"; "&LOWER(INDEX(Niveles!$C$2:$C$10,IFERROR(MATCH(TRUE,COUNTIFS(Catálogo!$J$2:$J$648,"*"&$A8&"*",Catálogo!$I$2:$I$648,"<>ausente",Catálogo!$M$2:$M$648,"parcial",Catálogo!$L$2:$L$648,"*area*",Catálogo!$Q$2:$Q$648,{1,2,3,4,5,6,7,8,9})>0,0),0)))&" (parcial)",""),IF(IFERROR(MATCH(TRUE,COUNTIFS(Catálogo!$J$2:$J$648,"*"&$A8&"*",Catálogo!$I$2:$I$648,"<>ausente",Catálogo!$M$2:$M$648,"parcial",Catálogo!$L$2:$L$648,"*area*",Catálogo!$Q$2:$Q$648,{1,2,3,4,5,6,7,8,9})>0,0),0)>0,INDEX(Niveles!$C$2:$C$10,IFERROR(MATCH(TRUE,COUNTIFS(Catálogo!$J$2:$J$648,"*"&$A8&"*",Catálogo!$I$2:$I$648,"<>ausente",Catálogo!$M$2:$M$648,"parcial",Catálogo!$L$2:$L$648,"*area*",Catálogo!$Q$2:$Q$648,{1,2,3,4,5,6,7,8,9})>0,0),0))&" (parcial)","—")) -> — | Q8: =IF(COUNTIFS(Cifras!$A$2:$A$399,$A8,Cifras!$E$2:$E$399,"Sí",Cifras!$F$2:$F$399,"Sí",Cifras!$D$2:$D$399,"distrito")>0,"Distrito",IF(COUNTIFS(Cifras!$A$2:$A$399,$A8,Cifras!$E$2:$E$399,"Sí",Cifras!$F$2:$F$399,"Sí",Cifras!$D$2:$D$399,"comuna")>0,"Comuna",IF(COUNTIFS(Cifras!$A$2:$A$399,$A8,Cifras!$E$2:$E$399,"Sí",Cifras!$F$2:$F$399,"Sí",Cifras!$D$2:$D$399,"partido")>0,"Partido",IF(COUNTIFS(Cifras!$A$2:$A$399,$A8,Cifras!$E$2:$E$399,"Sí",Cifras!$F$2:$F$399,"Sí",Cifras!$D$2:$D$399,"departamento")>0,"Departamento",IF(COUNTIFS(Cifras!$A$2:$A$399,$A8,Cifras!$E$2:$E$399,"Sí",Cifras!$F$2:$F$399,"Sí",Cifras!$D$2:$D$399,"provincia")>0,"Provincia",IF(COUNTIFS(Cifras!$A$2:$A$399,$A8,Cifras!$E$2:$E$399,"Sí",Cifras!$F$2:$F$399,"Sí",Cifras!$D$2:$D$399,"region")>0,"Región",IF(COUNTIFS(Cifras!$A$2:$A$399,$A8,Cifras!$E$2:$E$399,"Sí",Cifras!$F$2:$F$399,"Sí",Cifras!$D$2:$D$399,"pais")>0,"País","—"))))))) -> — | R8: =IF(IFERROR(MATCH(TRUE,COUNTIFS(Catálogo!$J$2:$J$648,"*"&$A8&"*",Catálogo!$I$2:$I$648,"<>ausente",Catálogo!$M$2:$M$648,"completa",Catálogo!$L$2:$L$648,"*area*",Catálogo!$L$2:$L$648,"*sexo*",Catálogo!$Q$2:$Q$648,{1,2,3,4,5,6,7,8,9})>0,0),0)>0,INDEX(Niveles!$C$2:$C$10,IFERROR(MATCH(TRUE,COUNTIFS(Catálogo!$J$2:$J$648,"*"&$A8&"*",Catálogo!$I$2:$I$648,"<>ausente",Catálogo!$M$2:$M$648,"completa",Catálogo!$L$2:$L$648,"*area*",Catálogo!$L$2:$L$648,"*sexo*",Catálogo!$Q$2:$Q$648,{1,2,3,4,5,6,7,8,9})>0,0),0))&IF(AND(IFERROR(MATCH(TRUE,COUNTIFS(Catálogo!$J$2:$J$648,"*"&$A8&"*",Catálogo!$I$2:$I$648,"<>ausente",Catálogo!$M$2:$M$648,"parcial",Catálogo!$L$2:$L$648,"*area*",Catálogo!$L$2:$L$648,"*sexo*",Catálogo!$Q$2:$Q$648,{1,2,3,4,5,6,7,8,9})>0,0),0)>0,IFERROR(MATCH(TRUE,COUNTIFS(Catálogo!$J$2:$J$648,"*"&$A8&"*",Catálogo!$I$2:$I$648,"<>ausente",Catálogo!$M$2:$M$648,"parcial",Catálogo!$L$2:$L$648,"*area*",Catálogo!$L$2:$L$648,"*sexo*",Catálogo!$Q$2:$Q$648,{1,2,3,4,5,6,7,8,9})>0,0),0)<IFERROR(MATCH(TRUE,COUNTIFS(Catálogo!$J$2:$J$648,"*"&$A8&"*",Catálogo!$I$2:$I$648,"<>ausente",Catálogo!$M$2:$M$648,"completa",Catálogo!$L$2:$L$648,"*area*",Catálogo!$L$2:$L$648,"*sexo*",Catálogo!$Q$2:$Q$648,{1,2,3,4,5,6,7,8,9})>0,0),0)),"; "&LOWER(INDEX(Niveles!$C$2:$C$10,IFERROR(MATCH(TRUE,COUNTIFS(Catálogo!$J$2:$J$648,"*"&$A8&"*",Catálogo!$I$2:$I$648,"<>ausente",Catálogo!$M$2:$M$648,"parcial",Catálogo!$L$2:$L$648,"*area*",Catálogo!$L$2:$L$648,"*sexo*",Catálogo!$Q$2:$Q$648,{1,2,3,4,5,6,7,8,9})>0,0),0)))&" (parcial)",""),IF(IFERROR(MATCH(TRUE,COUNTIFS(Catálogo!$J$2:$J$648,"*"&$A8&"*",Catálogo!$I$2:$I$648,"<>ausente",Catálogo!$M$2:$M$648,"parcial",Catálogo!$L$2:$L$648,"*area*",Catálogo!$L$2:$L$648,"*sexo*",Catálogo!$Q$2:$Q$648,{1,2,3,4,5,6,7,8,9})>0,0),0)>0,INDEX(Niveles!$C$2:$C$10,IFERROR(MATCH(TRUE,COUNTIFS(Catálogo!$J$2:$J$648,"*"&$A8&"*",Catálogo!$I$2:$I$648,"<>ausente",Catálogo!$M$2:$M$648,"parcial",Catálogo!$L$2:$L$648,"*area*",Catálogo!$L$2:$L$648,"*sexo*",Catálogo!$Q$2:$Q$648,{1,2,3,4,5,6,7,8,9})>0,0),0))&" (parcial)","—")) -> — | S8: =IF(COUNTIFS(Cifras!$A$2:$A$399,$A8,Cifras!$F$2:$F$399,"Sí",Cifras!$G$2:$G$399,"Sí",Cifras!$D$2:$D$399,"distrito")>0,"Distrito",IF(COUNTIFS(Cifras!$A$2:$A$399,$A8,Cifras!$F$2:$F$399,"Sí",Cifras!$G$2:$G$399,"Sí",Cifras!$D$2:$D$399,"comuna")>0,"Comuna",IF(COUNTIFS(Cifras!$A$2:$A$399,$A8,Cifras!$F$2:$F$399,"Sí",Cifras!$G$2:$G$399,"Sí",Cifras!$D$2:$D$399,"partido")>0,"Partido",IF(COUNTIFS(Cifras!$A$2:$A$399,$A8,Cifras!$F$2:$F$399,"Sí",Cifras!$G$2:$G$399,"Sí",Cifras!$D$2:$D$399,"departamento")>0,"Departamento",IF(COUNTIFS(Cifras!$A$2:$A$399,$A8,Cifras!$F$2:$F$399,"Sí",Cifras!$G$2:$G$399,"Sí",Cifras!$D$2:$D$399,"provincia")>0,"Provincia",IF(COUNTIFS(Cifras!$A$2:$A$399,$A8,Cifras!$F$2:$F$399,"Sí",Cifras!$G$2:$G$399,"Sí",Cifras!$D$2:$D$399,"region")>0,"Región",IF(COUNTIFS(Cifras!$A$2:$A$399,$A8,Cifras!$F$2:$F$399,"Sí",Cifras!$G$2:$G$399,"Sí",Cifras!$D$2:$D$399,"pais")>0,"País","—"))))))) -> — | T8: =IF(IFERROR(MATCH(TRUE,COUNTIFS(Catálogo!$J$2:$J$648,"*"&$A8&"*",Catálogo!$I$2:$I$648,"<>ausente",Catálogo!$M$2:$M$648,"completa",Catálogo!$L$2:$L$648,"*sexo*",Catálogo!$L$2:$L$648,"*edad*",Catálogo!$Q$2:$Q$648,{1,2,3,4,5,6,7,8,9})>0,0),0)>0,INDEX(Niveles!$C$2:$C$10,IFERROR(MATCH(TRUE,COUNTIFS(Catálogo!$J$2:$J$648,"*"&$A8&"*",Catálogo!$I$2:$I$648,"<>ausente",Catálogo!$M$2:$M$648,"completa",Catálogo!$L$2:$L$648,"*sexo*",Catálogo!$L$2:$L$648,"*edad*",Catálogo!$Q$2:$Q$648,{1,2,3,4,5,6,7,8,9})>0,0),0))&IF(AND(IFERROR(MATCH(TRUE,COUNTIFS(Catálogo!$J$2:$J$648,"*"&$A8&"*",Catálogo!$I$2:$I$648,"<>ausente",Catálogo!$M$2:$M$648,"parcial",Catálogo!$L$2:$L$648,"*sexo*",Catálogo!$L$2:$L$648,"*edad*",Catálogo!$Q$2:$Q$648,{1,2,3,4,5,6,7,8,9})>0,0),0)>0,IFERROR(MATCH(TRUE,COUNTIFS(Catálogo!$J$2:$J$648,"*"&$A8&"*",Catálogo!$I$2:$I$648,"<>ausente",Catálogo!$M$2:$M$648,"parcial",Catálogo!$L$2:$L$648,"*sexo*",Catálogo!$L$2:$L$648,"*edad*",Catálogo!$Q$2:$Q$648,{1,2,3,4,5,6,7,8,9})>0,0),0)<IFERROR(MATCH(TRUE,COUNTIFS(Catálogo!$J$2:$J$648,"*"&$A8&"*",Catálogo!$I$2:$I$648,"<>ausente",Catálogo!$M$2:$M$648,"completa",Catálogo!$L$2:$L$648,"*sexo*",Catálogo!$L$2:$L$648,"*edad*",Catálogo!$Q$2:$Q$648,{1,2,3,4,5,6,7,8,9})>0,0),0)),"; "&LOWER(INDEX(Niveles!$C$2:$C$10,IFERROR(MATCH(TRUE,COUNTIFS(Catálogo!$J$2:$J$648,"*"&$A8&"*",Catálogo!$I$2:$I$648,"<>ausente",Catálogo!$M$2:$M$648,"parcial",Catálogo!$L$2:$L$648,"*sexo*",Catálogo!$L$2:$L$648,"*edad*",Catálogo!$Q$2:$Q$648,{1,2,3,4,5,6,7,8,9})>0,0),0)))&" (parcial)",""),IF(IFERROR(MATCH(TRUE,COUNTIFS(Catálogo!$J$2:$J$648,"*"&$A8&"*",Catálogo!$I$2:$I$648,"<>ausente",Catálogo!$M$2:$M$648,"parcial",Catálogo!$L$2:$L$648,"*sexo*",Catálogo!$L$2:$L$648,"*edad*",Catálogo!$Q$2:$Q$648,{1,2,3,4,5,6,7,8,9})>0,0),0)>0,INDEX(Niveles!$C$2:$C$10,IFERROR(MATCH(TRUE,COUNTIFS(Catálogo!$J$2:$J$648,"*"&$A8&"*",Catálogo!$I$2:$I$648,"<>ausente",Catálogo!$M$2:$M$648,"parcial",Catálogo!$L$2:$L$648,"*sexo*",Catálogo!$L$2:$L$648,"*edad*",Catálogo!$Q$2:$Q$648,{1,2,3,4,5,6,7,8,9})>0,0),0))&" (parcial)","—")) -> — | U8: =SUMIFS(Cifras!$J$2:$J$399,Cifras!$A$2:$A$399,$A8) -> 0 | V8: Sin publicación | W8: Opcional: contrastar con el resumen general de 1907 (PDF 1222). Buscar un ejemplar digitalizado. | X8: Sin publicación digitalizada. Departamento y provincia (totales) desde los sinópticos de 1865 y 1875, que coinciden entre sí.
A9: 1865 | B9: pub_1865 | C9: 425 | D9: =COUNTIFS(Catálogo!$B$2:$B$648,$A9) -> 32 | E9: =COUNTIFS(Catálogo!$B$2:$B$648,$A9,Catálogo!$F$2:$F$648,"cuadro") -> 15 | F9: =COUNTIFS(Catálogo!$B$2:$B$648,$A9,Catálogo!$F$2:$F$648,"bloque") -> 14 | G9: =COUNTIFS(Catálogo!$B$2:$B$648,$A9,Catálogo!$F$2:$F$648,"texto") -> 3 | H9: =COUNTIFS(Catálogo!$B$2:$B$648,$A9,Catálogo!$I$2:$I$648,"verificada") -> 15 | I9: =COUNTIFS(Catálogo!$B$2:$B$648,$A9,Catálogo!$I$2:$I$648,"estimada") -> 15 | J9: =COUNTIFS(Catálogo!$B$2:$B$648,$A9,Catálogo!$I$2:$I$648,"desconocida")+COUNTIFS(Catálogo!$B$2:$B$648,$A9,Catálogo!$I$2:$I$648,"ausente") -> 2 | K9: =COUNTIFS(Catálogo!$B$2:$B$648,$A9,Catálogo!$O$2:$O$648,"transcrito") -> 3 | L9: =SUMIFS(Cifras!$H$2:$H$399,Cifras!$A$2:$A$399,$A9) -> 1887 | M9: =IF(COUNTIFS(Cifras!$A$2:$A$399,$A9,Cifras!$D$2:$D$399,"distrito")>0,"Distrito",IF(COUNTIFS(Cifras!$A$2:$A$399,$A9,Cifras!$D$2:$D$399,"comuna")>0,"Comuna",IF(COUNTIFS(Cifras!$A$2:$A$399,$A9,Cifras!$D$2:$D$399,"partido")>0,"Partido",IF(COUNTIFS(Cifras!$A$2:$A$399,$A9,Cifras!$D$2:$D$399,"departamento")>0,"Departamento",IF(COUNTIFS(Cifras!$A$2:$A$399,$A9,Cifras!$D$2:$D$399,"provincia")>0,"Provincia",IF(COUNTIFS(Cifras!$A$2:$A$399,$A9,Cifras!$D$2:$D$399,"region")>0,"Región",IF(COUNTIFS(Cifras!$A$2:$A$399,$A9,Cifras!$D$2:$D$399,"pais")>0,"País","—"))))))) -> Departamento | N9: =IF(IFERROR(MATCH(TRUE,COUNTIFS(Catálogo!$J$2:$J$648,"*"&$A9&"*",Catálogo!$I$2:$I$648,"<>ausente",Catálogo!$M$2:$M$648,"completa",Catálogo!$Q$2:$Q$648,{1,2,3,4,5,6,7,8,9})>0,0),0)>0,INDEX(Niveles!$C$2:$C$10,IFERROR(MATCH(TRUE,COUNTIFS(Catálogo!$J$2:$J$648,"*"&$A9&"*",Catálogo!$I$2:$I$648,"<>ausente",Catálogo!$M$2:$M$648,"completa",Catálogo!$Q$2:$Q$648,{1,2,3,4,5,6,7,8,9})>0,0),0))&IF(AND(IFERROR(MATCH(TRUE,COUNTIFS(Catálogo!$J$2:$J$648,"*"&$A9&"*",Catálogo!$I$2:$I$648,"<>ausente",Catálogo!$M$2:$M$648,"parcial",Catálogo!$Q$2:$Q$648,{1,2,3,4,5,6,7,8,9})>0,0),0)>0,IFERROR(MATCH(TRUE,COUNTIFS(Catálogo!$J$2:$J$648,"*"&$A9&"*",Catálogo!$I$2:$I$648,"<>ausente",Catálogo!$M$2:$M$648,"parcial",Catálogo!$Q$2:$Q$648,{1,2,3,4,5,6,7,8,9})>0,0),0)<IFERROR(MATCH(TRUE,COUNTIFS(Catálogo!$J$2:$J$648,"*"&$A9&"*",Catálogo!$I$2:$I$648,"<>ausente",Catálogo!$M$2:$M$648,"completa",Catálogo!$Q$2:$Q$648,{1,2,3,4,5,6,7,8,9})>0,0),0)),"; "&LOWER(INDEX(Niveles!$C$2:$C$10,IFERROR(MATCH(TRUE,COUNTIFS(Catálogo!$J$2:$J$648,"*"&$A9&"*",Catálogo!$I$2:$I$648,"<>ausente",Catálogo!$M$2:$M$648,"parcial",Catálogo!$Q$2:$Q$648,{1,2,3,4,5,6,7,8,9})>0,0),0)))&" (parcial)",""),IF(IFERROR(MATCH(TRUE,COUNTIFS(Catálogo!$J$2:$J$648,"*"&$A9&"*",Catálogo!$I$2:$I$648,"<>ausente",Catálogo!$M$2:$M$648,"parcial",Catálogo!$Q$2:$Q$648,{1,2,3,4,5,6,7,8,9})>0,0),0)>0,INDEX(Niveles!$C$2:$C$10,IFERROR(MATCH(TRUE,COUNTIFS(Catálogo!$J$2:$J$648,"*"&$A9&"*",Catálogo!$I$2:$I$648,"<>ausente",Catálogo!$M$2:$M$648,"parcial",Catálogo!$Q$2:$Q$648,{1,2,3,4,5,6,7,8,9})>0,0),0))&" (parcial)","—")) -> Distrito | O9: =IF(COUNTIFS(Cifras!$A$2:$A$399,$A9,Cifras!$E$2:$E$399,"Sí",Cifras!$D$2:$D$399,"distrito")>0,"Distrito",IF(COUNTIFS(Cifras!$A$2:$A$399,$A9,Cifras!$E$2:$E$399,"Sí",Cifras!$D$2:$D$399,"comuna")>0,"Comuna",IF(COUNTIFS(Cifras!$A$2:$A$399,$A9,Cifras!$E$2:$E$399,"Sí",Cifras!$D$2:$D$399,"partido")>0,"Partido",IF(COUNTIFS(Cifras!$A$2:$A$399,$A9,Cifras!$E$2:$E$399,"Sí",Cifras!$D$2:$D$399,"departamento")>0,"Departamento",IF(COUNTIFS(Cifras!$A$2:$A$399,$A9,Cifras!$E$2:$E$399,"Sí",Cifras!$D$2:$D$399,"provincia")>0,"Provincia",IF(COUNTIFS(Cifras!$A$2:$A$399,$A9,Cifras!$E$2:$E$399,"Sí",Cifras!$D$2:$D$399,"region")>0,"Región",IF(COUNTIFS(Cifras!$A$2:$A$399,$A9,Cifras!$E$2:$E$399,"Sí",Cifras!$D$2:$D$399,"pais")>0,"País","—"))))))) -> Provincia | P9: =IF(IFERROR(MATCH(TRUE,COUNTIFS(Catálogo!$J$2:$J$648,"*"&$A9&"*",Catálogo!$I$2:$I$648,"<>ausente",Catálogo!$M$2:$M$648,"completa",Catálogo!$L$2:$L$648,"*area*",Catálogo!$Q$2:$Q$648,{1,2,3,4,5,6,7,8,9})>0,0),0)>0,INDEX(Niveles!$C$2:$C$10,IFERROR(MATCH(TRUE,COUNTIFS(Catálogo!$J$2:$J$648,"*"&$A9&"*",Catálogo!$I$2:$I$648,"<>ausente",Catálogo!$M$2:$M$648,"completa",Catálogo!$L$2:$L$648,"*area*",Catálogo!$Q$2:$Q$648,{1,2,3,4,5,6,7,8,9})>0,0),0))&IF(AND(IFERROR(MATCH(TRUE,COUNTIFS(Catálogo!$J$2:$J$648,"*"&$A9&"*",Catálogo!$I$2:$I$648,"<>ausente",Catálogo!$M$2:$M$648,"parcial",Catálogo!$L$2:$L$648,"*area*",Catálogo!$Q$2:$Q$648,{1,2,3,4,5,6,7,8,9})>0,0),0)>0,IFERROR(MATCH(TRUE,COUNTIFS(Catálogo!$J$2:$J$648,"*"&$A9&"*",Catálogo!$I$2:$I$648,"<>ausente",Catálogo!$M$2:$M$648,"parcial",Catálogo!$L$2:$L$648,"*area*",Catálogo!$Q$2:$Q$648,{1,2,3,4,5,6,7,8,9})>0,0),0)<IFERROR(MATCH(TRUE,COUNTIFS(Catálogo!$J$2:$J$648,"*"&$A9&"*",Catálogo!$I$2:$I$648,"<>ausente",Catálogo!$M$2:$M$648,"completa",Catálogo!$L$2:$L$648,"*area*",Catálogo!$Q$2:$Q$648,{1,2,3,4,5,6,7,8,9})>0,0),0)),"; "&LOWER(INDEX(Niveles!$C$2:$C$10,IFERROR(MATCH(TRUE,COUNTIFS(Catálogo!$J$2:$J$648,"*"&$A9&"*",Catálogo!$I$2:$I$648,"<>ausente",Catálogo!$M$2:$M$648,"parcial",Catálogo!$L$2:$L$648,"*area*",Catálogo!$Q$2:$Q$648,{1,2,3,4,5,6,7,8,9})>0,0),0)))&" (parcial)",""),IF(IFERROR(MATCH(TRUE,COUNTIFS(Catálogo!$J$2:$J$648,"*"&$A9&"*",Catálogo!$I$2:$I$648,"<>ausente",Catálogo!$M$2:$M$648,"parcial",Catálogo!$L$2:$L$648,"*area*",Catálogo!$Q$2:$Q$648,{1,2,3,4,5,6,7,8,9})>0,0),0)>0,INDEX(Niveles!$C$2:$C$10,IFERROR(MATCH(TRUE,COUNTIFS(Catálogo!$J$2:$J$648,"*"&$A9&"*",Catálogo!$I$2:$I$648,"<>ausente",Catálogo!$M$2:$M$648,"parcial",Catálogo!$L$2:$L$648,"*area*",Catálogo!$Q$2:$Q$648,{1,2,3,4,5,6,7,8,9})>0,0),0))&" (parcial)","—")) -> Provincia | Q9: =IF(COUNTIFS(Cifras!$A$2:$A$399,$A9,Cifras!$E$2:$E$399,"Sí",Cifras!$F$2:$F$399,"Sí",Cifras!$D$2:$D$399,"distrito")>0,"Distrito",IF(COUNTIFS(Cifras!$A$2:$A$399,$A9,Cifras!$E$2:$E$399,"Sí",Cifras!$F$2:$F$399,"Sí",Cifras!$D$2:$D$399,"comuna")>0,"Comuna",IF(COUNTIFS(Cifras!$A$2:$A$399,$A9,Cifras!$E$2:$E$399,"Sí",Cifras!$F$2:$F$399,"Sí",Cifras!$D$2:$D$399,"partido")>0,"Partido",IF(COUNTIFS(Cifras!$A$2:$A$399,$A9,Cifras!$E$2:$E$399,"Sí",Cifras!$F$2:$F$399,"Sí",Cifras!$D$2:$D$399,"departamento")>0,"Departamento",IF(COUNTIFS(Cifras!$A$2:$A$399,$A9,Cifras!$E$2:$E$399,"Sí",Cifras!$F$2:$F$399,"Sí",Cifras!$D$2:$D$399,"provincia")>0,"Provincia",IF(COUNTIFS(Cifras!$A$2:$A$399,$A9,Cifras!$E$2:$E$399,"Sí",Cifras!$F$2:$F$399,"Sí",Cifras!$D$2:$D$399,"region")>0,"Región",IF(COUNTIFS(Cifras!$A$2:$A$399,$A9,Cifras!$E$2:$E$399,"Sí",Cifras!$F$2:$F$399,"Sí",Cifras!$D$2:$D$399,"pais")>0,"País","—"))))))) -> — | R9: =IF(IFERROR(MATCH(TRUE,COUNTIFS(Catálogo!$J$2:$J$648,"*"&$A9&"*",Catálogo!$I$2:$I$648,"<>ausente",Catálogo!$M$2:$M$648,"completa",Catálogo!$L$2:$L$648,"*area*",Catálogo!$L$2:$L$648,"*sexo*",Catálogo!$Q$2:$Q$648,{1,2,3,4,5,6,7,8,9})>0,0),0)>0,INDEX(Niveles!$C$2:$C$10,IFERROR(MATCH(TRUE,COUNTIFS(Catálogo!$J$2:$J$648,"*"&$A9&"*",Catálogo!$I$2:$I$648,"<>ausente",Catálogo!$M$2:$M$648,"completa",Catálogo!$L$2:$L$648,"*area*",Catálogo!$L$2:$L$648,"*sexo*",Catálogo!$Q$2:$Q$648,{1,2,3,4,5,6,7,8,9})>0,0),0))&IF(AND(IFERROR(MATCH(TRUE,COUNTIFS(Catálogo!$J$2:$J$648,"*"&$A9&"*",Catálogo!$I$2:$I$648,"<>ausente",Catálogo!$M$2:$M$648,"parcial",Catálogo!$L$2:$L$648,"*area*",Catálogo!$L$2:$L$648,"*sexo*",Catálogo!$Q$2:$Q$648,{1,2,3,4,5,6,7,8,9})>0,0),0)>0,IFERROR(MATCH(TRUE,COUNTIFS(Catálogo!$J$2:$J$648,"*"&$A9&"*",Catálogo!$I$2:$I$648,"<>ausente",Catálogo!$M$2:$M$648,"parcial",Catálogo!$L$2:$L$648,"*area*",Catálogo!$L$2:$L$648,"*sexo*",Catálogo!$Q$2:$Q$648,{1,2,3,4,5,6,7,8,9})>0,0),0)<IFERROR(MATCH(TRUE,COUNTIFS(Catálogo!$J$2:$J$648,"*"&$A9&"*",Catálogo!$I$2:$I$648,"<>ausente",Catálogo!$M$2:$M$648,"completa",Catálogo!$L$2:$L$648,"*area*",Catálogo!$L$2:$L$648,"*sexo*",Catálogo!$Q$2:$Q$648,{1,2,3,4,5,6,7,8,9})>0,0),0)),"; "&LOWER(INDEX(Niveles!$C$2:$C$10,IFERROR(MATCH(TRUE,COUNTIFS(Catálogo!$J$2:$J$648,"*"&$A9&"*",Catálogo!$I$2:$I$648,"<>ausente",Catálogo!$M$2:$M$648,"parcial",Catálogo!$L$2:$L$648,"*area*",Catálogo!$L$2:$L$648,"*sexo*",Catálogo!$Q$2:$Q$648,{1,2,3,4,5,6,7,8,9})>0,0),0)))&" (parcial)",""),IF(IFERROR(MATCH(TRUE,COUNTIFS(Catálogo!$J$2:$J$648,"*"&$A9&"*",Catálogo!$I$2:$I$648,"<>ausente",Catálogo!$M$2:$M$648,"parcial",Catálogo!$L$2:$L$648,"*area*",Catálogo!$L$2:$L$648,"*sexo*",Catálogo!$Q$2:$Q$648,{1,2,3,4,5,6,7,8,9})>0,0),0)>0,INDEX(Niveles!$C$2:$C$10,IFERROR(MATCH(TRUE,COUNTIFS(Catálogo!$J$2:$J$648,"*"&$A9&"*",Catálogo!$I$2:$I$648,"<>ausente",Catálogo!$M$2:$M$648,"parcial",Catálogo!$L$2:$L$648,"*area*",Catálogo!$L$2:$L$648,"*sexo*",Catálogo!$Q$2:$Q$648,{1,2,3,4,5,6,7,8,9})>0,0),0))&" (parcial)","—")) -> — | S9: =IF(COUNTIFS(Cifras!$A$2:$A$399,$A9,Cifras!$F$2:$F$399,"Sí",Cifras!$G$2:$G$399,"Sí",Cifras!$D$2:$D$399,"distrito")>0,"Distrito",IF(COUNTIFS(Cifras!$A$2:$A$399,$A9,Cifras!$F$2:$F$399,"Sí",Cifras!$G$2:$G$399,"Sí",Cifras!$D$2:$D$399,"comuna")>0,"Comuna",IF(COUNTIFS(Cifras!$A$2:$A$399,$A9,Cifras!$F$2:$F$399,"Sí",Cifras!$G$2:$G$399,"Sí",Cifras!$D$2:$D$399,"partido")>0,"Partido",IF(COUNTIFS(Cifras!$A$2:$A$399,$A9,Cifras!$F$2:$F$399,"Sí",Cifras!$G$2:$G$399,"Sí",Cifras!$D$2:$D$399,"departamento")>0,"Departamento",IF(COUNTIFS(Cifras!$A$2:$A$399,$A9,Cifras!$F$2:$F$399,"Sí",Cifras!$G$2:$G$399,"Sí",Cifras!$D$2:$D$399,"provincia")>0,"Provincia",IF(COUNTIFS(Cifras!$A$2:$A$399,$A9,Cifras!$F$2:$F$399,"Sí",Cifras!$G$2:$G$399,"Sí",Cifras!$D$2:$D$399,"region")>0,"Región",IF(COUNTIFS(Cifras!$A$2:$A$399,$A9,Cifras!$F$2:$F$399,"Sí",Cifras!$G$2:$G$399,"Sí",Cifras!$D$2:$D$399,"pais")>0,"País","—"))))))) -> Departamento | T9: =IF(IFERROR(MATCH(TRUE,COUNTIFS(Catálogo!$J$2:$J$648,"*"&$A9&"*",Catálogo!$I$2:$I$648,"<>ausente",Catálogo!$M$2:$M$648,"completa",Catálogo!$L$2:$L$648,"*sexo*",Catálogo!$L$2:$L$648,"*edad*",Catálogo!$Q$2:$Q$648,{1,2,3,4,5,6,7,8,9})>0,0),0)>0,INDEX(Niveles!$C$2:$C$10,IFERROR(MATCH(TRUE,COUNTIFS(Catálogo!$J$2:$J$648,"*"&$A9&"*",Catálogo!$I$2:$I$648,"<>ausente",Catálogo!$M$2:$M$648,"completa",Catálogo!$L$2:$L$648,"*sexo*",Catálogo!$L$2:$L$648,"*edad*",Catálogo!$Q$2:$Q$648,{1,2,3,4,5,6,7,8,9})>0,0),0))&IF(AND(IFERROR(MATCH(TRUE,COUNTIFS(Catálogo!$J$2:$J$648,"*"&$A9&"*",Catálogo!$I$2:$I$648,"<>ausente",Catálogo!$M$2:$M$648,"parcial",Catálogo!$L$2:$L$648,"*sexo*",Catálogo!$L$2:$L$648,"*edad*",Catálogo!$Q$2:$Q$648,{1,2,3,4,5,6,7,8,9})>0,0),0)>0,IFERROR(MATCH(TRUE,COUNTIFS(Catálogo!$J$2:$J$648,"*"&$A9&"*",Catálogo!$I$2:$I$648,"<>ausente",Catálogo!$M$2:$M$648,"parcial",Catálogo!$L$2:$L$648,"*sexo*",Catálogo!$L$2:$L$648,"*edad*",Catálogo!$Q$2:$Q$648,{1,2,3,4,5,6,7,8,9})>0,0),0)<IFERROR(MATCH(TRUE,COUNTIFS(Catálogo!$J$2:$J$648,"*"&$A9&"*",Catálogo!$I$2:$I$648,"<>ausente",Catálogo!$M$2:$M$648,"completa",Catálogo!$L$2:$L$648,"*sexo*",Catálogo!$L$2:$L$648,"*edad*",Catálogo!$Q$2:$Q$648,{1,2,3,4,5,6,7,8,9})>0,0),0)),"; "&LOWER(INDEX(Niveles!$C$2:$C$10,IFERROR(MATCH(TRUE,COUNTIFS(Catálogo!$J$2:$J$648,"*"&$A9&"*",Catálogo!$I$2:$I$648,"<>ausente",Catálogo!$M$2:$M$648,"parcial",Catálogo!$L$2:$L$648,"*sexo*",Catálogo!$L$2:$L$648,"*edad*",Catálogo!$Q$2:$Q$648,{1,2,3,4,5,6,7,8,9})>0,0),0)))&" (parcial)",""),IF(IFERROR(MATCH(TRUE,COUNTIFS(Catálogo!$J$2:$J$648,"*"&$A9&"*",Catálogo!$I$2:$I$648,"<>ausente",Catálogo!$M$2:$M$648,"parcial",Catálogo!$L$2:$L$648,"*sexo*",Catálogo!$L$2:$L$648,"*edad*",Catálogo!$Q$2:$Q$648,{1,2,3,4,5,6,7,8,9})>0,0),0)>0,INDEX(Niveles!$C$2:$C$10,IFERROR(MATCH(TRUE,COUNTIFS(Catálogo!$J$2:$J$648,"*"&$A9&"*",Catálogo!$I$2:$I$648,"<>ausente",Catálogo!$M$2:$M$648,"parcial",Catálogo!$L$2:$L$648,"*sexo*",Catálogo!$L$2:$L$648,"*edad*",Catálogo!$Q$2:$Q$648,{1,2,3,4,5,6,7,8,9})>0,0),0))&" (parcial)","—")) -> Distrito | U9: =SUMIFS(Cifras!$J$2:$J$399,Cifras!$A$2:$A$399,$A9) -> 6 | V9: Serie desde otros censos | W9: Parroquia × sexo × edad (pág. 386, PDF 419) y subdelegación/distrito × sexo × edad desde los bloques provinciales (p. ej. Coquimbo, PDF 302). | X9: Departamento × sexo × edad en 6 tramos (pág. 352) y provincia × sexo × edad (pág. 360) desde la propia publicación; valida 1952 C5 y C6. Departamento (total) desde su sinóptico, validado con el de 1875; provincia × área (1952 C9). Escaneo malo: cifras dudosas fijadas con sumas por fila y por provincia y revisadas con la copia de Memoria Chilena (4 corregidas en Itata y Linares). Erratas: Caupolicán 16–25 hombres y Quinchao hasta 7 hombres.
A10: 1875 | B10: pub_1875 | C10: 689 | D10: =COUNTIFS(Catálogo!$B$2:$B$648,$A10) -> 33 | E10: =COUNTIFS(Catálogo!$B$2:$B$648,$A10,Catálogo!$F$2:$F$648,"cuadro") -> 13 | F10: =COUNTIFS(Catálogo!$B$2:$B$648,$A10,Catálogo!$F$2:$F$648,"bloque") -> 19 | G10: =COUNTIFS(Catálogo!$B$2:$B$648,$A10,Catálogo!$F$2:$F$648,"texto") -> 1 | H10: =COUNTIFS(Catálogo!$B$2:$B$648,$A10,Catálogo!$I$2:$I$648,"verificada") -> 3 | I10: =COUNTIFS(Catálogo!$B$2:$B$648,$A10,Catálogo!$I$2:$I$648,"estimada") -> 29 | J10: =COUNTIFS(Catálogo!$B$2:$B$648,$A10,Catálogo!$I$2:$I$648,"desconocida")+COUNTIFS(Catálogo!$B$2:$B$648,$A10,Catálogo!$I$2:$I$648,"ausente") -> 1 | K10: =COUNTIFS(Catálogo!$B$2:$B$648,$A10,Catálogo!$O$2:$O$648,"transcrito") -> 3 | L10: =SUMIFS(Cifras!$H$2:$H$399,Cifras!$A$2:$A$399,$A10) -> 2174 | M10: =IF(COUNTIFS(Cifras!$A$2:$A$399,$A10,Cifras!$D$2:$D$399,"distrito")>0,"Distrito",IF(COUNTIFS(Cifras!$A$2:$A$399,$A10,Cifras!$D$2:$D$399,"comuna")>0,"Comuna",IF(COUNTIFS(Cifras!$A$2:$A$399,$A10,Cifras!$D$2:$D$399,"partido")>0,"Partido",IF(COUNTIFS(Cifras!$A$2:$A$399,$A10,Cifras!$D$2:$D$399,"departamento")>0,"Departamento",IF(COUNTIFS(Cifras!$A$2:$A$399,$A10,Cifras!$D$2:$D$399,"provincia")>0,"Provincia",IF(COUNTIFS(Cifras!$A$2:$A$399,$A10,Cifras!$D$2:$D$399,"region")>0,"Región",IF(COUNTIFS(Cifras!$A$2:$A$399,$A10,Cifras!$D$2:$D$399,"pais")>0,"País","—"))))))) -> Departamento | N10: =IF(IFERROR(MATCH(TRUE,COUNTIFS(Catálogo!$J$2:$J$648,"*"&$A10&"*",Catálogo!$I$2:$I$648,"<>ausente",Catálogo!$M$2:$M$648,"completa",Catálogo!$Q$2:$Q$648,{1,2,3,4,5,6,7,8,9})>0,0),0)>0,INDEX(Niveles!$C$2:$C$10,IFERROR(MATCH(TRUE,COUNTIFS(Catálogo!$J$2:$J$648,"*"&$A10&"*",Catálogo!$I$2:$I$648,"<>ausente",Catálogo!$M$2:$M$648,"completa",Catálogo!$Q$2:$Q$648,{1,2,3,4,5,6,7,8,9})>0,0),0))&IF(AND(IFERROR(MATCH(TRUE,COUNTIFS(Catálogo!$J$2:$J$648,"*"&$A10&"*",Catálogo!$I$2:$I$648,"<>ausente",Catálogo!$M$2:$M$648,"parcial",Catálogo!$Q$2:$Q$648,{1,2,3,4,5,6,7,8,9})>0,0),0)>0,IFERROR(MATCH(TRUE,COUNTIFS(Catálogo!$J$2:$J$648,"*"&$A10&"*",Catálogo!$I$2:$I$648,"<>ausente",Catálogo!$M$2:$M$648,"parcial",Catálogo!$Q$2:$Q$648,{1,2,3,4,5,6,7,8,9})>0,0),0)<IFERROR(MATCH(TRUE,COUNTIFS(Catálogo!$J$2:$J$648,"*"&$A10&"*",Catálogo!$I$2:$I$648,"<>ausente",Catálogo!$M$2:$M$648,"completa",Catálogo!$Q$2:$Q$648,{1,2,3,4,5,6,7,8,9})>0,0),0)),"; "&LOWER(INDEX(Niveles!$C$2:$C$10,IFERROR(MATCH(TRUE,COUNTIFS(Catálogo!$J$2:$J$648,"*"&$A10&"*",Catálogo!$I$2:$I$648,"<>ausente",Catálogo!$M$2:$M$648,"parcial",Catálogo!$Q$2:$Q$648,{1,2,3,4,5,6,7,8,9})>0,0),0)))&" (parcial)",""),IF(IFERROR(MATCH(TRUE,COUNTIFS(Catálogo!$J$2:$J$648,"*"&$A10&"*",Catálogo!$I$2:$I$648,"<>ausente",Catálogo!$M$2:$M$648,"parcial",Catálogo!$Q$2:$Q$648,{1,2,3,4,5,6,7,8,9})>0,0),0)>0,INDEX(Niveles!$C$2:$C$10,IFERROR(MATCH(TRUE,COUNTIFS(Catálogo!$J$2:$J$648,"*"&$A10&"*",Catálogo!$I$2:$I$648,"<>ausente",Catálogo!$M$2:$M$648,"parcial",Catálogo!$Q$2:$Q$648,{1,2,3,4,5,6,7,8,9})>0,0),0))&" (parcial)","—")) -> Distrito | O10: =IF(COUNTIFS(Cifras!$A$2:$A$399,$A10,Cifras!$E$2:$E$399,"Sí",Cifras!$D$2:$D$399,"distrito")>0,"Distrito",IF(COUNTIFS(Cifras!$A$2:$A$399,$A10,Cifras!$E$2:$E$399,"Sí",Cifras!$D$2:$D$399,"comuna")>0,"Comuna",IF(COUNTIFS(Cifras!$A$2:$A$399,$A10,Cifras!$E$2:$E$399,"Sí",Cifras!$D$2:$D$399,"partido")>0,"Partido",IF(COUNTIFS(Cifras!$A$2:$A$399,$A10,Cifras!$E$2:$E$399,"Sí",Cifras!$D$2:$D$399,"departamento")>0,"Departamento",IF(COUNTIFS(Cifras!$A$2:$A$399,$A10,Cifras!$E$2:$E$399,"Sí",Cifras!$D$2:$D$399,"provincia")>0,"Provincia",IF(COUNTIFS(Cifras!$A$2:$A$399,$A10,Cifras!$E$2:$E$399,"Sí",Cifras!$D$2:$D$399,"region")>0,"Región",IF(COUNTIFS(Cifras!$A$2:$A$399,$A10,Cifras!$E$2:$E$399,"Sí",Cifras!$D$2:$D$399,"pais")>0,"País","—"))))))) -> Departamento | P10: =IF(IFERROR(MATCH(TRUE,COUNTIFS(Catálogo!$J$2:$J$648,"*"&$A10&"*",Catálogo!$I$2:$I$648,"<>ausente",Catálogo!$M$2:$M$648,"completa",Catálogo!$L$2:$L$648,"*area*",Catálogo!$Q$2:$Q$648,{1,2,3,4,5,6,7,8,9})>0,0),0)>0,INDEX(Niveles!$C$2:$C$10,IFERROR(MATCH(TRUE,COUNTIFS(Catálogo!$J$2:$J$648,"*"&$A10&"*",Catálogo!$I$2:$I$648,"<>ausente",Catálogo!$M$2:$M$648,"completa",Catálogo!$L$2:$L$648,"*area*",Catálogo!$Q$2:$Q$648,{1,2,3,4,5,6,7,8,9})>0,0),0))&IF(AND(IFERROR(MATCH(TRUE,COUNTIFS(Catálogo!$J$2:$J$648,"*"&$A10&"*",Catálogo!$I$2:$I$648,"<>ausente",Catálogo!$M$2:$M$648,"parcial",Catálogo!$L$2:$L$648,"*area*",Catálogo!$Q$2:$Q$648,{1,2,3,4,5,6,7,8,9})>0,0),0)>0,IFERROR(MATCH(TRUE,COUNTIFS(Catálogo!$J$2:$J$648,"*"&$A10&"*",Catálogo!$I$2:$I$648,"<>ausente",Catálogo!$M$2:$M$648,"parcial",Catálogo!$L$2:$L$648,"*area*",Catálogo!$Q$2:$Q$648,{1,2,3,4,5,6,7,8,9})>0,0),0)<IFERROR(MATCH(TRUE,COUNTIFS(Catálogo!$J$2:$J$648,"*"&$A10&"*",Catálogo!$I$2:$I$648,"<>ausente",Catálogo!$M$2:$M$648,"completa",Catálogo!$L$2:$L$648,"*area*",Catálogo!$Q$2:$Q$648,{1,2,3,4,5,6,7,8,9})>0,0),0)),"; "&LOWER(INDEX(Niveles!$C$2:$C$10,IFERROR(MATCH(TRUE,COUNTIFS(Catálogo!$J$2:$J$648,"*"&$A10&"*",Catálogo!$I$2:$I$648,"<>ausente",Catálogo!$M$2:$M$648,"parcial",Catálogo!$L$2:$L$648,"*area*",Catálogo!$Q$2:$Q$648,{1,2,3,4,5,6,7,8,9})>0,0),0)))&" (parcial)",""),IF(IFERROR(MATCH(TRUE,COUNTIFS(Catálogo!$J$2:$J$648,"*"&$A10&"*",Catálogo!$I$2:$I$648,"<>ausente",Catálogo!$M$2:$M$648,"parcial",Catálogo!$L$2:$L$648,"*area*",Catálogo!$Q$2:$Q$648,{1,2,3,4,5,6,7,8,9})>0,0),0)>0,INDEX(Niveles!$C$2:$C$10,IFERROR(MATCH(TRUE,COUNTIFS(Catálogo!$J$2:$J$648,"*"&$A10&"*",Catálogo!$I$2:$I$648,"<>ausente",Catálogo!$M$2:$M$648,"parcial",Catálogo!$L$2:$L$648,"*area*",Catálogo!$Q$2:$Q$648,{1,2,3,4,5,6,7,8,9})>0,0),0))&" (parcial)","—")) -> Departamento | Q10: =IF(COUNTIFS(Cifras!$A$2:$A$399,$A10,Cifras!$E$2:$E$399,"Sí",Cifras!$F$2:$F$399,"Sí",Cifras!$D$2:$D$399,"distrito")>0,"Distrito",IF(COUNTIFS(Cifras!$A$2:$A$399,$A10,Cifras!$E$2:$E$399,"Sí",Cifras!$F$2:$F$399,"Sí",Cifras!$D$2:$D$399,"comuna")>0,"Comuna",IF(COUNTIFS(Cifras!$A$2:$A$399,$A10,Cifras!$E$2:$E$399,"Sí",Cifras!$F$2:$F$399,"Sí",Cifras!$D$2:$D$399,"partido")>0,"Partido",IF(COUNTIFS(Cifras!$A$2:$A$399,$A10,Cifras!$E$2:$E$399,"Sí",Cifras!$F$2:$F$399,"Sí",Cifras!$D$2:$D$399,"departamento")>0,"Departamento",IF(COUNTIFS(Cifras!$A$2:$A$399,$A10,Cifras!$E$2:$E$399,"Sí",Cifras!$F$2:$F$399,"Sí",Cifras!$D$2:$D$399,"provincia")>0,"Provincia",IF(COUNTIFS(Cifras!$A$2:$A$399,$A10,Cifras!$E$2:$E$399,"Sí",Cifras!$F$2:$F$399,"Sí",Cifras!$D$2:$D$399,"region")>0,"Región",IF(COUNTIFS(Cifras!$A$2:$A$399,$A10,Cifras!$E$2:$E$399,"Sí",Cifras!$F$2:$F$399,"Sí",Cifras!$D$2:$D$399,"pais")>0,"País","—"))))))) -> — | R10: =IF(IFERROR(MATCH(TRUE,COUNTIFS(Catálogo!$J$2:$J$648,"*"&$A10&"*",Catálogo!$I$2:$I$648,"<>ausente",Catálogo!$M$2:$M$648,"completa",Catálogo!$L$2:$L$648,"*area*",Catálogo!$L$2:$L$648,"*sexo*",Catálogo!$Q$2:$Q$648,{1,2,3,4,5,6,7,8,9})>0,0),0)>0,INDEX(Niveles!$C$2:$C$10,IFERROR(MATCH(TRUE,COUNTIFS(Catálogo!$J$2:$J$648,"*"&$A10&"*",Catálogo!$I$2:$I$648,"<>ausente",Catálogo!$M$2:$M$648,"completa",Catálogo!$L$2:$L$648,"*area*",Catálogo!$L$2:$L$648,"*sexo*",Catálogo!$Q$2:$Q$648,{1,2,3,4,5,6,7,8,9})>0,0),0))&IF(AND(IFERROR(MATCH(TRUE,COUNTIFS(Catálogo!$J$2:$J$648,"*"&$A10&"*",Catálogo!$I$2:$I$648,"<>ausente",Catálogo!$M$2:$M$648,"parcial",Catálogo!$L$2:$L$648,"*area*",Catálogo!$L$2:$L$648,"*sexo*",Catálogo!$Q$2:$Q$648,{1,2,3,4,5,6,7,8,9})>0,0),0)>0,IFERROR(MATCH(TRUE,COUNTIFS(Catálogo!$J$2:$J$648,"*"&$A10&"*",Catálogo!$I$2:$I$648,"<>ausente",Catálogo!$M$2:$M$648,"parcial",Catálogo!$L$2:$L$648,"*area*",Catálogo!$L$2:$L$648,"*sexo*",Catálogo!$Q$2:$Q$648,{1,2,3,4,5,6,7,8,9})>0,0),0)<IFERROR(MATCH(TRUE,COUNTIFS(Catálogo!$J$2:$J$648,"*"&$A10&"*",Catálogo!$I$2:$I$648,"<>ausente",Catálogo!$M$2:$M$648,"completa",Catálogo!$L$2:$L$648,"*area*",Catálogo!$L$2:$L$648,"*sexo*",Catálogo!$Q$2:$Q$648,{1,2,3,4,5,6,7,8,9})>0,0),0)),"; "&LOWER(INDEX(Niveles!$C$2:$C$10,IFERROR(MATCH(TRUE,COUNTIFS(Catálogo!$J$2:$J$648,"*"&$A10&"*",Catálogo!$I$2:$I$648,"<>ausente",Catálogo!$M$2:$M$648,"parcial",Catálogo!$L$2:$L$648,"*area*",Catálogo!$L$2:$L$648,"*sexo*",Catálogo!$Q$2:$Q$648,{1,2,3,4,5,6,7,8,9})>0,0),0)))&" (parcial)",""),IF(IFERROR(MATCH(TRUE,COUNTIFS(Catálogo!$J$2:$J$648,"*"&$A10&"*",Catálogo!$I$2:$I$648,"<>ausente",Catálogo!$M$2:$M$648,"parcial",Catálogo!$L$2:$L$648,"*area*",Catálogo!$L$2:$L$648,"*sexo*",Catálogo!$Q$2:$Q$648,{1,2,3,4,5,6,7,8,9})>0,0),0)>0,INDEX(Niveles!$C$2:$C$10,IFERROR(MATCH(TRUE,COUNTIFS(Catálogo!$J$2:$J$648,"*"&$A10&"*",Catálogo!$I$2:$I$648,"<>ausente",Catálogo!$M$2:$M$648,"parcial",Catálogo!$L$2:$L$648,"*area*",Catálogo!$L$2:$L$648,"*sexo*",Catálogo!$Q$2:$Q$648,{1,2,3,4,5,6,7,8,9})>0,0),0))&" (parcial)","—")) -> — | S10: =IF(COUNTIFS(Cifras!$A$2:$A$399,$A10,Cifras!$F$2:$F$399,"Sí",Cifras!$G$2:$G$399,"Sí",Cifras!$D$2:$D$399,"distrito")>0,"Distrito",IF(COUNTIFS(Cifras!$A$2:$A$399,$A10,Cifras!$F$2:$F$399,"Sí",Cifras!$G$2:$G$399,"Sí",Cifras!$D$2:$D$399,"comuna")>0,"Comuna",IF(COUNTIFS(Cifras!$A$2:$A$399,$A10,Cifras!$F$2:$F$399,"Sí",Cifras!$G$2:$G$399,"Sí",Cifras!$D$2:$D$399,"partido")>0,"Partido",IF(COUNTIFS(Cifras!$A$2:$A$399,$A10,Cifras!$F$2:$F$399,"Sí",Cifras!$G$2:$G$399,"Sí",Cifras!$D$2:$D$399,"departamento")>0,"Departamento",IF(COUNTIFS(Cifras!$A$2:$A$399,$A10,Cifras!$F$2:$F$399,"Sí",Cifras!$G$2:$G$399,"Sí",Cifras!$D$2:$D$399,"provincia")>0,"Provincia",IF(COUNTIFS(Cifras!$A$2:$A$399,$A10,Cifras!$F$2:$F$399,"Sí",Cifras!$G$2:$G$399,"Sí",Cifras!$D$2:$D$399,"region")>0,"Región",IF(COUNTIFS(Cifras!$A$2:$A$399,$A10,Cifras!$F$2:$F$399,"Sí",Cifras!$G$2:$G$399,"Sí",Cifras!$D$2:$D$399,"pais")>0,"País","—"))))))) -> Departamento | T10: =IF(IFERROR(MATCH(TRUE,COUNTIFS(Catálogo!$J$2:$J$648,"*"&$A10&"*",Catálogo!$I$2:$I$648,"<>ausente",Catálogo!$M$2:$M$648,"completa",Catálogo!$L$2:$L$648,"*sexo*",Catálogo!$L$2:$L$648,"*edad*",Catálogo!$Q$2:$Q$648,{1,2,3,4,5,6,7,8,9})>0,0),0)>0,INDEX(Niveles!$C$2:$C$10,IFERROR(MATCH(TRUE,COUNTIFS(Catálogo!$J$2:$J$648,"*"&$A10&"*",Catálogo!$I$2:$I$648,"<>ausente",Catálogo!$M$2:$M$648,"completa",Catálogo!$L$2:$L$648,"*sexo*",Catálogo!$L$2:$L$648,"*edad*",Catálogo!$Q$2:$Q$648,{1,2,3,4,5,6,7,8,9})>0,0),0))&IF(AND(IFERROR(MATCH(TRUE,COUNTIFS(Catálogo!$J$2:$J$648,"*"&$A10&"*",Catálogo!$I$2:$I$648,"<>ausente",Catálogo!$M$2:$M$648,"parcial",Catálogo!$L$2:$L$648,"*sexo*",Catálogo!$L$2:$L$648,"*edad*",Catálogo!$Q$2:$Q$648,{1,2,3,4,5,6,7,8,9})>0,0),0)>0,IFERROR(MATCH(TRUE,COUNTIFS(Catálogo!$J$2:$J$648,"*"&$A10&"*",Catálogo!$I$2:$I$648,"<>ausente",Catálogo!$M$2:$M$648,"parcial",Catálogo!$L$2:$L$648,"*sexo*",Catálogo!$L$2:$L$648,"*edad*",Catálogo!$Q$2:$Q$648,{1,2,3,4,5,6,7,8,9})>0,0),0)<IFERROR(MATCH(TRUE,COUNTIFS(Catálogo!$J$2:$J$648,"*"&$A10&"*",Catálogo!$I$2:$I$648,"<>ausente",Catálogo!$M$2:$M$648,"completa",Catálogo!$L$2:$L$648,"*sexo*",Catálogo!$L$2:$L$648,"*edad*",Catálogo!$Q$2:$Q$648,{1,2,3,4,5,6,7,8,9})>0,0),0)),"; "&LOWER(INDEX(Niveles!$C$2:$C$10,IFERROR(MATCH(TRUE,COUNTIFS(Catálogo!$J$2:$J$648,"*"&$A10&"*",Catálogo!$I$2:$I$648,"<>ausente",Catálogo!$M$2:$M$648,"parcial",Catálogo!$L$2:$L$648,"*sexo*",Catálogo!$L$2:$L$648,"*edad*",Catálogo!$Q$2:$Q$648,{1,2,3,4,5,6,7,8,9})>0,0),0)))&" (parcial)",""),IF(IFERROR(MATCH(TRUE,COUNTIFS(Catálogo!$J$2:$J$648,"*"&$A10&"*",Catálogo!$I$2:$I$648,"<>ausente",Catálogo!$M$2:$M$648,"parcial",Catálogo!$L$2:$L$648,"*sexo*",Catálogo!$L$2:$L$648,"*edad*",Catálogo!$Q$2:$Q$648,{1,2,3,4,5,6,7,8,9})>0,0),0)>0,INDEX(Niveles!$C$2:$C$10,IFERROR(MATCH(TRUE,COUNTIFS(Catálogo!$J$2:$J$648,"*"&$A10&"*",Catálogo!$I$2:$I$648,"<>ausente",Catálogo!$M$2:$M$648,"parcial",Catálogo!$L$2:$L$648,"*sexo*",Catálogo!$L$2:$L$648,"*edad*",Catálogo!$Q$2:$Q$648,{1,2,3,4,5,6,7,8,9})>0,0),0))&" (parcial)","—")) -> Distrito | U10: =SUMIFS(Cifras!$J$2:$J$399,Cifras!$A$2:$A$399,$A10) -> 3 | V10: Núcleo completo | W10: Opcional: subdelegación y distrito × sexo × edad, con urbana y rural del total (bloques provinciales). El área no viene por sexo. | X10: Departamento × sexo × edad en 6 tramos y departamento × área del cuadro general (págs. 602-605); provincias = 1952 C6 y C9, departamentos = sinóptico de 1875. Erratas: Valdivia urbana, La Unión 80+ hombres, Angol 51-80 hombres.
A11: 1885 | B11: pub_1885 | C11: 905 | D11: =COUNTIFS(Catálogo!$B$2:$B$648,$A11) -> 35 | E11: =COUNTIFS(Catálogo!$B$2:$B$648,$A11,Catálogo!$F$2:$F$648,"cuadro") -> 11 | F11: =COUNTIFS(Catálogo!$B$2:$B$648,$A11,Catálogo!$F$2:$F$648,"bloque") -> 23 | G11: =COUNTIFS(Catálogo!$B$2:$B$648,$A11,Catálogo!$F$2:$F$648,"texto") -> 1 | H11: =COUNTIFS(Catálogo!$B$2:$B$648,$A11,Catálogo!$I$2:$I$648,"verificada") -> 3 | I11: =COUNTIFS(Catálogo!$B$2:$B$648,$A11,Catálogo!$I$2:$I$648,"estimada") -> 31 | J11: =COUNTIFS(Catálogo!$B$2:$B$648,$A11,Catálogo!$I$2:$I$648,"desconocida")+COUNTIFS(Catálogo!$B$2:$B$648,$A11,Catálogo!$I$2:$I$648,"ausente") -> 1 | K11: =COUNTIFS(Catálogo!$B$2:$B$648,$A11,Catálogo!$O$2:$O$648,"transcrito") -> 2 | L11: =SUMIFS(Cifras!$H$2:$H$399,Cifras!$A$2:$A$399,$A11) -> 5640 | M11: =IF(COUNTIFS(Cifras!$A$2:$A$399,$A11,Cifras!$D$2:$D$399,"distrito")>0,"Distrito",IF(COUNTIFS(Cifras!$A$2:$A$399,$A11,Cifras!$D$2:$D$399,"comuna")>0,"Comuna",IF(COUNTIFS(Cifras!$A$2:$A$399,$A11,Cifras!$D$2:$D$399,"partido")>0,"Partido",IF(COUNTIFS(Cifras!$A$2:$A$399,$A11,Cifras!$D$2:$D$399,"departamento")>0,"Departamento",IF(COUNTIFS(Cifras!$A$2:$A$399,$A11,Cifras!$D$2:$D$399,"provincia")>0,"Provincia",IF(COUNTIFS(Cifras!$A$2:$A$399,$A11,Cifras!$D$2:$D$399,"region")>0,"Región",IF(COUNTIFS(Cifras!$A$2:$A$399,$A11,Cifras!$D$2:$D$399,"pais")>0,"País","—"))))))) -> Departamento | N11: =IF(IFERROR(MATCH(TRUE,COUNTIFS(Catálogo!$J$2:$J$648,"*"&$A11&"*",Catálogo!$I$2:$I$648,"<>ausente",Catálogo!$M$2:$M$648,"completa",Catálogo!$Q$2:$Q$648,{1,2,3,4,5,6,7,8,9})>0,0),0)>0,INDEX(Niveles!$C$2:$C$10,IFERROR(MATCH(TRUE,COUNTIFS(Catálogo!$J$2:$J$648,"*"&$A11&"*",Catálogo!$I$2:$I$648,"<>ausente",Catálogo!$M$2:$M$648,"completa",Catálogo!$Q$2:$Q$648,{1,2,3,4,5,6,7,8,9})>0,0),0))&IF(AND(IFERROR(MATCH(TRUE,COUNTIFS(Catálogo!$J$2:$J$648,"*"&$A11&"*",Catálogo!$I$2:$I$648,"<>ausente",Catálogo!$M$2:$M$648,"parcial",Catálogo!$Q$2:$Q$648,{1,2,3,4,5,6,7,8,9})>0,0),0)>0,IFERROR(MATCH(TRUE,COUNTIFS(Catálogo!$J$2:$J$648,"*"&$A11&"*",Catálogo!$I$2:$I$648,"<>ausente",Catálogo!$M$2:$M$648,"parcial",Catálogo!$Q$2:$Q$648,{1,2,3,4,5,6,7,8,9})>0,0),0)<IFERROR(MATCH(TRUE,COUNTIFS(Catálogo!$J$2:$J$648,"*"&$A11&"*",Catálogo!$I$2:$I$648,"<>ausente",Catálogo!$M$2:$M$648,"completa",Catálogo!$Q$2:$Q$648,{1,2,3,4,5,6,7,8,9})>0,0),0)),"; "&LOWER(INDEX(Niveles!$C$2:$C$10,IFERROR(MATCH(TRUE,COUNTIFS(Catálogo!$J$2:$J$648,"*"&$A11&"*",Catálogo!$I$2:$I$648,"<>ausente",Catálogo!$M$2:$M$648,"parcial",Catálogo!$Q$2:$Q$648,{1,2,3,4,5,6,7,8,9})>0,0),0)))&" (parcial)",""),IF(IFERROR(MATCH(TRUE,COUNTIFS(Catálogo!$J$2:$J$648,"*"&$A11&"*",Catálogo!$I$2:$I$648,"<>ausente",Catálogo!$M$2:$M$648,"parcial",Catálogo!$Q$2:$Q$648,{1,2,3,4,5,6,7,8,9})>0,0),0)>0,INDEX(Niveles!$C$2:$C$10,IFERROR(MATCH(TRUE,COUNTIFS(Catálogo!$J$2:$J$648,"*"&$A11&"*",Catálogo!$I$2:$I$648,"<>ausente",Catálogo!$M$2:$M$648,"parcial",Catálogo!$Q$2:$Q$648,{1,2,3,4,5,6,7,8,9})>0,0),0))&" (parcial)","—")) -> Distrito | O11: =IF(COUNTIFS(Cifras!$A$2:$A$399,$A11,Cifras!$E$2:$E$399,"Sí",Cifras!$D$2:$D$399,"distrito")>0,"Distrito",IF(COUNTIFS(Cifras!$A$2:$A$399,$A11,Cifras!$E$2:$E$399,"Sí",Cifras!$D$2:$D$399,"comuna")>0,"Comuna",IF(COUNTIFS(Cifras!$A$2:$A$399,$A11,Cifras!$E$2:$E$399,"Sí",Cifras!$D$2:$D$399,"partido")>0,"Partido",IF(COUNTIFS(Cifras!$A$2:$A$399,$A11,Cifras!$E$2:$E$399,"Sí",Cifras!$D$2:$D$399,"departamento")>0,"Departamento",IF(COUNTIFS(Cifras!$A$2:$A$399,$A11,Cifras!$E$2:$E$399,"Sí",Cifras!$D$2:$D$399,"provincia")>0,"Provincia",IF(COUNTIFS(Cifras!$A$2:$A$399,$A11,Cifras!$E$2:$E$399,"Sí",Cifras!$D$2:$D$399,"region")>0,"Región",IF(COUNTIFS(Cifras!$A$2:$A$399,$A11,Cifras!$E$2:$E$399,"Sí",Cifras!$D$2:$D$399,"pais")>0,"País","—"))))))) -> Departamento | P11: =IF(IFERROR(MATCH(TRUE,COUNTIFS(Catálogo!$J$2:$J$648,"*"&$A11&"*",Catálogo!$I$2:$I$648,"<>ausente",Catálogo!$M$2:$M$648,"completa",Catálogo!$L$2:$L$648,"*area*",Catálogo!$Q$2:$Q$648,{1,2,3,4,5,6,7,8,9})>0,0),0)>0,INDEX(Niveles!$C$2:$C$10,IFERROR(MATCH(TRUE,COUNTIFS(Catálogo!$J$2:$J$648,"*"&$A11&"*",Catálogo!$I$2:$I$648,"<>ausente",Catálogo!$M$2:$M$648,"completa",Catálogo!$L$2:$L$648,"*area*",Catálogo!$Q$2:$Q$648,{1,2,3,4,5,6,7,8,9})>0,0),0))&IF(AND(IFERROR(MATCH(TRUE,COUNTIFS(Catálogo!$J$2:$J$648,"*"&$A11&"*",Catálogo!$I$2:$I$648,"<>ausente",Catálogo!$M$2:$M$648,"parcial",Catálogo!$L$2:$L$648,"*area*",Catálogo!$Q$2:$Q$648,{1,2,3,4,5,6,7,8,9})>0,0),0)>0,IFERROR(MATCH(TRUE,COUNTIFS(Catálogo!$J$2:$J$648,"*"&$A11&"*",Catálogo!$I$2:$I$648,"<>ausente",Catálogo!$M$2:$M$648,"parcial",Catálogo!$L$2:$L$648,"*area*",Catálogo!$Q$2:$Q$648,{1,2,3,4,5,6,7,8,9})>0,0),0)<IFERROR(MATCH(TRUE,COUNTIFS(Catálogo!$J$2:$J$648,"*"&$A11&"*",Catálogo!$I$2:$I$648,"<>ausente",Catálogo!$M$2:$M$648,"completa",Catálogo!$L$2:$L$648,"*area*",Catálogo!$Q$2:$Q$648,{1,2,3,4,5,6,7,8,9})>0,0),0)),"; "&LOWER(INDEX(Niveles!$C$2:$C$10,IFERROR(MATCH(TRUE,COUNTIFS(Catálogo!$J$2:$J$648,"*"&$A11&"*",Catálogo!$I$2:$I$648,"<>ausente",Catálogo!$M$2:$M$648,"parcial",Catálogo!$L$2:$L$648,"*area*",Catálogo!$Q$2:$Q$648,{1,2,3,4,5,6,7,8,9})>0,0),0)))&" (parcial)",""),IF(IFERROR(MATCH(TRUE,COUNTIFS(Catálogo!$J$2:$J$648,"*"&$A11&"*",Catálogo!$I$2:$I$648,"<>ausente",Catálogo!$M$2:$M$648,"parcial",Catálogo!$L$2:$L$648,"*area*",Catálogo!$Q$2:$Q$648,{1,2,3,4,5,6,7,8,9})>0,0),0)>0,INDEX(Niveles!$C$2:$C$10,IFERROR(MATCH(TRUE,COUNTIFS(Catálogo!$J$2:$J$648,"*"&$A11&"*",Catálogo!$I$2:$I$648,"<>ausente",Catálogo!$M$2:$M$648,"parcial",Catálogo!$L$2:$L$648,"*area*",Catálogo!$Q$2:$Q$648,{1,2,3,4,5,6,7,8,9})>0,0),0))&" (parcial)","—")) -> Departamento | Q11: =IF(COUNTIFS(Cifras!$A$2:$A$399,$A11,Cifras!$E$2:$E$399,"Sí",Cifras!$F$2:$F$399,"Sí",Cifras!$D$2:$D$399,"distrito")>0,"Distrito",IF(COUNTIFS(Cifras!$A$2:$A$399,$A11,Cifras!$E$2:$E$399,"Sí",Cifras!$F$2:$F$399,"Sí",Cifras!$D$2:$D$399,"comuna")>0,"Comuna",IF(COUNTIFS(Cifras!$A$2:$A$399,$A11,Cifras!$E$2:$E$399,"Sí",Cifras!$F$2:$F$399,"Sí",Cifras!$D$2:$D$399,"partido")>0,"Partido",IF(COUNTIFS(Cifras!$A$2:$A$399,$A11,Cifras!$E$2:$E$399,"Sí",Cifras!$F$2:$F$399,"Sí",Cifras!$D$2:$D$399,"departamento")>0,"Departamento",IF(COUNTIFS(Cifras!$A$2:$A$399,$A11,Cifras!$E$2:$E$399,"Sí",Cifras!$F$2:$F$399,"Sí",Cifras!$D$2:$D$399,"provincia")>0,"Provincia",IF(COUNTIFS(Cifras!$A$2:$A$399,$A11,Cifras!$E$2:$E$399,"Sí",Cifras!$F$2:$F$399,"Sí",Cifras!$D$2:$D$399,"region")>0,"Región",IF(COUNTIFS(Cifras!$A$2:$A$399,$A11,Cifras!$E$2:$E$399,"Sí",Cifras!$F$2:$F$399,"Sí",Cifras!$D$2:$D$399,"pais")>0,"País","—"))))))) -> — | R11: =IF(IFERROR(MATCH(TRUE,COUNTIFS(Catálogo!$J$2:$J$648,"*"&$A11&"*",Catálogo!$I$2:$I$648,"<>ausente",Catálogo!$M$2:$M$648,"completa",Catálogo!$L$2:$L$648,"*area*",Catálogo!$L$2:$L$648,"*sexo*",Catálogo!$Q$2:$Q$648,{1,2,3,4,5,6,7,8,9})>0,0),0)>0,INDEX(Niveles!$C$2:$C$10,IFERROR(MATCH(TRUE,COUNTIFS(Catálogo!$J$2:$J$648,"*"&$A11&"*",Catálogo!$I$2:$I$648,"<>ausente",Catálogo!$M$2:$M$648,"completa",Catálogo!$L$2:$L$648,"*area*",Catálogo!$L$2:$L$648,"*sexo*",Catálogo!$Q$2:$Q$648,{1,2,3,4,5,6,7,8,9})>0,0),0))&IF(AND(IFERROR(MATCH(TRUE,COUNTIFS(Catálogo!$J$2:$J$648,"*"&$A11&"*",Catálogo!$I$2:$I$648,"<>ausente",Catálogo!$M$2:$M$648,"parcial",Catálogo!$L$2:$L$648,"*area*",Catálogo!$L$2:$L$648,"*sexo*",Catálogo!$Q$2:$Q$648,{1,2,3,4,5,6,7,8,9})>0,0),0)>0,IFERROR(MATCH(TRUE,COUNTIFS(Catálogo!$J$2:$J$648,"*"&$A11&"*",Catálogo!$I$2:$I$648,"<>ausente",Catálogo!$M$2:$M$648,"parcial",Catálogo!$L$2:$L$648,"*area*",Catálogo!$L$2:$L$648,"*sexo*",Catálogo!$Q$2:$Q$648,{1,2,3,4,5,6,7,8,9})>0,0),0)<IFERROR(MATCH(TRUE,COUNTIFS(Catálogo!$J$2:$J$648,"*"&$A11&"*",Catálogo!$I$2:$I$648,"<>ausente",Catálogo!$M$2:$M$648,"completa",Catálogo!$L$2:$L$648,"*area*",Catálogo!$L$2:$L$648,"*sexo*",Catálogo!$Q$2:$Q$648,{1,2,3,4,5,6,7,8,9})>0,0),0)),"; "&LOWER(INDEX(Niveles!$C$2:$C$10,IFERROR(MATCH(TRUE,COUNTIFS(Catálogo!$J$2:$J$648,"*"&$A11&"*",Catálogo!$I$2:$I$648,"<>ausente",Catálogo!$M$2:$M$648,"parcial",Catálogo!$L$2:$L$648,"*area*",Catálogo!$L$2:$L$648,"*sexo*",Catálogo!$Q$2:$Q$648,{1,2,3,4,5,6,7,8,9})>0,0),0)))&" (parcial)",""),IF(IFERROR(MATCH(TRUE,COUNTIFS(Catálogo!$J$2:$J$648,"*"&$A11&"*",Catálogo!$I$2:$I$648,"<>ausente",Catálogo!$M$2:$M$648,"parcial",Catálogo!$L$2:$L$648,"*area*",Catálogo!$L$2:$L$648,"*sexo*",Catálogo!$Q$2:$Q$648,{1,2,3,4,5,6,7,8,9})>0,0),0)>0,INDEX(Niveles!$C$2:$C$10,IFERROR(MATCH(TRUE,COUNTIFS(Catálogo!$J$2:$J$648,"*"&$A11&"*",Catálogo!$I$2:$I$648,"<>ausente",Catálogo!$M$2:$M$648,"parcial",Catálogo!$L$2:$L$648,"*area*",Catálogo!$L$2:$L$648,"*sexo*",Catálogo!$Q$2:$Q$648,{1,2,3,4,5,6,7,8,9})>0,0),0))&" (parcial)","—")) -> — | S11: =IF(COUNTIFS(Cifras!$A$2:$A$399,$A11,Cifras!$F$2:$F$399,"Sí",Cifras!$G$2:$G$399,"Sí",Cifras!$D$2:$D$399,"distrito")>0,"Distrito",IF(COUNTIFS(Cifras!$A$2:$A$399,$A11,Cifras!$F$2:$F$399,"Sí",Cifras!$G$2:$G$399,"Sí",Cifras!$D$2:$D$399,"comuna")>0,"Comuna",IF(COUNTIFS(Cifras!$A$2:$A$399,$A11,Cifras!$F$2:$F$399,"Sí",Cifras!$G$2:$G$399,"Sí",Cifras!$D$2:$D$399,"partido")>0,"Partido",IF(COUNTIFS(Cifras!$A$2:$A$399,$A11,Cifras!$F$2:$F$399,"Sí",Cifras!$G$2:$G$399,"Sí",Cifras!$D$2:$D$399,"departamento")>0,"Departamento",IF(COUNTIFS(Cifras!$A$2:$A$399,$A11,Cifras!$F$2:$F$399,"Sí",Cifras!$G$2:$G$399,"Sí",Cifras!$D$2:$D$399,"provincia")>0,"Provincia",IF(COUNTIFS(Cifras!$A$2:$A$399,$A11,Cifras!$F$2:$F$399,"Sí",Cifras!$G$2:$G$399,"Sí",Cifras!$D$2:$D$399,"region")>0,"Región",IF(COUNTIFS(Cifras!$A$2:$A$399,$A11,Cifras!$F$2:$F$399,"Sí",Cifras!$G$2:$G$399,"Sí",Cifras!$D$2:$D$399,"pais")>0,"País","—"))))))) -> Departamento | T11: =IF(IFERROR(MATCH(TRUE,COUNTIFS(Catálogo!$J$2:$J$648,"*"&$A11&"*",Catálogo!$I$2:$I$648,"<>ausente",Catálogo!$M$2:$M$648,"completa",Catálogo!$L$2:$L$648,"*sexo*",Catálogo!$L$2:$L$648,"*edad*",Catálogo!$Q$2:$Q$648,{1,2,3,4,5,6,7,8,9})>0,0),0)>0,INDEX(Niveles!$C$2:$C$10,IFERROR(MATCH(TRUE,COUNTIFS(Catálogo!$J$2:$J$648,"*"&$A11&"*",Catálogo!$I$2:$I$648,"<>ausente",Catálogo!$M$2:$M$648,"completa",Catálogo!$L$2:$L$648,"*sexo*",Catálogo!$L$2:$L$648,"*edad*",Catálogo!$Q$2:$Q$648,{1,2,3,4,5,6,7,8,9})>0,0),0))&IF(AND(IFERROR(MATCH(TRUE,COUNTIFS(Catálogo!$J$2:$J$648,"*"&$A11&"*",Catálogo!$I$2:$I$648,"<>ausente",Catálogo!$M$2:$M$648,"parcial",Catálogo!$L$2:$L$648,"*sexo*",Catálogo!$L$2:$L$648,"*edad*",Catálogo!$Q$2:$Q$648,{1,2,3,4,5,6,7,8,9})>0,0),0)>0,IFERROR(MATCH(TRUE,COUNTIFS(Catálogo!$J$2:$J$648,"*"&$A11&"*",Catálogo!$I$2:$I$648,"<>ausente",Catálogo!$M$2:$M$648,"parcial",Catálogo!$L$2:$L$648,"*sexo*",Catálogo!$L$2:$L$648,"*edad*",Catálogo!$Q$2:$Q$648,{1,2,3,4,5,6,7,8,9})>0,0),0)<IFERROR(MATCH(TRUE,COUNTIFS(Catálogo!$J$2:$J$648,"*"&$A11&"*",Catálogo!$I$2:$I$648,"<>ausente",Catálogo!$M$2:$M$648,"completa",Catálogo!$L$2:$L$648,"*sexo*",Catálogo!$L$2:$L$648,"*edad*",Catálogo!$Q$2:$Q$648,{1,2,3,4,5,6,7,8,9})>0,0),0)),"; "&LOWER(INDEX(Niveles!$C$2:$C$10,IFERROR(MATCH(TRUE,COUNTIFS(Catálogo!$J$2:$J$648,"*"&$A11&"*",Catálogo!$I$2:$I$648,"<>ausente",Catálogo!$M$2:$M$648,"parcial",Catálogo!$L$2:$L$648,"*sexo*",Catálogo!$L$2:$L$648,"*edad*",Catálogo!$Q$2:$Q$648,{1,2,3,4,5,6,7,8,9})>0,0),0)))&" (parcial)",""),IF(IFERROR(MATCH(TRUE,COUNTIFS(Catálogo!$J$2:$J$648,"*"&$A11&"*",Catálogo!$I$2:$I$648,"<>ausente",Catálogo!$M$2:$M$648,"parcial",Catálogo!$L$2:$L$648,"*sexo*",Catálogo!$L$2:$L$648,"*edad*",Catálogo!$Q$2:$Q$648,{1,2,3,4,5,6,7,8,9})>0,0),0)>0,INDEX(Niveles!$C$2:$C$10,IFERROR(MATCH(TRUE,COUNTIFS(Catálogo!$J$2:$J$648,"*"&$A11&"*",Catálogo!$I$2:$I$648,"<>ausente",Catálogo!$M$2:$M$648,"parcial",Catálogo!$L$2:$L$648,"*sexo*",Catálogo!$L$2:$L$648,"*edad*",Catálogo!$Q$2:$Q$648,{1,2,3,4,5,6,7,8,9})>0,0),0))&" (parcial)","—")) -> Distrito | U11: =SUMIFS(Cifras!$J$2:$J$399,Cifras!$A$2:$A$399,$A11) -> 15 | V11: Núcleo completo | W11: Opcional: subdelegación y distrito × sexo × edad, con urbana y rural (bloques provinciales del tomo I). El área no viene por sexo. El tomo 2 (Memoria Chilena) trae profesiones y extranjeros. | X11: Departamento × sexo × edad en 26 grupos (meses bajo 1 año) y departamento × área del cuadro general (págs. 839-846, leído en la copia de Memoria Chilena del tomo I porque el PDF del INE tiene filas manchadas). Incluye Tacna; sin ella, provincias = 1952 C5 y C9 y decenios del país = 1952 C7. 13 erratas anotadas; 1952 C5 tiene una errata de 3 000 en Malleco (Angol).
A12: 1895 | B12: pub_1895 | C12: 2547 | D12: =COUNTIFS(Catálogo!$B$2:$B$648,$A12) -> 40 | E12: =COUNTIFS(Catálogo!$B$2:$B$648,$A12,Catálogo!$F$2:$F$648,"cuadro") -> 12 | F12: =COUNTIFS(Catálogo!$B$2:$B$648,$A12,Catálogo!$F$2:$F$648,"bloque") -> 23 | G12: =COUNTIFS(Catálogo!$B$2:$B$648,$A12,Catálogo!$F$2:$F$648,"texto") -> 5 | H12: =COUNTIFS(Catálogo!$B$2:$B$648,$A12,Catálogo!$I$2:$I$648,"verificada") -> 4 | I12: =COUNTIFS(Catálogo!$B$2:$B$648,$A12,Catálogo!$I$2:$I$648,"estimada") -> 32 | J12: =COUNTIFS(Catálogo!$B$2:$B$648,$A12,Catálogo!$I$2:$I$648,"desconocida")+COUNTIFS(Catálogo!$B$2:$B$648,$A12,Catálogo!$I$2:$I$648,"ausente") -> 4 | K12: =COUNTIFS(Catálogo!$B$2:$B$648,$A12,Catálogo!$O$2:$O$648,"transcrito") -> 2 | L12: =SUMIFS(Cifras!$H$2:$H$399,Cifras!$A$2:$A$399,$A12) -> 6109 | M12: =IF(COUNTIFS(Cifras!$A$2:$A$399,$A12,Cifras!$D$2:$D$399,"distrito")>0,"Distrito",IF(COUNTIFS(Cifras!$A$2:$A$399,$A12,Cifras!$D$2:$D$399,"comuna")>0,"Comuna",IF(COUNTIFS(Cifras!$A$2:$A$399,$A12,Cifras!$D$2:$D$399,"partido")>0,"Partido",IF(COUNTIFS(Cifras!$A$2:$A$399,$A12,Cifras!$D$2:$D$399,"departamento")>0,"Departamento",IF(COUNTIFS(Cifras!$A$2:$A$399,$A12,Cifras!$D$2:$D$399,"provincia")>0,"Provincia",IF(COUNTIFS(Cifras!$A$2:$A$399,$A12,Cifras!$D$2:$D$399,"region")>0,"Región",IF(COUNTIFS(Cifras!$A$2:$A$399,$A12,Cifras!$D$2:$D$399,"pais")>0,"País","—"))))))) -> Departamento | N12: =IF(IFERROR(MATCH(TRUE,COUNTIFS(Catálogo!$J$2:$J$648,"*"&$A12&"*",Catálogo!$I$2:$I$648,"<>ausente",Catálogo!$M$2:$M$648,"completa",Catálogo!$Q$2:$Q$648,{1,2,3,4,5,6,7,8,9})>0,0),0)>0,INDEX(Niveles!$C$2:$C$10,IFERROR(MATCH(TRUE,COUNTIFS(Catálogo!$J$2:$J$648,"*"&$A12&"*",Catálogo!$I$2:$I$648,"<>ausente",Catálogo!$M$2:$M$648,"completa",Catálogo!$Q$2:$Q$648,{1,2,3,4,5,6,7,8,9})>0,0),0))&IF(AND(IFERROR(MATCH(TRUE,COUNTIFS(Catálogo!$J$2:$J$648,"*"&$A12&"*",Catálogo!$I$2:$I$648,"<>ausente",Catálogo!$M$2:$M$648,"parcial",Catálogo!$Q$2:$Q$648,{1,2,3,4,5,6,7,8,9})>0,0),0)>0,IFERROR(MATCH(TRUE,COUNTIFS(Catálogo!$J$2:$J$648,"*"&$A12&"*",Catálogo!$I$2:$I$648,"<>ausente",Catálogo!$M$2:$M$648,"parcial",Catálogo!$Q$2:$Q$648,{1,2,3,4,5,6,7,8,9})>0,0),0)<IFERROR(MATCH(TRUE,COUNTIFS(Catálogo!$J$2:$J$648,"*"&$A12&"*",Catálogo!$I$2:$I$648,"<>ausente",Catálogo!$M$2:$M$648,"completa",Catálogo!$Q$2:$Q$648,{1,2,3,4,5,6,7,8,9})>0,0),0)),"; "&LOWER(INDEX(Niveles!$C$2:$C$10,IFERROR(MATCH(TRUE,COUNTIFS(Catálogo!$J$2:$J$648,"*"&$A12&"*",Catálogo!$I$2:$I$648,"<>ausente",Catálogo!$M$2:$M$648,"parcial",Catálogo!$Q$2:$Q$648,{1,2,3,4,5,6,7,8,9})>0,0),0)))&" (parcial)",""),IF(IFERROR(MATCH(TRUE,COUNTIFS(Catálogo!$J$2:$J$648,"*"&$A12&"*",Catálogo!$I$2:$I$648,"<>ausente",Catálogo!$M$2:$M$648,"parcial",Catálogo!$Q$2:$Q$648,{1,2,3,4,5,6,7,8,9})>0,0),0)>0,INDEX(Niveles!$C$2:$C$10,IFERROR(MATCH(TRUE,COUNTIFS(Catálogo!$J$2:$J$648,"*"&$A12&"*",Catálogo!$I$2:$I$648,"<>ausente",Catálogo!$M$2:$M$648,"parcial",Catálogo!$Q$2:$Q$648,{1,2,3,4,5,6,7,8,9})>0,0),0))&" (parcial)","—")) -> Distrito | O12: =IF(COUNTIFS(Cifras!$A$2:$A$399,$A12,Cifras!$E$2:$E$399,"Sí",Cifras!$D$2:$D$399,"distrito")>0,"Distrito",IF(COUNTIFS(Cifras!$A$2:$A$399,$A12,Cifras!$E$2:$E$399,"Sí",Cifras!$D$2:$D$399,"comuna")>0,"Comuna",IF(COUNTIFS(Cifras!$A$2:$A$399,$A12,Cifras!$E$2:$E$399,"Sí",Cifras!$D$2:$D$399,"partido")>0,"Partido",IF(COUNTIFS(Cifras!$A$2:$A$399,$A12,Cifras!$E$2:$E$399,"Sí",Cifras!$D$2:$D$399,"departamento")>0,"Departamento",IF(COUNTIFS(Cifras!$A$2:$A$399,$A12,Cifras!$E$2:$E$399,"Sí",Cifras!$D$2:$D$399,"provincia")>0,"Provincia",IF(COUNTIFS(Cifras!$A$2:$A$399,$A12,Cifras!$E$2:$E$399,"Sí",Cifras!$D$2:$D$399,"region")>0,"Región",IF(COUNTIFS(Cifras!$A$2:$A$399,$A12,Cifras!$E$2:$E$399,"Sí",Cifras!$D$2:$D$399,"pais")>0,"País","—"))))))) -> Departamento | P12: =IF(IFERROR(MATCH(TRUE,COUNTIFS(Catálogo!$J$2:$J$648,"*"&$A12&"*",Catálogo!$I$2:$I$648,"<>ausente",Catálogo!$M$2:$M$648,"completa",Catálogo!$L$2:$L$648,"*area*",Catálogo!$Q$2:$Q$648,{1,2,3,4,5,6,7,8,9})>0,0),0)>0,INDEX(Niveles!$C$2:$C$10,IFERROR(MATCH(TRUE,COUNTIFS(Catálogo!$J$2:$J$648,"*"&$A12&"*",Catálogo!$I$2:$I$648,"<>ausente",Catálogo!$M$2:$M$648,"completa",Catálogo!$L$2:$L$648,"*area*",Catálogo!$Q$2:$Q$648,{1,2,3,4,5,6,7,8,9})>0,0),0))&IF(AND(IFERROR(MATCH(TRUE,COUNTIFS(Catálogo!$J$2:$J$648,"*"&$A12&"*",Catálogo!$I$2:$I$648,"<>ausente",Catálogo!$M$2:$M$648,"parcial",Catálogo!$L$2:$L$648,"*area*",Catálogo!$Q$2:$Q$648,{1,2,3,4,5,6,7,8,9})>0,0),0)>0,IFERROR(MATCH(TRUE,COUNTIFS(Catálogo!$J$2:$J$648,"*"&$A12&"*",Catálogo!$I$2:$I$648,"<>ausente",Catálogo!$M$2:$M$648,"parcial",Catálogo!$L$2:$L$648,"*area*",Catálogo!$Q$2:$Q$648,{1,2,3,4,5,6,7,8,9})>0,0),0)<IFERROR(MATCH(TRUE,COUNTIFS(Catálogo!$J$2:$J$648,"*"&$A12&"*",Catálogo!$I$2:$I$648,"<>ausente",Catálogo!$M$2:$M$648,"completa",Catálogo!$L$2:$L$648,"*area*",Catálogo!$Q$2:$Q$648,{1,2,3,4,5,6,7,8,9})>0,0),0)),"; "&LOWER(INDEX(Niveles!$C$2:$C$10,IFERROR(MATCH(TRUE,COUNTIFS(Catálogo!$J$2:$J$648,"*"&$A12&"*",Catálogo!$I$2:$I$648,"<>ausente",Catálogo!$M$2:$M$648,"parcial",Catálogo!$L$2:$L$648,"*area*",Catálogo!$Q$2:$Q$648,{1,2,3,4,5,6,7,8,9})>0,0),0)))&" (parcial)",""),IF(IFERROR(MATCH(TRUE,COUNTIFS(Catálogo!$J$2:$J$648,"*"&$A12&"*",Catálogo!$I$2:$I$648,"<>ausente",Catálogo!$M$2:$M$648,"parcial",Catálogo!$L$2:$L$648,"*area*",Catálogo!$Q$2:$Q$648,{1,2,3,4,5,6,7,8,9})>0,0),0)>0,INDEX(Niveles!$C$2:$C$10,IFERROR(MATCH(TRUE,COUNTIFS(Catálogo!$J$2:$J$648,"*"&$A12&"*",Catálogo!$I$2:$I$648,"<>ausente",Catálogo!$M$2:$M$648,"parcial",Catálogo!$L$2:$L$648,"*area*",Catálogo!$Q$2:$Q$648,{1,2,3,4,5,6,7,8,9})>0,0),0))&" (parcial)","—")) -> Departamento | Q12: =IF(COUNTIFS(Cifras!$A$2:$A$399,$A12,Cifras!$E$2:$E$399,"Sí",Cifras!$F$2:$F$399,"Sí",Cifras!$D$2:$D$399,"distrito")>0,"Distrito",IF(COUNTIFS(Cifras!$A$2:$A$399,$A12,Cifras!$E$2:$E$399,"Sí",Cifras!$F$2:$F$399,"Sí",Cifras!$D$2:$D$399,"comuna")>0,"Comuna",IF(COUNTIFS(Cifras!$A$2:$A$399,$A12,Cifras!$E$2:$E$399,"Sí",Cifras!$F$2:$F$399,"Sí",Cifras!$D$2:$D$399,"partido")>0,"Partido",IF(COUNTIFS(Cifras!$A$2:$A$399,$A12,Cifras!$E$2:$E$399,"Sí",Cifras!$F$2:$F$399,"Sí",Cifras!$D$2:$D$399,"departamento")>0,"Departamento",IF(COUNTIFS(Cifras!$A$2:$A$399,$A12,Cifras!$E$2:$E$399,"Sí",Cifras!$F$2:$F$399,"Sí",Cifras!$D$2:$D$399,"provincia")>0,"Provincia",IF(COUNTIFS(Cifras!$A$2:$A$399,$A12,Cifras!$E$2:$E$399,"Sí",Cifras!$F$2:$F$399,"Sí",Cifras!$D$2:$D$399,"region")>0,"Región",IF(COUNTIFS(Cifras!$A$2:$A$399,$A12,Cifras!$E$2:$E$399,"Sí",Cifras!$F$2:$F$399,"Sí",Cifras!$D$2:$D$399,"pais")>0,"País","—"))))))) -> — | R12: =IF(IFERROR(MATCH(TRUE,COUNTIFS(Catálogo!$J$2:$J$648,"*"&$A12&"*",Catálogo!$I$2:$I$648,"<>ausente",Catálogo!$M$2:$M$648,"completa",Catálogo!$L$2:$L$648,"*area*",Catálogo!$L$2:$L$648,"*sexo*",Catálogo!$Q$2:$Q$648,{1,2,3,4,5,6,7,8,9})>0,0),0)>0,INDEX(Niveles!$C$2:$C$10,IFERROR(MATCH(TRUE,COUNTIFS(Catálogo!$J$2:$J$648,"*"&$A12&"*",Catálogo!$I$2:$I$648,"<>ausente",Catálogo!$M$2:$M$648,"completa",Catálogo!$L$2:$L$648,"*area*",Catálogo!$L$2:$L$648,"*sexo*",Catálogo!$Q$2:$Q$648,{1,2,3,4,5,6,7,8,9})>0,0),0))&IF(AND(IFERROR(MATCH(TRUE,COUNTIFS(Catálogo!$J$2:$J$648,"*"&$A12&"*",Catálogo!$I$2:$I$648,"<>ausente",Catálogo!$M$2:$M$648,"parcial",Catálogo!$L$2:$L$648,"*area*",Catálogo!$L$2:$L$648,"*sexo*",Catálogo!$Q$2:$Q$648,{1,2,3,4,5,6,7,8,9})>0,0),0)>0,IFERROR(MATCH(TRUE,COUNTIFS(Catálogo!$J$2:$J$648,"*"&$A12&"*",Catálogo!$I$2:$I$648,"<>ausente",Catálogo!$M$2:$M$648,"parcial",Catálogo!$L$2:$L$648,"*area*",Catálogo!$L$2:$L$648,"*sexo*",Catálogo!$Q$2:$Q$648,{1,2,3,4,5,6,7,8,9})>0,0),0)<IFERROR(MATCH(TRUE,COUNTIFS(Catálogo!$J$2:$J$648,"*"&$A12&"*",Catálogo!$I$2:$I$648,"<>ausente",Catálogo!$M$2:$M$648,"completa",Catálogo!$L$2:$L$648,"*area*",Catálogo!$L$2:$L$648,"*sexo*",Catálogo!$Q$2:$Q$648,{1,2,3,4,5,6,7,8,9})>0,0),0)),"; "&LOWER(INDEX(Niveles!$C$2:$C$10,IFERROR(MATCH(TRUE,COUNTIFS(Catálogo!$J$2:$J$648,"*"&$A12&"*",Catálogo!$I$2:$I$648,"<>ausente",Catálogo!$M$2:$M$648,"parcial",Catálogo!$L$2:$L$648,"*area*",Catálogo!$L$2:$L$648,"*sexo*",Catálogo!$Q$2:$Q$648,{1,2,3,4,5,6,7,8,9})>0,0),0)))&" (parcial)",""),IF(IFERROR(MATCH(TRUE,COUNTIFS(Catálogo!$J$2:$J$648,"*"&$A12&"*",Catálogo!$I$2:$I$648,"<>ausente",Catálogo!$M$2:$M$648,"parcial",Catálogo!$L$2:$L$648,"*area*",Catálogo!$L$2:$L$648,"*sexo*",Catálogo!$Q$2:$Q$648,{1,2,3,4,5,6,7,8,9})>0,0),0)>0,INDEX(Niveles!$C$2:$C$10,IFERROR(MATCH(TRUE,COUNTIFS(Catálogo!$J$2:$J$648,"*"&$A12&"*",Catálogo!$I$2:$I$648,"<>ausente",Catálogo!$M$2:$M$648,"parcial",Catálogo!$L$2:$L$648,"*area*",Catálogo!$L$2:$L$648,"*sexo*",Catálogo!$Q$2:$Q$648,{1,2,3,4,5,6,7,8,9})>0,0),0))&" (parcial)","—")) -> — | S12: =IF(COUNTIFS(Cifras!$A$2:$A$399,$A12,Cifras!$F$2:$F$399,"Sí",Cifras!$G$2:$G$399,"Sí",Cifras!$D$2:$D$399,"distrito")>0,"Distrito",IF(COUNTIFS(Cifras!$A$2:$A$399,$A12,Cifras!$F$2:$F$399,"Sí",Cifras!$G$2:$G$399,"Sí",Cifras!$D$2:$D$399,"comuna")>0,"Comuna",IF(COUNTIFS(Cifras!$A$2:$A$399,$A12,Cifras!$F$2:$F$399,"Sí",Cifras!$G$2:$G$399,"Sí",Cifras!$D$2:$D$399,"partido")>0,"Partido",IF(COUNTIFS(Cifras!$A$2:$A$399,$A12,Cifras!$F$2:$F$399,"Sí",Cifras!$G$2:$G$399,"Sí",Cifras!$D$2:$D$399,"departamento")>0,"Departamento",IF(COUNTIFS(Cifras!$A$2:$A$399,$A12,Cifras!$F$2:$F$399,"Sí",Cifras!$G$2:$G$399,"Sí",Cifras!$D$2:$D$399,"provincia")>0,"Provincia",IF(COUNTIFS(Cifras!$A$2:$A$399,$A12,Cifras!$F$2:$F$399,"Sí",Cifras!$G$2:$G$399,"Sí",Cifras!$D$2:$D$399,"region")>0,"Región",IF(COUNTIFS(Cifras!$A$2:$A$399,$A12,Cifras!$F$2:$F$399,"Sí",Cifras!$G$2:$G$399,"Sí",Cifras!$D$2:$D$399,"pais")>0,"País","—"))))))) -> Departamento | T12: =IF(IFERROR(MATCH(TRUE,COUNTIFS(Catálogo!$J$2:$J$648,"*"&$A12&"*",Catálogo!$I$2:$I$648,"<>ausente",Catálogo!$M$2:$M$648,"completa",Catálogo!$L$2:$L$648,"*sexo*",Catálogo!$L$2:$L$648,"*edad*",Catálogo!$Q$2:$Q$648,{1,2,3,4,5,6,7,8,9})>0,0),0)>0,INDEX(Niveles!$C$2:$C$10,IFERROR(MATCH(TRUE,COUNTIFS(Catálogo!$J$2:$J$648,"*"&$A12&"*",Catálogo!$I$2:$I$648,"<>ausente",Catálogo!$M$2:$M$648,"completa",Catálogo!$L$2:$L$648,"*sexo*",Catálogo!$L$2:$L$648,"*edad*",Catálogo!$Q$2:$Q$648,{1,2,3,4,5,6,7,8,9})>0,0),0))&IF(AND(IFERROR(MATCH(TRUE,COUNTIFS(Catálogo!$J$2:$J$648,"*"&$A12&"*",Catálogo!$I$2:$I$648,"<>ausente",Catálogo!$M$2:$M$648,"parcial",Catálogo!$L$2:$L$648,"*sexo*",Catálogo!$L$2:$L$648,"*edad*",Catálogo!$Q$2:$Q$648,{1,2,3,4,5,6,7,8,9})>0,0),0)>0,IFERROR(MATCH(TRUE,COUNTIFS(Catálogo!$J$2:$J$648,"*"&$A12&"*",Catálogo!$I$2:$I$648,"<>ausente",Catálogo!$M$2:$M$648,"parcial",Catálogo!$L$2:$L$648,"*sexo*",Catálogo!$L$2:$L$648,"*edad*",Catálogo!$Q$2:$Q$648,{1,2,3,4,5,6,7,8,9})>0,0),0)<IFERROR(MATCH(TRUE,COUNTIFS(Catálogo!$J$2:$J$648,"*"&$A12&"*",Catálogo!$I$2:$I$648,"<>ausente",Catálogo!$M$2:$M$648,"completa",Catálogo!$L$2:$L$648,"*sexo*",Catálogo!$L$2:$L$648,"*edad*",Catálogo!$Q$2:$Q$648,{1,2,3,4,5,6,7,8,9})>0,0),0)),"; "&LOWER(INDEX(Niveles!$C$2:$C$10,IFERROR(MATCH(TRUE,COUNTIFS(Catálogo!$J$2:$J$648,"*"&$A12&"*",Catálogo!$I$2:$I$648,"<>ausente",Catálogo!$M$2:$M$648,"parcial",Catálogo!$L$2:$L$648,"*sexo*",Catálogo!$L$2:$L$648,"*edad*",Catálogo!$Q$2:$Q$648,{1,2,3,4,5,6,7,8,9})>0,0),0)))&" (parcial)",""),IF(IFERROR(MATCH(TRUE,COUNTIFS(Catálogo!$J$2:$J$648,"*"&$A12&"*",Catálogo!$I$2:$I$648,"<>ausente",Catálogo!$M$2:$M$648,"parcial",Catálogo!$L$2:$L$648,"*sexo*",Catálogo!$L$2:$L$648,"*edad*",Catálogo!$Q$2:$Q$648,{1,2,3,4,5,6,7,8,9})>0,0),0)>0,INDEX(Niveles!$C$2:$C$10,IFERROR(MATCH(TRUE,COUNTIFS(Catálogo!$J$2:$J$648,"*"&$A12&"*",Catálogo!$I$2:$I$648,"<>ausente",Catálogo!$M$2:$M$648,"parcial",Catálogo!$L$2:$L$648,"*sexo*",Catálogo!$L$2:$L$648,"*edad*",Catálogo!$Q$2:$Q$648,{1,2,3,4,5,6,7,8,9})>0,0),0))&" (parcial)","—")) -> Distrito | U12: =SUMIFS(Cifras!$J$2:$J$399,Cifras!$A$2:$A$399,$A12) -> 60 | V12: Núcleo completo | W12: Opcional: subdelegación y distrito × sexo × edad, con urbana y rural del total (bloques provinciales de los tomos I a IV). El área no viene por sexo. | X12: Departamento × sexo × edad en 26 grupos (meses bajo 1 año) y departamento × área del cuadro general del tomo IV (págs. 467-486, leído en la copia de Memoria Chilena porque el PDF del INE está a ~72 dpi); provincias = 1952 C5, decenios del país = 1952 C7, área = 1920 C3. Muchas erratas del original anotadas; Colchagua menores de 2 años desde el tomo II (pág. 511).
A13: 1907 | B13: pub_1907 | C13: 1277 | D13: =COUNTIFS(Catálogo!$B$2:$B$648,$A13) -> 34 | E13: =COUNTIFS(Catálogo!$B$2:$B$648,$A13,Catálogo!$F$2:$F$648,"cuadro") -> 5 | F13: =COUNTIFS(Catálogo!$B$2:$B$648,$A13,Catálogo!$F$2:$F$648,"bloque") -> 25 | G13: =COUNTIFS(Catálogo!$B$2:$B$648,$A13,Catálogo!$F$2:$F$648,"texto") -> 4 | H13: =COUNTIFS(Catálogo!$B$2:$B$648,$A13,Catálogo!$I$2:$I$648,"verificada") -> 7 | I13: =COUNTIFS(Catálogo!$B$2:$B$648,$A13,Catálogo!$I$2:$I$648,"estimada") -> 27 | J13: =COUNTIFS(Catálogo!$B$2:$B$648,$A13,Catálogo!$I$2:$I$648,"desconocida")+COUNTIFS(Catálogo!$B$2:$B$648,$A13,Catálogo!$I$2:$I$648,"ausente") -> 0 | K13: =COUNTIFS(Catálogo!$B$2:$B$648,$A13,Catálogo!$O$2:$O$648,"transcrito") -> 2 | L13: =SUMIFS(Cifras!$H$2:$H$399,Cifras!$A$2:$A$399,$A13) -> 5980 | M13: =IF(COUNTIFS(Cifras!$A$2:$A$399,$A13,Cifras!$D$2:$D$399,"distrito")>0,"Distrito",IF(COUNTIFS(Cifras!$A$2:$A$399,$A13,Cifras!$D$2:$D$399,"comuna")>0,"Comuna",IF(COUNTIFS(Cifras!$A$2:$A$399,$A13,Cifras!$D$2:$D$399,"partido")>0,"Partido",IF(COUNTIFS(Cifras!$A$2:$A$399,$A13,Cifras!$D$2:$D$399,"departamento")>0,"Departamento",IF(COUNTIFS(Cifras!$A$2:$A$399,$A13,Cifras!$D$2:$D$399,"provincia")>0,"Provincia",IF(COUNTIFS(Cifras!$A$2:$A$399,$A13,Cifras!$D$2:$D$399,"region")>0,"Región",IF(COUNTIFS(Cifras!$A$2:$A$399,$A13,Cifras!$D$2:$D$399,"pais")>0,"País","—"))))))) -> Departamento | N13: =IF(IFERROR(MATCH(TRUE,COUNTIFS(Catálogo!$J$2:$J$648,"*"&$A13&"*",Catálogo!$I$2:$I$648,"<>ausente",Catálogo!$M$2:$M$648,"completa",Catálogo!$Q$2:$Q$648,{1,2,3,4,5,6,7,8,9})>0,0),0)>0,INDEX(Niveles!$C$2:$C$10,IFERROR(MATCH(TRUE,COUNTIFS(Catálogo!$J$2:$J$648,"*"&$A13&"*",Catálogo!$I$2:$I$648,"<>ausente",Catálogo!$M$2:$M$648,"completa",Catálogo!$Q$2:$Q$648,{1,2,3,4,5,6,7,8,9})>0,0),0))&IF(AND(IFERROR(MATCH(TRUE,COUNTIFS(Catálogo!$J$2:$J$648,"*"&$A13&"*",Catálogo!$I$2:$I$648,"<>ausente",Catálogo!$M$2:$M$648,"parcial",Catálogo!$Q$2:$Q$648,{1,2,3,4,5,6,7,8,9})>0,0),0)>0,IFERROR(MATCH(TRUE,COUNTIFS(Catálogo!$J$2:$J$648,"*"&$A13&"*",Catálogo!$I$2:$I$648,"<>ausente",Catálogo!$M$2:$M$648,"parcial",Catálogo!$Q$2:$Q$648,{1,2,3,4,5,6,7,8,9})>0,0),0)<IFERROR(MATCH(TRUE,COUNTIFS(Catálogo!$J$2:$J$648,"*"&$A13&"*",Catálogo!$I$2:$I$648,"<>ausente",Catálogo!$M$2:$M$648,"completa",Catálogo!$Q$2:$Q$648,{1,2,3,4,5,6,7,8,9})>0,0),0)),"; "&LOWER(INDEX(Niveles!$C$2:$C$10,IFERROR(MATCH(TRUE,COUNTIFS(Catálogo!$J$2:$J$648,"*"&$A13&"*",Catálogo!$I$2:$I$648,"<>ausente",Catálogo!$M$2:$M$648,"parcial",Catálogo!$Q$2:$Q$648,{1,2,3,4,5,6,7,8,9})>0,0),0)))&" (parcial)",""),IF(IFERROR(MATCH(TRUE,COUNTIFS(Catálogo!$J$2:$J$648,"*"&$A13&"*",Catálogo!$I$2:$I$648,"<>ausente",Catálogo!$M$2:$M$648,"parcial",Catálogo!$Q$2:$Q$648,{1,2,3,4,5,6,7,8,9})>0,0),0)>0,INDEX(Niveles!$C$2:$C$10,IFERROR(MATCH(TRUE,COUNTIFS(Catálogo!$J$2:$J$648,"*"&$A13&"*",Catálogo!$I$2:$I$648,"<>ausente",Catálogo!$M$2:$M$648,"parcial",Catálogo!$Q$2:$Q$648,{1,2,3,4,5,6,7,8,9})>0,0),0))&" (parcial)","—")) -> Distrito | O13: =IF(COUNTIFS(Cifras!$A$2:$A$399,$A13,Cifras!$E$2:$E$399,"Sí",Cifras!$D$2:$D$399,"distrito")>0,"Distrito",IF(COUNTIFS(Cifras!$A$2:$A$399,$A13,Cifras!$E$2:$E$399,"Sí",Cifras!$D$2:$D$399,"comuna")>0,"Comuna",IF(COUNTIFS(Cifras!$A$2:$A$399,$A13,Cifras!$E$2:$E$399,"Sí",Cifras!$D$2:$D$399,"partido")>0,"Partido",IF(COUNTIFS(Cifras!$A$2:$A$399,$A13,Cifras!$E$2:$E$399,"Sí",Cifras!$D$2:$D$399,"departamento")>0,"Departamento",IF(COUNTIFS(Cifras!$A$2:$A$399,$A13,Cifras!$E$2:$E$399,"Sí",Cifras!$D$2:$D$399,"provincia")>0,"Provincia",IF(COUNTIFS(Cifras!$A$2:$A$399,$A13,Cifras!$E$2:$E$399,"Sí",Cifras!$D$2:$D$399,"region")>0,"Región",IF(COUNTIFS(Cifras!$A$2:$A$399,$A13,Cifras!$E$2:$E$399,"Sí",Cifras!$D$2:$D$399,"pais")>0,"País","—"))))))) -> Departamento | P13: =IF(IFERROR(MATCH(TRUE,COUNTIFS(Catálogo!$J$2:$J$648,"*"&$A13&"*",Catálogo!$I$2:$I$648,"<>ausente",Catálogo!$M$2:$M$648,"completa",Catálogo!$L$2:$L$648,"*area*",Catálogo!$Q$2:$Q$648,{1,2,3,4,5,6,7,8,9})>0,0),0)>0,INDEX(Niveles!$C$2:$C$10,IFERROR(MATCH(TRUE,COUNTIFS(Catálogo!$J$2:$J$648,"*"&$A13&"*",Catálogo!$I$2:$I$648,"<>ausente",Catálogo!$M$2:$M$648,"completa",Catálogo!$L$2:$L$648,"*area*",Catálogo!$Q$2:$Q$648,{1,2,3,4,5,6,7,8,9})>0,0),0))&IF(AND(IFERROR(MATCH(TRUE,COUNTIFS(Catálogo!$J$2:$J$648,"*"&$A13&"*",Catálogo!$I$2:$I$648,"<>ausente",Catálogo!$M$2:$M$648,"parcial",Catálogo!$L$2:$L$648,"*area*",Catálogo!$Q$2:$Q$648,{1,2,3,4,5,6,7,8,9})>0,0),0)>0,IFERROR(MATCH(TRUE,COUNTIFS(Catálogo!$J$2:$J$648,"*"&$A13&"*",Catálogo!$I$2:$I$648,"<>ausente",Catálogo!$M$2:$M$648,"parcial",Catálogo!$L$2:$L$648,"*area*",Catálogo!$Q$2:$Q$648,{1,2,3,4,5,6,7,8,9})>0,0),0)<IFERROR(MATCH(TRUE,COUNTIFS(Catálogo!$J$2:$J$648,"*"&$A13&"*",Catálogo!$I$2:$I$648,"<>ausente",Catálogo!$M$2:$M$648,"completa",Catálogo!$L$2:$L$648,"*area*",Catálogo!$Q$2:$Q$648,{1,2,3,4,5,6,7,8,9})>0,0),0)),"; "&LOWER(INDEX(Niveles!$C$2:$C$10,IFERROR(MATCH(TRUE,COUNTIFS(Catálogo!$J$2:$J$648,"*"&$A13&"*",Catálogo!$I$2:$I$648,"<>ausente",Catálogo!$M$2:$M$648,"parcial",Catálogo!$L$2:$L$648,"*area*",Catálogo!$Q$2:$Q$648,{1,2,3,4,5,6,7,8,9})>0,0),0)))&" (parcial)",""),IF(IFERROR(MATCH(TRUE,COUNTIFS(Catálogo!$J$2:$J$648,"*"&$A13&"*",Catálogo!$I$2:$I$648,"<>ausente",Catálogo!$M$2:$M$648,"parcial",Catálogo!$L$2:$L$648,"*area*",Catálogo!$Q$2:$Q$648,{1,2,3,4,5,6,7,8,9})>0,0),0)>0,INDEX(Niveles!$C$2:$C$10,IFERROR(MATCH(TRUE,COUNTIFS(Catálogo!$J$2:$J$648,"*"&$A13&"*",Catálogo!$I$2:$I$648,"<>ausente",Catálogo!$M$2:$M$648,"parcial",Catálogo!$L$2:$L$648,"*area*",Catálogo!$Q$2:$Q$648,{1,2,3,4,5,6,7,8,9})>0,0),0))&" (parcial)","—")) -> Distrito | Q13: =IF(COUNTIFS(Cifras!$A$2:$A$399,$A13,Cifras!$E$2:$E$399,"Sí",Cifras!$F$2:$F$399,"Sí",Cifras!$D$2:$D$399,"distrito")>0,"Distrito",IF(COUNTIFS(Cifras!$A$2:$A$399,$A13,Cifras!$E$2:$E$399,"Sí",Cifras!$F$2:$F$399,"Sí",Cifras!$D$2:$D$399,"comuna")>0,"Comuna",IF(COUNTIFS(Cifras!$A$2:$A$399,$A13,Cifras!$E$2:$E$399,"Sí",Cifras!$F$2:$F$399,"Sí",Cifras!$D$2:$D$399,"partido")>0,"Partido",IF(COUNTIFS(Cifras!$A$2:$A$399,$A13,Cifras!$E$2:$E$399,"Sí",Cifras!$F$2:$F$399,"Sí",Cifras!$D$2:$D$399,"departamento")>0,"Departamento",IF(COUNTIFS(Cifras!$A$2:$A$399,$A13,Cifras!$E$2:$E$399,"Sí",Cifras!$F$2:$F$399,"Sí",Cifras!$D$2:$D$399,"provincia")>0,"Provincia",IF(COUNTIFS(Cifras!$A$2:$A$399,$A13,Cifras!$E$2:$E$399,"Sí",Cifras!$F$2:$F$399,"Sí",Cifras!$D$2:$D$399,"region")>0,"Región",IF(COUNTIFS(Cifras!$A$2:$A$399,$A13,Cifras!$E$2:$E$399,"Sí",Cifras!$F$2:$F$399,"Sí",Cifras!$D$2:$D$399,"pais")>0,"País","—"))))))) -> Departamento | R13: =IF(IFERROR(MATCH(TRUE,COUNTIFS(Catálogo!$J$2:$J$648,"*"&$A13&"*",Catálogo!$I$2:$I$648,"<>ausente",Catálogo!$M$2:$M$648,"completa",Catálogo!$L$2:$L$648,"*area*",Catálogo!$L$2:$L$648,"*sexo*",Catálogo!$Q$2:$Q$648,{1,2,3,4,5,6,7,8,9})>0,0),0)>0,INDEX(Niveles!$C$2:$C$10,IFERROR(MATCH(TRUE,COUNTIFS(Catálogo!$J$2:$J$648,"*"&$A13&"*",Catálogo!$I$2:$I$648,"<>ausente",Catálogo!$M$2:$M$648,"completa",Catálogo!$L$2:$L$648,"*area*",Catálogo!$L$2:$L$648,"*sexo*",Catálogo!$Q$2:$Q$648,{1,2,3,4,5,6,7,8,9})>0,0),0))&IF(AND(IFERROR(MATCH(TRUE,COUNTIFS(Catálogo!$J$2:$J$648,"*"&$A13&"*",Catálogo!$I$2:$I$648,"<>ausente",Catálogo!$M$2:$M$648,"parcial",Catálogo!$L$2:$L$648,"*area*",Catálogo!$L$2:$L$648,"*sexo*",Catálogo!$Q$2:$Q$648,{1,2,3,4,5,6,7,8,9})>0,0),0)>0,IFERROR(MATCH(TRUE,COUNTIFS(Catálogo!$J$2:$J$648,"*"&$A13&"*",Catálogo!$I$2:$I$648,"<>ausente",Catálogo!$M$2:$M$648,"parcial",Catálogo!$L$2:$L$648,"*area*",Catálogo!$L$2:$L$648,"*sexo*",Catálogo!$Q$2:$Q$648,{1,2,3,4,5,6,7,8,9})>0,0),0)<IFERROR(MATCH(TRUE,COUNTIFS(Catálogo!$J$2:$J$648,"*"&$A13&"*",Catálogo!$I$2:$I$648,"<>ausente",Catálogo!$M$2:$M$648,"completa",Catálogo!$L$2:$L$648,"*area*",Catálogo!$L$2:$L$648,"*sexo*",Catálogo!$Q$2:$Q$648,{1,2,3,4,5,6,7,8,9})>0,0),0)),"; "&LOWER(INDEX(Niveles!$C$2:$C$10,IFERROR(MATCH(TRUE,COUNTIFS(Catálogo!$J$2:$J$648,"*"&$A13&"*",Catálogo!$I$2:$I$648,"<>ausente",Catálogo!$M$2:$M$648,"parcial",Catálogo!$L$2:$L$648,"*area*",Catálogo!$L$2:$L$648,"*sexo*",Catálogo!$Q$2:$Q$648,{1,2,3,4,5,6,7,8,9})>0,0),0)))&" (parcial)",""),IF(IFERROR(MATCH(TRUE,COUNTIFS(Catálogo!$J$2:$J$648,"*"&$A13&"*",Catálogo!$I$2:$I$648,"<>ausente",Catálogo!$M$2:$M$648,"parcial",Catálogo!$L$2:$L$648,"*area*",Catálogo!$L$2:$L$648,"*sexo*",Catálogo!$Q$2:$Q$648,{1,2,3,4,5,6,7,8,9})>0,0),0)>0,INDEX(Niveles!$C$2:$C$10,IFERROR(MATCH(TRUE,COUNTIFS(Catálogo!$J$2:$J$648,"*"&$A13&"*",Catálogo!$I$2:$I$648,"<>ausente",Catálogo!$M$2:$M$648,"parcial",Catálogo!$L$2:$L$648,"*area*",Catálogo!$L$2:$L$648,"*sexo*",Catálogo!$Q$2:$Q$648,{1,2,3,4,5,6,7,8,9})>0,0),0))&" (parcial)","—")) -> Distrito | S13: =IF(COUNTIFS(Cifras!$A$2:$A$399,$A13,Cifras!$F$2:$F$399,"Sí",Cifras!$G$2:$G$399,"Sí",Cifras!$D$2:$D$399,"distrito")>0,"Distrito",IF(COUNTIFS(Cifras!$A$2:$A$399,$A13,Cifras!$F$2:$F$399,"Sí",Cifras!$G$2:$G$399,"Sí",Cifras!$D$2:$D$399,"comuna")>0,"Comuna",IF(COUNTIFS(Cifras!$A$2:$A$399,$A13,Cifras!$F$2:$F$399,"Sí",Cifras!$G$2:$G$399,"Sí",Cifras!$D$2:$D$399,"partido")>0,"Partido",IF(COUNTIFS(Cifras!$A$2:$A$399,$A13,Cifras!$F$2:$F$399,"Sí",Cifras!$G$2:$G$399,"Sí",Cifras!$D$2:$D$399,"departamento")>0,"Departamento",IF(COUNTIFS(Cifras!$A$2:$A$399,$A13,Cifras!$F$2:$F$399,"Sí",Cifras!$G$2:$G$399,"Sí",Cifras!$D$2:$D$399,"provincia")>0,"Provincia",IF(COUNTIFS(Cifras!$A$2:$A$399,$A13,Cifras!$F$2:$F$399,"Sí",Cifras!$G$2:$G$399,"Sí",Cifras!$D$2:$D$399,"region")>0,"Región",IF(COUNTIFS(Cifras!$A$2:$A$399,$A13,Cifras!$F$2:$F$399,"Sí",Cifras!$G$2:$G$399,"Sí",Cifras!$D$2:$D$399,"pais")>0,"País","—"))))))) -> Departamento | T13: =IF(IFERROR(MATCH(TRUE,COUNTIFS(Catálogo!$J$2:$J$648,"*"&$A13&"*",Catálogo!$I$2:$I$648,"<>ausente",Catálogo!$M$2:$M$648,"completa",Catálogo!$L$2:$L$648,"*sexo*",Catálogo!$L$2:$L$648,"*edad*",Catálogo!$Q$2:$Q$648,{1,2,3,4,5,6,7,8,9})>0,0),0)>0,INDEX(Niveles!$C$2:$C$10,IFERROR(MATCH(TRUE,COUNTIFS(Catálogo!$J$2:$J$648,"*"&$A13&"*",Catálogo!$I$2:$I$648,"<>ausente",Catálogo!$M$2:$M$648,"completa",Catálogo!$L$2:$L$648,"*sexo*",Catálogo!$L$2:$L$648,"*edad*",Catálogo!$Q$2:$Q$648,{1,2,3,4,5,6,7,8,9})>0,0),0))&IF(AND(IFERROR(MATCH(TRUE,COUNTIFS(Catálogo!$J$2:$J$648,"*"&$A13&"*",Catálogo!$I$2:$I$648,"<>ausente",Catálogo!$M$2:$M$648,"parcial",Catálogo!$L$2:$L$648,"*sexo*",Catálogo!$L$2:$L$648,"*edad*",Catálogo!$Q$2:$Q$648,{1,2,3,4,5,6,7,8,9})>0,0),0)>0,IFERROR(MATCH(TRUE,COUNTIFS(Catálogo!$J$2:$J$648,"*"&$A13&"*",Catálogo!$I$2:$I$648,"<>ausente",Catálogo!$M$2:$M$648,"parcial",Catálogo!$L$2:$L$648,"*sexo*",Catálogo!$L$2:$L$648,"*edad*",Catálogo!$Q$2:$Q$648,{1,2,3,4,5,6,7,8,9})>0,0),0)<IFERROR(MATCH(TRUE,COUNTIFS(Catálogo!$J$2:$J$648,"*"&$A13&"*",Catálogo!$I$2:$I$648,"<>ausente",Catálogo!$M$2:$M$648,"completa",Catálogo!$L$2:$L$648,"*sexo*",Catálogo!$L$2:$L$648,"*edad*",Catálogo!$Q$2:$Q$648,{1,2,3,4,5,6,7,8,9})>0,0),0)),"; "&LOWER(INDEX(Niveles!$C$2:$C$10,IFERROR(MATCH(TRUE,COUNTIFS(Catálogo!$J$2:$J$648,"*"&$A13&"*",Catálogo!$I$2:$I$648,"<>ausente",Catálogo!$M$2:$M$648,"parcial",Catálogo!$L$2:$L$648,"*sexo*",Catálogo!$L$2:$L$648,"*edad*",Catálogo!$Q$2:$Q$648,{1,2,3,4,5,6,7,8,9})>0,0),0)))&" (parcial)",""),IF(IFERROR(MATCH(TRUE,COUNTIFS(Catálogo!$J$2:$J$648,"*"&$A13&"*",Catálogo!$I$2:$I$648,"<>ausente",Catálogo!$M$2:$M$648,"parcial",Catálogo!$L$2:$L$648,"*sexo*",Catálogo!$L$2:$L$648,"*edad*",Catálogo!$Q$2:$Q$648,{1,2,3,4,5,6,7,8,9})>0,0),0)>0,INDEX(Niveles!$C$2:$C$10,IFERROR(MATCH(TRUE,COUNTIFS(Catálogo!$J$2:$J$648,"*"&$A13&"*",Catálogo!$I$2:$I$648,"<>ausente",Catálogo!$M$2:$M$648,"parcial",Catálogo!$L$2:$L$648,"*sexo*",Catálogo!$L$2:$L$648,"*edad*",Catálogo!$Q$2:$Q$648,{1,2,3,4,5,6,7,8,9})>0,0),0))&" (parcial)","—")) -> Departamento | U13: =SUMIFS(Cifras!$J$2:$J$399,Cifras!$A$2:$A$399,$A13) -> 6 | V13: Núcleo completo | W13: Opcional: subdelegación y distrito × área × sexo (cuadro 1 de cada departamento). La edad no viene por área ni bajo departamento. | X13: Departamento × área × sexo (cuadro 1 del resumen de cada provincia; = 1920 C3 salvo Quillota, que cuenta 2 694 personas como urbanas que el total de Valparaíso pone como rurales) y departamento × sexo × edad en 18 grupos (cuadro 7 de cada departamento; provincias = 1952 C5, decenios = 1952 C7). Tacna incluye Tarata.
A14: 1920 | B14: pub_1920 | C14: 625 | D14: =COUNTIFS(Catálogo!$B$2:$B$648,$A14) -> 27 | E14: =COUNTIFS(Catálogo!$B$2:$B$648,$A14,Catálogo!$F$2:$F$648,"cuadro") -> 26 | F14: =COUNTIFS(Catálogo!$B$2:$B$648,$A14,Catálogo!$F$2:$F$648,"bloque") -> 0 | G14: =COUNTIFS(Catálogo!$B$2:$B$648,$A14,Catálogo!$F$2:$F$648,"texto") -> 1 | H14: =COUNTIFS(Catálogo!$B$2:$B$648,$A14,Catálogo!$I$2:$I$648,"verificada") -> 15 | I14: =COUNTIFS(Catálogo!$B$2:$B$648,$A14,Catálogo!$I$2:$I$648,"estimada") -> 12 | J14: =COUNTIFS(Catálogo!$B$2:$B$648,$A14,Catálogo!$I$2:$I$648,"desconocida")+COUNTIFS(Catálogo!$B$2:$B$648,$A14,Catálogo!$I$2:$I$648,"ausente") -> 0 | K14: =COUNTIFS(Catálogo!$B$2:$B$648,$A14,Catálogo!$O$2:$O$648,"transcrito") -> 4 | L14: =SUMIFS(Cifras!$H$2:$H$399,Cifras!$A$2:$A$399,$A14) -> 8743 | M14: =IF(COUNTIFS(Cifras!$A$2:$A$399,$A14,Cifras!$D$2:$D$399,"distrito")>0,"Distrito",IF(COUNTIFS(Cifras!$A$2:$A$399,$A14,Cifras!$D$2:$D$399,"comuna")>0,"Comuna",IF(COUNTIFS(Cifras!$A$2:$A$399,$A14,Cifras!$D$2:$D$399,"partido")>0,"Partido",IF(COUNTIFS(Cifras!$A$2:$A$399,$A14,Cifras!$D$2:$D$399,"departamento")>0,"Departamento",IF(COUNTIFS(Cifras!$A$2:$A$399,$A14,Cifras!$D$2:$D$399,"provincia")>0,"Provincia",IF(COUNTIFS(Cifras!$A$2:$A$399,$A14,Cifras!$D$2:$D$399,"region")>0,"Región",IF(COUNTIFS(Cifras!$A$2:$A$399,$A14,Cifras!$D$2:$D$399,"pais")>0,"País","—"))))))) -> Departamento | N14: =IF(IFERROR(MATCH(TRUE,COUNTIFS(Catálogo!$J$2:$J$648,"*"&$A14&"*",Catálogo!$I$2:$I$648,"<>ausente",Catálogo!$M$2:$M$648,"completa",Catálogo!$Q$2:$Q$648,{1,2,3,4,5,6,7,8,9})>0,0),0)>0,INDEX(Niveles!$C$2:$C$10,IFERROR(MATCH(TRUE,COUNTIFS(Catálogo!$J$2:$J$648,"*"&$A14&"*",Catálogo!$I$2:$I$648,"<>ausente",Catálogo!$M$2:$M$648,"completa",Catálogo!$Q$2:$Q$648,{1,2,3,4,5,6,7,8,9})>0,0),0))&IF(AND(IFERROR(MATCH(TRUE,COUNTIFS(Catálogo!$J$2:$J$648,"*"&$A14&"*",Catálogo!$I$2:$I$648,"<>ausente",Catálogo!$M$2:$M$648,"parcial",Catálogo!$Q$2:$Q$648,{1,2,3,4,5,6,7,8,9})>0,0),0)>0,IFERROR(MATCH(TRUE,COUNTIFS(Catálogo!$J$2:$J$648,"*"&$A14&"*",Catálogo!$I$2:$I$648,"<>ausente",Catálogo!$M$2:$M$648,"parcial",Catálogo!$Q$2:$Q$648,{1,2,3,4,5,6,7,8,9})>0,0),0)<IFERROR(MATCH(TRUE,COUNTIFS(Catálogo!$J$2:$J$648,"*"&$A14&"*",Catálogo!$I$2:$I$648,"<>ausente",Catálogo!$M$2:$M$648,"completa",Catálogo!$Q$2:$Q$648,{1,2,3,4,5,6,7,8,9})>0,0),0)),"; "&LOWER(INDEX(Niveles!$C$2:$C$10,IFERROR(MATCH(TRUE,COUNTIFS(Catálogo!$J$2:$J$648,"*"&$A14&"*",Catálogo!$I$2:$I$648,"<>ausente",Catálogo!$M$2:$M$648,"parcial",Catálogo!$Q$2:$Q$648,{1,2,3,4,5,6,7,8,9})>0,0),0)))&" (parcial)",""),IF(IFERROR(MATCH(TRUE,COUNTIFS(Catálogo!$J$2:$J$648,"*"&$A14&"*",Catálogo!$I$2:$I$648,"<>ausente",Catálogo!$M$2:$M$648,"parcial",Catálogo!$Q$2:$Q$648,{1,2,3,4,5,6,7,8,9})>0,0),0)>0,INDEX(Niveles!$C$2:$C$10,IFERROR(MATCH(TRUE,COUNTIFS(Catálogo!$J$2:$J$648,"*"&$A14&"*",Catálogo!$I$2:$I$648,"<>ausente",Catálogo!$M$2:$M$648,"parcial",Catálogo!$Q$2:$Q$648,{1,2,3,4,5,6,7,8,9})>0,0),0))&" (parcial)","—")) -> Distrito | O14: =IF(COUNTIFS(Cifras!$A$2:$A$399,$A14,Cifras!$E$2:$E$399,"Sí",Cifras!$D$2:$D$399,"distrito")>0,"Distrito",IF(COUNTIFS(Cifras!$A$2:$A$399,$A14,Cifras!$E$2:$E$399,"Sí",Cifras!$D$2:$D$399,"comuna")>0,"Comuna",IF(COUNTIFS(Cifras!$A$2:$A$399,$A14,Cifras!$E$2:$E$399,"Sí",Cifras!$D$2:$D$399,"partido")>0,"Partido",IF(COUNTIFS(Cifras!$A$2:$A$399,$A14,Cifras!$E$2:$E$399,"Sí",Cifras!$D$2:$D$399,"departamento")>0,"Departamento",IF(COUNTIFS(Cifras!$A$2:$A$399,$A14,Cifras!$E$2:$E$399,"Sí",Cifras!$D$2:$D$399,"provincia")>0,"Provincia",IF(COUNTIFS(Cifras!$A$2:$A$399,$A14,Cifras!$E$2:$E$399,"Sí",Cifras!$D$2:$D$399,"region")>0,"Región",IF(COUNTIFS(Cifras!$A$2:$A$399,$A14,Cifras!$E$2:$E$399,"Sí",Cifras!$D$2:$D$399,"pais")>0,"País","—"))))))) -> Departamento | P14: =IF(IFERROR(MATCH(TRUE,COUNTIFS(Catálogo!$J$2:$J$648,"*"&$A14&"*",Catálogo!$I$2:$I$648,"<>ausente",Catálogo!$M$2:$M$648,"completa",Catálogo!$L$2:$L$648,"*area*",Catálogo!$Q$2:$Q$648,{1,2,3,4,5,6,7,8,9})>0,0),0)>0,INDEX(Niveles!$C$2:$C$10,IFERROR(MATCH(TRUE,COUNTIFS(Catálogo!$J$2:$J$648,"*"&$A14&"*",Catálogo!$I$2:$I$648,"<>ausente",Catálogo!$M$2:$M$648,"completa",Catálogo!$L$2:$L$648,"*area*",Catálogo!$Q$2:$Q$648,{1,2,3,4,5,6,7,8,9})>0,0),0))&IF(AND(IFERROR(MATCH(TRUE,COUNTIFS(Catálogo!$J$2:$J$648,"*"&$A14&"*",Catálogo!$I$2:$I$648,"<>ausente",Catálogo!$M$2:$M$648,"parcial",Catálogo!$L$2:$L$648,"*area*",Catálogo!$Q$2:$Q$648,{1,2,3,4,5,6,7,8,9})>0,0),0)>0,IFERROR(MATCH(TRUE,COUNTIFS(Catálogo!$J$2:$J$648,"*"&$A14&"*",Catálogo!$I$2:$I$648,"<>ausente",Catálogo!$M$2:$M$648,"parcial",Catálogo!$L$2:$L$648,"*area*",Catálogo!$Q$2:$Q$648,{1,2,3,4,5,6,7,8,9})>0,0),0)<IFERROR(MATCH(TRUE,COUNTIFS(Catálogo!$J$2:$J$648,"*"&$A14&"*",Catálogo!$I$2:$I$648,"<>ausente",Catálogo!$M$2:$M$648,"completa",Catálogo!$L$2:$L$648,"*area*",Catálogo!$Q$2:$Q$648,{1,2,3,4,5,6,7,8,9})>0,0),0)),"; "&LOWER(INDEX(Niveles!$C$2:$C$10,IFERROR(MATCH(TRUE,COUNTIFS(Catálogo!$J$2:$J$648,"*"&$A14&"*",Catálogo!$I$2:$I$648,"<>ausente",Catálogo!$M$2:$M$648,"parcial",Catálogo!$L$2:$L$648,"*area*",Catálogo!$Q$2:$Q$648,{1,2,3,4,5,6,7,8,9})>0,0),0)))&" (parcial)",""),IF(IFERROR(MATCH(TRUE,COUNTIFS(Catálogo!$J$2:$J$648,"*"&$A14&"*",Catálogo!$I$2:$I$648,"<>ausente",Catálogo!$M$2:$M$648,"parcial",Catálogo!$L$2:$L$648,"*area*",Catálogo!$Q$2:$Q$648,{1,2,3,4,5,6,7,8,9})>0,0),0)>0,INDEX(Niveles!$C$2:$C$10,IFERROR(MATCH(TRUE,COUNTIFS(Catálogo!$J$2:$J$648,"*"&$A14&"*",Catálogo!$I$2:$I$648,"<>ausente",Catálogo!$M$2:$M$648,"parcial",Catálogo!$L$2:$L$648,"*area*",Catálogo!$Q$2:$Q$648,{1,2,3,4,5,6,7,8,9})>0,0),0))&" (parcial)","—")) -> Distrito | Q14: =IF(COUNTIFS(Cifras!$A$2:$A$399,$A14,Cifras!$E$2:$E$399,"Sí",Cifras!$F$2:$F$399,"Sí",Cifras!$D$2:$D$399,"distrito")>0,"Distrito",IF(COUNTIFS(Cifras!$A$2:$A$399,$A14,Cifras!$E$2:$E$399,"Sí",Cifras!$F$2:$F$399,"Sí",Cifras!$D$2:$D$399,"comuna")>0,"Comuna",IF(COUNTIFS(Cifras!$A$2:$A$399,$A14,Cifras!$E$2:$E$399,"Sí",Cifras!$F$2:$F$399,"Sí",Cifras!$D$2:$D$399,"partido")>0,"Partido",IF(COUNTIFS(Cifras!$A$2:$A$399,$A14,Cifras!$E$2:$E$399,"Sí",Cifras!$F$2:$F$399,"Sí",Cifras!$D$2:$D$399,"departamento")>0,"Departamento",IF(COUNTIFS(Cifras!$A$2:$A$399,$A14,Cifras!$E$2:$E$399,"Sí",Cifras!$F$2:$F$399,"Sí",Cifras!$D$2:$D$399,"provincia")>0,"Provincia",IF(COUNTIFS(Cifras!$A$2:$A$399,$A14,Cifras!$E$2:$E$399,"Sí",Cifras!$F$2:$F$399,"Sí",Cifras!$D$2:$D$399,"region")>0,"Región",IF(COUNTIFS(Cifras!$A$2:$A$399,$A14,Cifras!$E$2:$E$399,"Sí",Cifras!$F$2:$F$399,"Sí",Cifras!$D$2:$D$399,"pais")>0,"País","—"))))))) -> Departamento | R14: =IF(IFERROR(MATCH(TRUE,COUNTIFS(Catálogo!$J$2:$J$648,"*"&$A14&"*",Catálogo!$I$2:$I$648,"<>ausente",Catálogo!$M$2:$M$648,"completa",Catálogo!$L$2:$L$648,"*area*",Catálogo!$L$2:$L$648,"*sexo*",Catálogo!$Q$2:$Q$648,{1,2,3,4,5,6,7,8,9})>0,0),0)>0,INDEX(Niveles!$C$2:$C$10,IFERROR(MATCH(TRUE,COUNTIFS(Catálogo!$J$2:$J$648,"*"&$A14&"*",Catálogo!$I$2:$I$648,"<>ausente",Catálogo!$M$2:$M$648,"completa",Catálogo!$L$2:$L$648,"*area*",Catálogo!$L$2:$L$648,"*sexo*",Catálogo!$Q$2:$Q$648,{1,2,3,4,5,6,7,8,9})>0,0),0))&IF(AND(IFERROR(MATCH(TRUE,COUNTIFS(Catálogo!$J$2:$J$648,"*"&$A14&"*",Catálogo!$I$2:$I$648,"<>ausente",Catálogo!$M$2:$M$648,"parcial",Catálogo!$L$2:$L$648,"*area*",Catálogo!$L$2:$L$648,"*sexo*",Catálogo!$Q$2:$Q$648,{1,2,3,4,5,6,7,8,9})>0,0),0)>0,IFERROR(MATCH(TRUE,COUNTIFS(Catálogo!$J$2:$J$648,"*"&$A14&"*",Catálogo!$I$2:$I$648,"<>ausente",Catálogo!$M$2:$M$648,"parcial",Catálogo!$L$2:$L$648,"*area*",Catálogo!$L$2:$L$648,"*sexo*",Catálogo!$Q$2:$Q$648,{1,2,3,4,5,6,7,8,9})>0,0),0)<IFERROR(MATCH(TRUE,COUNTIFS(Catálogo!$J$2:$J$648,"*"&$A14&"*",Catálogo!$I$2:$I$648,"<>ausente",Catálogo!$M$2:$M$648,"completa",Catálogo!$L$2:$L$648,"*area*",Catálogo!$L$2:$L$648,"*sexo*",Catálogo!$Q$2:$Q$648,{1,2,3,4,5,6,7,8,9})>0,0),0)),"; "&LOWER(INDEX(Niveles!$C$2:$C$10,IFERROR(MATCH(TRUE,COUNTIFS(Catálogo!$J$2:$J$648,"*"&$A14&"*",Catálogo!$I$2:$I$648,"<>ausente",Catálogo!$M$2:$M$648,"parcial",Catálogo!$L$2:$L$648,"*area*",Catálogo!$L$2:$L$648,"*sexo*",Catálogo!$Q$2:$Q$648,{1,2,3,4,5,6,7,8,9})>0,0),0)))&" (parcial)",""),IF(IFERROR(MATCH(TRUE,COUNTIFS(Catálogo!$J$2:$J$648,"*"&$A14&"*",Catálogo!$I$2:$I$648,"<>ausente",Catálogo!$M$2:$M$648,"parcial",Catálogo!$L$2:$L$648,"*area*",Catálogo!$L$2:$L$648,"*sexo*",Catálogo!$Q$2:$Q$648,{1,2,3,4,5,6,7,8,9})>0,0),0)>0,INDEX(Niveles!$C$2:$C$10,IFERROR(MATCH(TRUE,COUNTIFS(Catálogo!$J$2:$J$648,"*"&$A14&"*",Catálogo!$I$2:$I$648,"<>ausente",Catálogo!$M$2:$M$648,"parcial",Catálogo!$L$2:$L$648,"*area*",Catálogo!$L$2:$L$648,"*sexo*",Catálogo!$Q$2:$Q$648,{1,2,3,4,5,6,7,8,9})>0,0),0))&" (parcial)","—")) -> Distrito | S14: =IF(COUNTIFS(Cifras!$A$2:$A$399,$A14,Cifras!$F$2:$F$399,"Sí",Cifras!$G$2:$G$399,"Sí",Cifras!$D$2:$D$399,"distrito")>0,"Distrito",IF(COUNTIFS(Cifras!$A$2:$A$399,$A14,Cifras!$F$2:$F$399,"Sí",Cifras!$G$2:$G$399,"Sí",Cifras!$D$2:$D$399,"comuna")>0,"Comuna",IF(COUNTIFS(Cifras!$A$2:$A$399,$A14,Cifras!$F$2:$F$399,"Sí",Cifras!$G$2:$G$399,"Sí",Cifras!$D$2:$D$399,"partido")>0,"Partido",IF(COUNTIFS(Cifras!$A$2:$A$399,$A14,Cifras!$F$2:$F$399,"Sí",Cifras!$G$2:$G$399,"Sí",Cifras!$D$2:$D$399,"departamento")>0,"Departamento",IF(COUNTIFS(Cifras!$A$2:$A$399,$A14,Cifras!$F$2:$F$399,"Sí",Cifras!$G$2:$G$399,"Sí",Cifras!$D$2:$D$399,"provincia")>0,"Provincia",IF(COUNTIFS(Cifras!$A$2:$A$399,$A14,Cifras!$F$2:$F$399,"Sí",Cifras!$G$2:$G$399,"Sí",Cifras!$D$2:$D$399,"region")>0,"Región",IF(COUNTIFS(Cifras!$A$2:$A$399,$A14,Cifras!$F$2:$F$399,"Sí",Cifras!$G$2:$G$399,"Sí",Cifras!$D$2:$D$399,"pais")>0,"País","—"))))))) -> Departamento | T14: =IF(IFERROR(MATCH(TRUE,COUNTIFS(Catálogo!$J$2:$J$648,"*"&$A14&"*",Catálogo!$I$2:$I$648,"<>ausente",Catálogo!$M$2:$M$648,"completa",Catálogo!$L$2:$L$648,"*sexo*",Catálogo!$L$2:$L$648,"*edad*",Catálogo!$Q$2:$Q$648,{1,2,3,4,5,6,7,8,9})>0,0),0)>0,INDEX(Niveles!$C$2:$C$10,IFERROR(MATCH(TRUE,COUNTIFS(Catálogo!$J$2:$J$648,"*"&$A14&"*",Catálogo!$I$2:$I$648,"<>ausente",Catálogo!$M$2:$M$648,"completa",Catálogo!$L$2:$L$648,"*sexo*",Catálogo!$L$2:$L$648,"*edad*",Catálogo!$Q$2:$Q$648,{1,2,3,4,5,6,7,8,9})>0,0),0))&IF(AND(IFERROR(MATCH(TRUE,COUNTIFS(Catálogo!$J$2:$J$648,"*"&$A14&"*",Catálogo!$I$2:$I$648,"<>ausente",Catálogo!$M$2:$M$648,"parcial",Catálogo!$L$2:$L$648,"*sexo*",Catálogo!$L$2:$L$648,"*edad*",Catálogo!$Q$2:$Q$648,{1,2,3,4,5,6,7,8,9})>0,0),0)>0,IFERROR(MATCH(TRUE,COUNTIFS(Catálogo!$J$2:$J$648,"*"&$A14&"*",Catálogo!$I$2:$I$648,"<>ausente",Catálogo!$M$2:$M$648,"parcial",Catálogo!$L$2:$L$648,"*sexo*",Catálogo!$L$2:$L$648,"*edad*",Catálogo!$Q$2:$Q$648,{1,2,3,4,5,6,7,8,9})>0,0),0)<IFERROR(MATCH(TRUE,COUNTIFS(Catálogo!$J$2:$J$648,"*"&$A14&"*",Catálogo!$I$2:$I$648,"<>ausente",Catálogo!$M$2:$M$648,"completa",Catálogo!$L$2:$L$648,"*sexo*",Catálogo!$L$2:$L$648,"*edad*",Catálogo!$Q$2:$Q$648,{1,2,3,4,5,6,7,8,9})>0,0),0)),"; "&LOWER(INDEX(Niveles!$C$2:$C$10,IFERROR(MATCH(TRUE,COUNTIFS(Catálogo!$J$2:$J$648,"*"&$A14&"*",Catálogo!$I$2:$I$648,"<>ausente",Catálogo!$M$2:$M$648,"parcial",Catálogo!$L$2:$L$648,"*sexo*",Catálogo!$L$2:$L$648,"*edad*",Catálogo!$Q$2:$Q$648,{1,2,3,4,5,6,7,8,9})>0,0),0)))&" (parcial)",""),IF(IFERROR(MATCH(TRUE,COUNTIFS(Catálogo!$J$2:$J$648,"*"&$A14&"*",Catálogo!$I$2:$I$648,"<>ausente",Catálogo!$M$2:$M$648,"parcial",Catálogo!$L$2:$L$648,"*sexo*",Catálogo!$L$2:$L$648,"*edad*",Catálogo!$Q$2:$Q$648,{1,2,3,4,5,6,7,8,9})>0,0),0)>0,INDEX(Niveles!$C$2:$C$10,IFERROR(MATCH(TRUE,COUNTIFS(Catálogo!$J$2:$J$648,"*"&$A14&"*",Catálogo!$I$2:$I$648,"<>ausente",Catálogo!$M$2:$M$648,"parcial",Catálogo!$L$2:$L$648,"*sexo*",Catálogo!$L$2:$L$648,"*edad*",Catálogo!$Q$2:$Q$648,{1,2,3,4,5,6,7,8,9})>0,0),0))&" (parcial)","—")) -> Departamento | U14: =SUMIFS(Cifras!$J$2:$J$399,Cifras!$A$2:$A$399,$A14) -> 17 | V14: Núcleo completo | W14: Opcional: comunas y subdelegaciones × área × sexo (Cuadro 5, págs. 8–104). La edad no viene por área ni bajo departamento. | X14: Departamento × área × sexo (Cuadro 4) y departamento × sexo × edad en 28 grupos (cap. II, cuadro 4: 7.221 cifras; decenios = 1952 C7). Erratas: Talca (total del departamento = Cuadro 3 errado; 45–49 y 60–64), La Ligua (2 años), Llanquihue (40–44, 85–89).
A15: 1930 | B15: pub_1930 | C15: 1025 | D15: =COUNTIFS(Catálogo!$B$2:$B$648,$A15) -> 24 | E15: =COUNTIFS(Catálogo!$B$2:$B$648,$A15,Catálogo!$F$2:$F$648,"cuadro") -> 16 | F15: =COUNTIFS(Catálogo!$B$2:$B$648,$A15,Catálogo!$F$2:$F$648,"bloque") -> 0 | G15: =COUNTIFS(Catálogo!$B$2:$B$648,$A15,Catálogo!$F$2:$F$648,"texto") -> 8 | H15: =COUNTIFS(Catálogo!$B$2:$B$648,$A15,Catálogo!$I$2:$I$648,"verificada") -> 4 | I15: =COUNTIFS(Catálogo!$B$2:$B$648,$A15,Catálogo!$I$2:$I$648,"estimada") -> 20 | J15: =COUNTIFS(Catálogo!$B$2:$B$648,$A15,Catálogo!$I$2:$I$648,"desconocida")+COUNTIFS(Catálogo!$B$2:$B$648,$A15,Catálogo!$I$2:$I$648,"ausente") -> 0 | K15: =COUNTIFS(Catálogo!$B$2:$B$648,$A15,Catálogo!$O$2:$O$648,"transcrito") -> 3 | L15: =SUMIFS(Cifras!$H$2:$H$399,Cifras!$A$2:$A$399,$A15) -> 8488 | M15: =IF(COUNTIFS(Cifras!$A$2:$A$399,$A15,Cifras!$D$2:$D$399,"distrito")>0,"Distrito",IF(COUNTIFS(Cifras!$A$2:$A$399,$A15,Cifras!$D$2:$D$399,"comuna")>0,"Comuna",IF(COUNTIFS(Cifras!$A$2:$A$399,$A15,Cifras!$D$2:$D$399,"partido")>0,"Partido",IF(COUNTIFS(Cifras!$A$2:$A$399,$A15,Cifras!$D$2:$D$399,"departamento")>0,"Departamento",IF(COUNTIFS(Cifras!$A$2:$A$399,$A15,Cifras!$D$2:$D$399,"provincia")>0,"Provincia",IF(COUNTIFS(Cifras!$A$2:$A$399,$A15,Cifras!$D$2:$D$399,"region")>0,"Región",IF(COUNTIFS(Cifras!$A$2:$A$399,$A15,Cifras!$D$2:$D$399,"pais")>0,"País","—"))))))) -> Comuna | N15: =IF(IFERROR(MATCH(TRUE,COUNTIFS(Catálogo!$J$2:$J$648,"*"&$A15&"*",Catálogo!$I$2:$I$648,"<>ausente",Catálogo!$M$2:$M$648,"completa",Catálogo!$Q$2:$Q$648,{1,2,3,4,5,6,7,8,9})>0,0),0)>0,INDEX(Niveles!$C$2:$C$10,IFERROR(MATCH(TRUE,COUNTIFS(Catálogo!$J$2:$J$648,"*"&$A15&"*",Catálogo!$I$2:$I$648,"<>ausente",Catálogo!$M$2:$M$648,"completa",Catálogo!$Q$2:$Q$648,{1,2,3,4,5,6,7,8,9})>0,0),0))&IF(AND(IFERROR(MATCH(TRUE,COUNTIFS(Catálogo!$J$2:$J$648,"*"&$A15&"*",Catálogo!$I$2:$I$648,"<>ausente",Catálogo!$M$2:$M$648,"parcial",Catálogo!$Q$2:$Q$648,{1,2,3,4,5,6,7,8,9})>0,0),0)>0,IFERROR(MATCH(TRUE,COUNTIFS(Catálogo!$J$2:$J$648,"*"&$A15&"*",Catálogo!$I$2:$I$648,"<>ausente",Catálogo!$M$2:$M$648,"parcial",Catálogo!$Q$2:$Q$648,{1,2,3,4,5,6,7,8,9})>0,0),0)<IFERROR(MATCH(TRUE,COUNTIFS(Catálogo!$J$2:$J$648,"*"&$A15&"*",Catálogo!$I$2:$I$648,"<>ausente",Catálogo!$M$2:$M$648,"completa",Catálogo!$Q$2:$Q$648,{1,2,3,4,5,6,7,8,9})>0,0),0)),"; "&LOWER(INDEX(Niveles!$C$2:$C$10,IFERROR(MATCH(TRUE,COUNTIFS(Catálogo!$J$2:$J$648,"*"&$A15&"*",Catálogo!$I$2:$I$648,"<>ausente",Catálogo!$M$2:$M$648,"parcial",Catálogo!$Q$2:$Q$648,{1,2,3,4,5,6,7,8,9})>0,0),0)))&" (parcial)",""),IF(IFERROR(MATCH(TRUE,COUNTIFS(Catálogo!$J$2:$J$648,"*"&$A15&"*",Catálogo!$I$2:$I$648,"<>ausente",Catálogo!$M$2:$M$648,"parcial",Catálogo!$Q$2:$Q$648,{1,2,3,4,5,6,7,8,9})>0,0),0)>0,INDEX(Niveles!$C$2:$C$10,IFERROR(MATCH(TRUE,COUNTIFS(Catálogo!$J$2:$J$648,"*"&$A15&"*",Catálogo!$I$2:$I$648,"<>ausente",Catálogo!$M$2:$M$648,"parcial",Catálogo!$Q$2:$Q$648,{1,2,3,4,5,6,7,8,9})>0,0),0))&" (parcial)","—")) -> Entidad | O15: =IF(COUNTIFS(Cifras!$A$2:$A$399,$A15,Cifras!$E$2:$E$399,"Sí",Cifras!$D$2:$D$399,"distrito")>0,"Distrito",IF(COUNTIFS(Cifras!$A$2:$A$399,$A15,Cifras!$E$2:$E$399,"Sí",Cifras!$D$2:$D$399,"comuna")>0,"Comuna",IF(COUNTIFS(Cifras!$A$2:$A$399,$A15,Cifras!$E$2:$E$399,"Sí",Cifras!$D$2:$D$399,"partido")>0,"Partido",IF(COUNTIFS(Cifras!$A$2:$A$399,$A15,Cifras!$E$2:$E$399,"Sí",Cifras!$D$2:$D$399,"departamento")>0,"Departamento",IF(COUNTIFS(Cifras!$A$2:$A$399,$A15,Cifras!$E$2:$E$399,"Sí",Cifras!$D$2:$D$399,"provincia")>0,"Provincia",IF(COUNTIFS(Cifras!$A$2:$A$399,$A15,Cifras!$E$2:$E$399,"Sí",Cifras!$D$2:$D$399,"region")>0,"Región",IF(COUNTIFS(Cifras!$A$2:$A$399,$A15,Cifras!$E$2:$E$399,"Sí",Cifras!$D$2:$D$399,"pais")>0,"País","—"))))))) -> Comuna | P15: =IF(IFERROR(MATCH(TRUE,COUNTIFS(Catálogo!$J$2:$J$648,"*"&$A15&"*",Catálogo!$I$2:$I$648,"<>ausente",Catálogo!$M$2:$M$648,"completa",Catálogo!$L$2:$L$648,"*area*",Catálogo!$Q$2:$Q$648,{1,2,3,4,5,6,7,8,9})>0,0),0)>0,INDEX(Niveles!$C$2:$C$10,IFERROR(MATCH(TRUE,COUNTIFS(Catálogo!$J$2:$J$648,"*"&$A15&"*",Catálogo!$I$2:$I$648,"<>ausente",Catálogo!$M$2:$M$648,"completa",Catálogo!$L$2:$L$648,"*area*",Catálogo!$Q$2:$Q$648,{1,2,3,4,5,6,7,8,9})>0,0),0))&IF(AND(IFERROR(MATCH(TRUE,COUNTIFS(Catálogo!$J$2:$J$648,"*"&$A15&"*",Catálogo!$I$2:$I$648,"<>ausente",Catálogo!$M$2:$M$648,"parcial",Catálogo!$L$2:$L$648,"*area*",Catálogo!$Q$2:$Q$648,{1,2,3,4,5,6,7,8,9})>0,0),0)>0,IFERROR(MATCH(TRUE,COUNTIFS(Catálogo!$J$2:$J$648,"*"&$A15&"*",Catálogo!$I$2:$I$648,"<>ausente",Catálogo!$M$2:$M$648,"parcial",Catálogo!$L$2:$L$648,"*area*",Catálogo!$Q$2:$Q$648,{1,2,3,4,5,6,7,8,9})>0,0),0)<IFERROR(MATCH(TRUE,COUNTIFS(Catálogo!$J$2:$J$648,"*"&$A15&"*",Catálogo!$I$2:$I$648,"<>ausente",Catálogo!$M$2:$M$648,"completa",Catálogo!$L$2:$L$648,"*area*",Catálogo!$Q$2:$Q$648,{1,2,3,4,5,6,7,8,9})>0,0),0)),"; "&LOWER(INDEX(Niveles!$C$2:$C$10,IFERROR(MATCH(TRUE,COUNTIFS(Catálogo!$J$2:$J$648,"*"&$A15&"*",Catálogo!$I$2:$I$648,"<>ausente",Catálogo!$M$2:$M$648,"parcial",Catálogo!$L$2:$L$648,"*area*",Catálogo!$Q$2:$Q$648,{1,2,3,4,5,6,7,8,9})>0,0),0)))&" (parcial)",""),IF(IFERROR(MATCH(TRUE,COUNTIFS(Catálogo!$J$2:$J$648,"*"&$A15&"*",Catálogo!$I$2:$I$648,"<>ausente",Catálogo!$M$2:$M$648,"parcial",Catálogo!$L$2:$L$648,"*area*",Catálogo!$Q$2:$Q$648,{1,2,3,4,5,6,7,8,9})>0,0),0)>0,INDEX(Niveles!$C$2:$C$10,IFERROR(MATCH(TRUE,COUNTIFS(Catálogo!$J$2:$J$648,"*"&$A15&"*",Catálogo!$I$2:$I$648,"<>ausente",Catálogo!$M$2:$M$648,"parcial",Catálogo!$L$2:$L$648,"*area*",Catálogo!$Q$2:$Q$648,{1,2,3,4,5,6,7,8,9})>0,0),0))&" (parcial)","—")) -> Comuna | Q15: =IF(COUNTIFS(Cifras!$A$2:$A$399,$A15,Cifras!$E$2:$E$399,"Sí",Cifras!$F$2:$F$399,"Sí",Cifras!$D$2:$D$399,"distrito")>0,"Distrito",IF(COUNTIFS(Cifras!$A$2:$A$399,$A15,Cifras!$E$2:$E$399,"Sí",Cifras!$F$2:$F$399,"Sí",Cifras!$D$2:$D$399,"comuna")>0,"Comuna",IF(COUNTIFS(Cifras!$A$2:$A$399,$A15,Cifras!$E$2:$E$399,"Sí",Cifras!$F$2:$F$399,"Sí",Cifras!$D$2:$D$399,"partido")>0,"Partido",IF(COUNTIFS(Cifras!$A$2:$A$399,$A15,Cifras!$E$2:$E$399,"Sí",Cifras!$F$2:$F$399,"Sí",Cifras!$D$2:$D$399,"departamento")>0,"Departamento",IF(COUNTIFS(Cifras!$A$2:$A$399,$A15,Cifras!$E$2:$E$399,"Sí",Cifras!$F$2:$F$399,"Sí",Cifras!$D$2:$D$399,"provincia")>0,"Provincia",IF(COUNTIFS(Cifras!$A$2:$A$399,$A15,Cifras!$E$2:$E$399,"Sí",Cifras!$F$2:$F$399,"Sí",Cifras!$D$2:$D$399,"region")>0,"Región",IF(COUNTIFS(Cifras!$A$2:$A$399,$A15,Cifras!$E$2:$E$399,"Sí",Cifras!$F$2:$F$399,"Sí",Cifras!$D$2:$D$399,"pais")>0,"País","—"))))))) -> Comuna | R15: =IF(IFERROR(MATCH(TRUE,COUNTIFS(Catálogo!$J$2:$J$648,"*"&$A15&"*",Catálogo!$I$2:$I$648,"<>ausente",Catálogo!$M$2:$M$648,"completa",Catálogo!$L$2:$L$648,"*area*",Catálogo!$L$2:$L$648,"*sexo*",Catálogo!$Q$2:$Q$648,{1,2,3,4,5,6,7,8,9})>0,0),0)>0,INDEX(Niveles!$C$2:$C$10,IFERROR(MATCH(TRUE,COUNTIFS(Catálogo!$J$2:$J$648,"*"&$A15&"*",Catálogo!$I$2:$I$648,"<>ausente",Catálogo!$M$2:$M$648,"completa",Catálogo!$L$2:$L$648,"*area*",Catálogo!$L$2:$L$648,"*sexo*",Catálogo!$Q$2:$Q$648,{1,2,3,4,5,6,7,8,9})>0,0),0))&IF(AND(IFERROR(MATCH(TRUE,COUNTIFS(Catálogo!$J$2:$J$648,"*"&$A15&"*",Catálogo!$I$2:$I$648,"<>ausente",Catálogo!$M$2:$M$648,"parcial",Catálogo!$L$2:$L$648,"*area*",Catálogo!$L$2:$L$648,"*sexo*",Catálogo!$Q$2:$Q$648,{1,2,3,4,5,6,7,8,9})>0,0),0)>0,IFERROR(MATCH(TRUE,COUNTIFS(Catálogo!$J$2:$J$648,"*"&$A15&"*",Catálogo!$I$2:$I$648,"<>ausente",Catálogo!$M$2:$M$648,"parcial",Catálogo!$L$2:$L$648,"*area*",Catálogo!$L$2:$L$648,"*sexo*",Catálogo!$Q$2:$Q$648,{1,2,3,4,5,6,7,8,9})>0,0),0)<IFERROR(MATCH(TRUE,COUNTIFS(Catálogo!$J$2:$J$648,"*"&$A15&"*",Catálogo!$I$2:$I$648,"<>ausente",Catálogo!$M$2:$M$648,"completa",Catálogo!$L$2:$L$648,"*area*",Catálogo!$L$2:$L$648,"*sexo*",Catálogo!$Q$2:$Q$648,{1,2,3,4,5,6,7,8,9})>0,0),0)),"; "&LOWER(INDEX(Niveles!$C$2:$C$10,IFERROR(MATCH(TRUE,COUNTIFS(Catálogo!$J$2:$J$648,"*"&$A15&"*",Catálogo!$I$2:$I$648,"<>ausente",Catálogo!$M$2:$M$648,"parcial",Catálogo!$L$2:$L$648,"*area*",Catálogo!$L$2:$L$648,"*sexo*",Catálogo!$Q$2:$Q$648,{1,2,3,4,5,6,7,8,9})>0,0),0)))&" (parcial)",""),IF(IFERROR(MATCH(TRUE,COUNTIFS(Catálogo!$J$2:$J$648,"*"&$A15&"*",Catálogo!$I$2:$I$648,"<>ausente",Catálogo!$M$2:$M$648,"parcial",Catálogo!$L$2:$L$648,"*area*",Catálogo!$L$2:$L$648,"*sexo*",Catálogo!$Q$2:$Q$648,{1,2,3,4,5,6,7,8,9})>0,0),0)>0,INDEX(Niveles!$C$2:$C$10,IFERROR(MATCH(TRUE,COUNTIFS(Catálogo!$J$2:$J$648,"*"&$A15&"*",Catálogo!$I$2:$I$648,"<>ausente",Catálogo!$M$2:$M$648,"parcial",Catálogo!$L$2:$L$648,"*area*",Catálogo!$L$2:$L$648,"*sexo*",Catálogo!$Q$2:$Q$648,{1,2,3,4,5,6,7,8,9})>0,0),0))&" (parcial)","—")) -> Comuna | S15: =IF(COUNTIFS(Cifras!$A$2:$A$399,$A15,Cifras!$F$2:$F$399,"Sí",Cifras!$G$2:$G$399,"Sí",Cifras!$D$2:$D$399,"distrito")>0,"Distrito",IF(COUNTIFS(Cifras!$A$2:$A$399,$A15,Cifras!$F$2:$F$399,"Sí",Cifras!$G$2:$G$399,"Sí",Cifras!$D$2:$D$399,"comuna")>0,"Comuna",IF(COUNTIFS(Cifras!$A$2:$A$399,$A15,Cifras!$F$2:$F$399,"Sí",Cifras!$G$2:$G$399,"Sí",Cifras!$D$2:$D$399,"partido")>0,"Partido",IF(COUNTIFS(Cifras!$A$2:$A$399,$A15,Cifras!$F$2:$F$399,"Sí",Cifras!$G$2:$G$399,"Sí",Cifras!$D$2:$D$399,"departamento")>0,"Departamento",IF(COUNTIFS(Cifras!$A$2:$A$399,$A15,Cifras!$F$2:$F$399,"Sí",Cifras!$G$2:$G$399,"Sí",Cifras!$D$2:$D$399,"provincia")>0,"Provincia",IF(COUNTIFS(Cifras!$A$2:$A$399,$A15,Cifras!$F$2:$F$399,"Sí",Cifras!$G$2:$G$399,"Sí",Cifras!$D$2:$D$399,"region")>0,"Región",IF(COUNTIFS(Cifras!$A$2:$A$399,$A15,Cifras!$F$2:$F$399,"Sí",Cifras!$G$2:$G$399,"Sí",Cifras!$D$2:$D$399,"pais")>0,"País","—"))))))) -> Provincia | T15: =IF(IFERROR(MATCH(TRUE,COUNTIFS(Catálogo!$J$2:$J$648,"*"&$A15&"*",Catálogo!$I$2:$I$648,"<>ausente",Catálogo!$M$2:$M$648,"completa",Catálogo!$L$2:$L$648,"*sexo*",Catálogo!$L$2:$L$648,"*edad*",Catálogo!$Q$2:$Q$648,{1,2,3,4,5,6,7,8,9})>0,0),0)>0,INDEX(Niveles!$C$2:$C$10,IFERROR(MATCH(TRUE,COUNTIFS(Catálogo!$J$2:$J$648,"*"&$A15&"*",Catálogo!$I$2:$I$648,"<>ausente",Catálogo!$M$2:$M$648,"completa",Catálogo!$L$2:$L$648,"*sexo*",Catálogo!$L$2:$L$648,"*edad*",Catálogo!$Q$2:$Q$648,{1,2,3,4,5,6,7,8,9})>0,0),0))&IF(AND(IFERROR(MATCH(TRUE,COUNTIFS(Catálogo!$J$2:$J$648,"*"&$A15&"*",Catálogo!$I$2:$I$648,"<>ausente",Catálogo!$M$2:$M$648,"parcial",Catálogo!$L$2:$L$648,"*sexo*",Catálogo!$L$2:$L$648,"*edad*",Catálogo!$Q$2:$Q$648,{1,2,3,4,5,6,7,8,9})>0,0),0)>0,IFERROR(MATCH(TRUE,COUNTIFS(Catálogo!$J$2:$J$648,"*"&$A15&"*",Catálogo!$I$2:$I$648,"<>ausente",Catálogo!$M$2:$M$648,"parcial",Catálogo!$L$2:$L$648,"*sexo*",Catálogo!$L$2:$L$648,"*edad*",Catálogo!$Q$2:$Q$648,{1,2,3,4,5,6,7,8,9})>0,0),0)<IFERROR(MATCH(TRUE,COUNTIFS(Catálogo!$J$2:$J$648,"*"&$A15&"*",Catálogo!$I$2:$I$648,"<>ausente",Catálogo!$M$2:$M$648,"completa",Catálogo!$L$2:$L$648,"*sexo*",Catálogo!$L$2:$L$648,"*edad*",Catálogo!$Q$2:$Q$648,{1,2,3,4,5,6,7,8,9})>0,0),0)),"; "&LOWER(INDEX(Niveles!$C$2:$C$10,IFERROR(MATCH(TRUE,COUNTIFS(Catálogo!$J$2:$J$648,"*"&$A15&"*",Catálogo!$I$2:$I$648,"<>ausente",Catálogo!$M$2:$M$648,"parcial",Catálogo!$L$2:$L$648,"*sexo*",Catálogo!$L$2:$L$648,"*edad*",Catálogo!$Q$2:$Q$648,{1,2,3,4,5,6,7,8,9})>0,0),0)))&" (parcial)",""),IF(IFERROR(MATCH(TRUE,COUNTIFS(Catálogo!$J$2:$J$648,"*"&$A15&"*",Catálogo!$I$2:$I$648,"<>ausente",Catálogo!$M$2:$M$648,"parcial",Catálogo!$L$2:$L$648,"*sexo*",Catálogo!$L$2:$L$648,"*edad*",Catálogo!$Q$2:$Q$648,{1,2,3,4,5,6,7,8,9})>0,0),0)>0,INDEX(Niveles!$C$2:$C$10,IFERROR(MATCH(TRUE,COUNTIFS(Catálogo!$J$2:$J$648,"*"&$A15&"*",Catálogo!$I$2:$I$648,"<>ausente",Catálogo!$M$2:$M$648,"parcial",Catálogo!$L$2:$L$648,"*sexo*",Catálogo!$L$2:$L$648,"*edad*",Catálogo!$Q$2:$Q$648,{1,2,3,4,5,6,7,8,9})>0,0),0))&" (parcial)","—")) -> Comuna | U15: =SUMIFS(Cifras!$J$2:$J$399,Cifras!$A$2:$A$399,$A15) -> 8 | V15: Núcleo completo | W15: Opcional: comuna × sexo × edad simple (PDF ~337-480, muy extenso). Área × edad no viene. | X15: Comuna × área × sexo (Cuadro 9) y provincia × sexo × edad simple (tomo de edades, Cuadro 4: 5.253 cifras, totales = país y 1952 C5; décadas = 1952 C7). Erratas: Atacama (C9, C10), Valdivia edades 30, 31 y 40; compensadas en Cautín y Magallanes.
A16: 1940 | B16: pub_1940 | C16: 361 | D16: =COUNTIFS(Catálogo!$B$2:$B$648,$A16) -> 23 | E16: =COUNTIFS(Catálogo!$B$2:$B$648,$A16,Catálogo!$F$2:$F$648,"cuadro") -> 21 | F16: =COUNTIFS(Catálogo!$B$2:$B$648,$A16,Catálogo!$F$2:$F$648,"bloque") -> 0 | G16: =COUNTIFS(Catálogo!$B$2:$B$648,$A16,Catálogo!$F$2:$F$648,"texto") -> 2 | H16: =COUNTIFS(Catálogo!$B$2:$B$648,$A16,Catálogo!$I$2:$I$648,"verificada") -> 4 | I16: =COUNTIFS(Catálogo!$B$2:$B$648,$A16,Catálogo!$I$2:$I$648,"estimada") -> 17 | J16: =COUNTIFS(Catálogo!$B$2:$B$648,$A16,Catálogo!$I$2:$I$648,"desconocida")+COUNTIFS(Catálogo!$B$2:$B$648,$A16,Catálogo!$I$2:$I$648,"ausente") -> 2 | K16: =COUNTIFS(Catálogo!$B$2:$B$648,$A16,Catálogo!$O$2:$O$648,"transcrito") -> 2 | L16: =SUMIFS(Cifras!$H$2:$H$399,Cifras!$A$2:$A$399,$A16) -> 4892 | M16: =IF(COUNTIFS(Cifras!$A$2:$A$399,$A16,Cifras!$D$2:$D$399,"distrito")>0,"Distrito",IF(COUNTIFS(Cifras!$A$2:$A$399,$A16,Cifras!$D$2:$D$399,"comuna")>0,"Comuna",IF(COUNTIFS(Cifras!$A$2:$A$399,$A16,Cifras!$D$2:$D$399,"partido")>0,"Partido",IF(COUNTIFS(Cifras!$A$2:$A$399,$A16,Cifras!$D$2:$D$399,"departamento")>0,"Departamento",IF(COUNTIFS(Cifras!$A$2:$A$399,$A16,Cifras!$D$2:$D$399,"provincia")>0,"Provincia",IF(COUNTIFS(Cifras!$A$2:$A$399,$A16,Cifras!$D$2:$D$399,"region")>0,"Región",IF(COUNTIFS(Cifras!$A$2:$A$399,$A16,Cifras!$D$2:$D$399,"pais")>0,"País","—"))))))) -> Comuna | N16: =IF(IFERROR(MATCH(TRUE,COUNTIFS(Catálogo!$J$2:$J$648,"*"&$A16&"*",Catálogo!$I$2:$I$648,"<>ausente",Catálogo!$M$2:$M$648,"completa",Catálogo!$Q$2:$Q$648,{1,2,3,4,5,6,7,8,9})>0,0),0)>0,INDEX(Niveles!$C$2:$C$10,IFERROR(MATCH(TRUE,COUNTIFS(Catálogo!$J$2:$J$648,"*"&$A16&"*",Catálogo!$I$2:$I$648,"<>ausente",Catálogo!$M$2:$M$648,"completa",Catálogo!$Q$2:$Q$648,{1,2,3,4,5,6,7,8,9})>0,0),0))&IF(AND(IFERROR(MATCH(TRUE,COUNTIFS(Catálogo!$J$2:$J$648,"*"&$A16&"*",Catálogo!$I$2:$I$648,"<>ausente",Catálogo!$M$2:$M$648,"parcial",Catálogo!$Q$2:$Q$648,{1,2,3,4,5,6,7,8,9})>0,0),0)>0,IFERROR(MATCH(TRUE,COUNTIFS(Catálogo!$J$2:$J$648,"*"&$A16&"*",Catálogo!$I$2:$I$648,"<>ausente",Catálogo!$M$2:$M$648,"parcial",Catálogo!$Q$2:$Q$648,{1,2,3,4,5,6,7,8,9})>0,0),0)<IFERROR(MATCH(TRUE,COUNTIFS(Catálogo!$J$2:$J$648,"*"&$A16&"*",Catálogo!$I$2:$I$648,"<>ausente",Catálogo!$M$2:$M$648,"completa",Catálogo!$Q$2:$Q$648,{1,2,3,4,5,6,7,8,9})>0,0),0)),"; "&LOWER(INDEX(Niveles!$C$2:$C$10,IFERROR(MATCH(TRUE,COUNTIFS(Catálogo!$J$2:$J$648,"*"&$A16&"*",Catálogo!$I$2:$I$648,"<>ausente",Catálogo!$M$2:$M$648,"parcial",Catálogo!$Q$2:$Q$648,{1,2,3,4,5,6,7,8,9})>0,0),0)))&" (parcial)",""),IF(IFERROR(MATCH(TRUE,COUNTIFS(Catálogo!$J$2:$J$648,"*"&$A16&"*",Catálogo!$I$2:$I$648,"<>ausente",Catálogo!$M$2:$M$648,"parcial",Catálogo!$Q$2:$Q$648,{1,2,3,4,5,6,7,8,9})>0,0),0)>0,INDEX(Niveles!$C$2:$C$10,IFERROR(MATCH(TRUE,COUNTIFS(Catálogo!$J$2:$J$648,"*"&$A16&"*",Catálogo!$I$2:$I$648,"<>ausente",Catálogo!$M$2:$M$648,"parcial",Catálogo!$Q$2:$Q$648,{1,2,3,4,5,6,7,8,9})>0,0),0))&" (parcial)","—")) -> Distrito | O16: =IF(COUNTIFS(Cifras!$A$2:$A$399,$A16,Cifras!$E$2:$E$399,"Sí",Cifras!$D$2:$D$399,"distrito")>0,"Distrito",IF(COUNTIFS(Cifras!$A$2:$A$399,$A16,Cifras!$E$2:$E$399,"Sí",Cifras!$D$2:$D$399,"comuna")>0,"Comuna",IF(COUNTIFS(Cifras!$A$2:$A$399,$A16,Cifras!$E$2:$E$399,"Sí",Cifras!$D$2:$D$399,"partido")>0,"Partido",IF(COUNTIFS(Cifras!$A$2:$A$399,$A16,Cifras!$E$2:$E$399,"Sí",Cifras!$D$2:$D$399,"departamento")>0,"Departamento",IF(COUNTIFS(Cifras!$A$2:$A$399,$A16,Cifras!$E$2:$E$399,"Sí",Cifras!$D$2:$D$399,"provincia")>0,"Provincia",IF(COUNTIFS(Cifras!$A$2:$A$399,$A16,Cifras!$E$2:$E$399,"Sí",Cifras!$D$2:$D$399,"region")>0,"Región",IF(COUNTIFS(Cifras!$A$2:$A$399,$A16,Cifras!$E$2:$E$399,"Sí",Cifras!$D$2:$D$399,"pais")>0,"País","—"))))))) -> Comuna | P16: =IF(IFERROR(MATCH(TRUE,COUNTIFS(Catálogo!$J$2:$J$648,"*"&$A16&"*",Catálogo!$I$2:$I$648,"<>ausente",Catálogo!$M$2:$M$648,"completa",Catálogo!$L$2:$L$648,"*area*",Catálogo!$Q$2:$Q$648,{1,2,3,4,5,6,7,8,9})>0,0),0)>0,INDEX(Niveles!$C$2:$C$10,IFERROR(MATCH(TRUE,COUNTIFS(Catálogo!$J$2:$J$648,"*"&$A16&"*",Catálogo!$I$2:$I$648,"<>ausente",Catálogo!$M$2:$M$648,"completa",Catálogo!$L$2:$L$648,"*area*",Catálogo!$Q$2:$Q$648,{1,2,3,4,5,6,7,8,9})>0,0),0))&IF(AND(IFERROR(MATCH(TRUE,COUNTIFS(Catálogo!$J$2:$J$648,"*"&$A16&"*",Catálogo!$I$2:$I$648,"<>ausente",Catálogo!$M$2:$M$648,"parcial",Catálogo!$L$2:$L$648,"*area*",Catálogo!$Q$2:$Q$648,{1,2,3,4,5,6,7,8,9})>0,0),0)>0,IFERROR(MATCH(TRUE,COUNTIFS(Catálogo!$J$2:$J$648,"*"&$A16&"*",Catálogo!$I$2:$I$648,"<>ausente",Catálogo!$M$2:$M$648,"parcial",Catálogo!$L$2:$L$648,"*area*",Catálogo!$Q$2:$Q$648,{1,2,3,4,5,6,7,8,9})>0,0),0)<IFERROR(MATCH(TRUE,COUNTIFS(Catálogo!$J$2:$J$648,"*"&$A16&"*",Catálogo!$I$2:$I$648,"<>ausente",Catálogo!$M$2:$M$648,"completa",Catálogo!$L$2:$L$648,"*area*",Catálogo!$Q$2:$Q$648,{1,2,3,4,5,6,7,8,9})>0,0),0)),"; "&LOWER(INDEX(Niveles!$C$2:$C$10,IFERROR(MATCH(TRUE,COUNTIFS(Catálogo!$J$2:$J$648,"*"&$A16&"*",Catálogo!$I$2:$I$648,"<>ausente",Catálogo!$M$2:$M$648,"parcial",Catálogo!$L$2:$L$648,"*area*",Catálogo!$Q$2:$Q$648,{1,2,3,4,5,6,7,8,9})>0,0),0)))&" (parcial)",""),IF(IFERROR(MATCH(TRUE,COUNTIFS(Catálogo!$J$2:$J$648,"*"&$A16&"*",Catálogo!$I$2:$I$648,"<>ausente",Catálogo!$M$2:$M$648,"parcial",Catálogo!$L$2:$L$648,"*area*",Catálogo!$Q$2:$Q$648,{1,2,3,4,5,6,7,8,9})>0,0),0)>0,INDEX(Niveles!$C$2:$C$10,IFERROR(MATCH(TRUE,COUNTIFS(Catálogo!$J$2:$J$648,"*"&$A16&"*",Catálogo!$I$2:$I$648,"<>ausente",Catálogo!$M$2:$M$648,"parcial",Catálogo!$L$2:$L$648,"*area*",Catálogo!$Q$2:$Q$648,{1,2,3,4,5,6,7,8,9})>0,0),0))&" (parcial)","—")) -> Distrito | Q16: =IF(COUNTIFS(Cifras!$A$2:$A$399,$A16,Cifras!$E$2:$E$399,"Sí",Cifras!$F$2:$F$399,"Sí",Cifras!$D$2:$D$399,"distrito")>0,"Distrito",IF(COUNTIFS(Cifras!$A$2:$A$399,$A16,Cifras!$E$2:$E$399,"Sí",Cifras!$F$2:$F$399,"Sí",Cifras!$D$2:$D$399,"comuna")>0,"Comuna",IF(COUNTIFS(Cifras!$A$2:$A$399,$A16,Cifras!$E$2:$E$399,"Sí",Cifras!$F$2:$F$399,"Sí",Cifras!$D$2:$D$399,"partido")>0,"Partido",IF(COUNTIFS(Cifras!$A$2:$A$399,$A16,Cifras!$E$2:$E$399,"Sí",Cifras!$F$2:$F$399,"Sí",Cifras!$D$2:$D$399,"departamento")>0,"Departamento",IF(COUNTIFS(Cifras!$A$2:$A$399,$A16,Cifras!$E$2:$E$399,"Sí",Cifras!$F$2:$F$399,"Sí",Cifras!$D$2:$D$399,"provincia")>0,"Provincia",IF(COUNTIFS(Cifras!$A$2:$A$399,$A16,Cifras!$E$2:$E$399,"Sí",Cifras!$F$2:$F$399,"Sí",Cifras!$D$2:$D$399,"region")>0,"Región",IF(COUNTIFS(Cifras!$A$2:$A$399,$A16,Cifras!$E$2:$E$399,"Sí",Cifras!$F$2:$F$399,"Sí",Cifras!$D$2:$D$399,"pais")>0,"País","—"))))))) -> Comuna | R16: =IF(IFERROR(MATCH(TRUE,COUNTIFS(Catálogo!$J$2:$J$648,"*"&$A16&"*",Catálogo!$I$2:$I$648,"<>ausente",Catálogo!$M$2:$M$648,"completa",Catálogo!$L$2:$L$648,"*area*",Catálogo!$L$2:$L$648,"*sexo*",Catálogo!$Q$2:$Q$648,{1,2,3,4,5,6,7,8,9})>0,0),0)>0,INDEX(Niveles!$C$2:$C$10,IFERROR(MATCH(TRUE,COUNTIFS(Catálogo!$J$2:$J$648,"*"&$A16&"*",Catálogo!$I$2:$I$648,"<>ausente",Catálogo!$M$2:$M$648,"completa",Catálogo!$L$2:$L$648,"*area*",Catálogo!$L$2:$L$648,"*sexo*",Catálogo!$Q$2:$Q$648,{1,2,3,4,5,6,7,8,9})>0,0),0))&IF(AND(IFERROR(MATCH(TRUE,COUNTIFS(Catálogo!$J$2:$J$648,"*"&$A16&"*",Catálogo!$I$2:$I$648,"<>ausente",Catálogo!$M$2:$M$648,"parcial",Catálogo!$L$2:$L$648,"*area*",Catálogo!$L$2:$L$648,"*sexo*",Catálogo!$Q$2:$Q$648,{1,2,3,4,5,6,7,8,9})>0,0),0)>0,IFERROR(MATCH(TRUE,COUNTIFS(Catálogo!$J$2:$J$648,"*"&$A16&"*",Catálogo!$I$2:$I$648,"<>ausente",Catálogo!$M$2:$M$648,"parcial",Catálogo!$L$2:$L$648,"*area*",Catálogo!$L$2:$L$648,"*sexo*",Catálogo!$Q$2:$Q$648,{1,2,3,4,5,6,7,8,9})>0,0),0)<IFERROR(MATCH(TRUE,COUNTIFS(Catálogo!$J$2:$J$648,"*"&$A16&"*",Catálogo!$I$2:$I$648,"<>ausente",Catálogo!$M$2:$M$648,"completa",Catálogo!$L$2:$L$648,"*area*",Catálogo!$L$2:$L$648,"*sexo*",Catálogo!$Q$2:$Q$648,{1,2,3,4,5,6,7,8,9})>0,0),0)),"; "&LOWER(INDEX(Niveles!$C$2:$C$10,IFERROR(MATCH(TRUE,COUNTIFS(Catálogo!$J$2:$J$648,"*"&$A16&"*",Catálogo!$I$2:$I$648,"<>ausente",Catálogo!$M$2:$M$648,"parcial",Catálogo!$L$2:$L$648,"*area*",Catálogo!$L$2:$L$648,"*sexo*",Catálogo!$Q$2:$Q$648,{1,2,3,4,5,6,7,8,9})>0,0),0)))&" (parcial)",""),IF(IFERROR(MATCH(TRUE,COUNTIFS(Catálogo!$J$2:$J$648,"*"&$A16&"*",Catálogo!$I$2:$I$648,"<>ausente",Catálogo!$M$2:$M$648,"parcial",Catálogo!$L$2:$L$648,"*area*",Catálogo!$L$2:$L$648,"*sexo*",Catálogo!$Q$2:$Q$648,{1,2,3,4,5,6,7,8,9})>0,0),0)>0,INDEX(Niveles!$C$2:$C$10,IFERROR(MATCH(TRUE,COUNTIFS(Catálogo!$J$2:$J$648,"*"&$A16&"*",Catálogo!$I$2:$I$648,"<>ausente",Catálogo!$M$2:$M$648,"parcial",Catálogo!$L$2:$L$648,"*area*",Catálogo!$L$2:$L$648,"*sexo*",Catálogo!$Q$2:$Q$648,{1,2,3,4,5,6,7,8,9})>0,0),0))&" (parcial)","—")) -> Distrito | S16: =IF(COUNTIFS(Cifras!$A$2:$A$399,$A16,Cifras!$F$2:$F$399,"Sí",Cifras!$G$2:$G$399,"Sí",Cifras!$D$2:$D$399,"distrito")>0,"Distrito",IF(COUNTIFS(Cifras!$A$2:$A$399,$A16,Cifras!$F$2:$F$399,"Sí",Cifras!$G$2:$G$399,"Sí",Cifras!$D$2:$D$399,"comuna")>0,"Comuna",IF(COUNTIFS(Cifras!$A$2:$A$399,$A16,Cifras!$F$2:$F$399,"Sí",Cifras!$G$2:$G$399,"Sí",Cifras!$D$2:$D$399,"partido")>0,"Partido",IF(COUNTIFS(Cifras!$A$2:$A$399,$A16,Cifras!$F$2:$F$399,"Sí",Cifras!$G$2:$G$399,"Sí",Cifras!$D$2:$D$399,"departamento")>0,"Departamento",IF(COUNTIFS(Cifras!$A$2:$A$399,$A16,Cifras!$F$2:$F$399,"Sí",Cifras!$G$2:$G$399,"Sí",Cifras!$D$2:$D$399,"provincia")>0,"Provincia",IF(COUNTIFS(Cifras!$A$2:$A$399,$A16,Cifras!$F$2:$F$399,"Sí",Cifras!$G$2:$G$399,"Sí",Cifras!$D$2:$D$399,"region")>0,"Región",IF(COUNTIFS(Cifras!$A$2:$A$399,$A16,Cifras!$F$2:$F$399,"Sí",Cifras!$G$2:$G$399,"Sí",Cifras!$D$2:$D$399,"pais")>0,"País","—"))))))) -> Provincia | T16: =IF(IFERROR(MATCH(TRUE,COUNTIFS(Catálogo!$J$2:$J$648,"*"&$A16&"*",Catálogo!$I$2:$I$648,"<>ausente",Catálogo!$M$2:$M$648,"completa",Catálogo!$L$2:$L$648,"*sexo*",Catálogo!$L$2:$L$648,"*edad*",Catálogo!$Q$2:$Q$648,{1,2,3,4,5,6,7,8,9})>0,0),0)>0,INDEX(Niveles!$C$2:$C$10,IFERROR(MATCH(TRUE,COUNTIFS(Catálogo!$J$2:$J$648,"*"&$A16&"*",Catálogo!$I$2:$I$648,"<>ausente",Catálogo!$M$2:$M$648,"completa",Catálogo!$L$2:$L$648,"*sexo*",Catálogo!$L$2:$L$648,"*edad*",Catálogo!$Q$2:$Q$648,{1,2,3,4,5,6,7,8,9})>0,0),0))&IF(AND(IFERROR(MATCH(TRUE,COUNTIFS(Catálogo!$J$2:$J$648,"*"&$A16&"*",Catálogo!$I$2:$I$648,"<>ausente",Catálogo!$M$2:$M$648,"parcial",Catálogo!$L$2:$L$648,"*sexo*",Catálogo!$L$2:$L$648,"*edad*",Catálogo!$Q$2:$Q$648,{1,2,3,4,5,6,7,8,9})>0,0),0)>0,IFERROR(MATCH(TRUE,COUNTIFS(Catálogo!$J$2:$J$648,"*"&$A16&"*",Catálogo!$I$2:$I$648,"<>ausente",Catálogo!$M$2:$M$648,"parcial",Catálogo!$L$2:$L$648,"*sexo*",Catálogo!$L$2:$L$648,"*edad*",Catálogo!$Q$2:$Q$648,{1,2,3,4,5,6,7,8,9})>0,0),0)<IFERROR(MATCH(TRUE,COUNTIFS(Catálogo!$J$2:$J$648,"*"&$A16&"*",Catálogo!$I$2:$I$648,"<>ausente",Catálogo!$M$2:$M$648,"completa",Catálogo!$L$2:$L$648,"*sexo*",Catálogo!$L$2:$L$648,"*edad*",Catálogo!$Q$2:$Q$648,{1,2,3,4,5,6,7,8,9})>0,0),0)),"; "&LOWER(INDEX(Niveles!$C$2:$C$10,IFERROR(MATCH(TRUE,COUNTIFS(Catálogo!$J$2:$J$648,"*"&$A16&"*",Catálogo!$I$2:$I$648,"<>ausente",Catálogo!$M$2:$M$648,"parcial",Catálogo!$L$2:$L$648,"*sexo*",Catálogo!$L$2:$L$648,"*edad*",Catálogo!$Q$2:$Q$648,{1,2,3,4,5,6,7,8,9})>0,0),0)))&" (parcial)",""),IF(IFERROR(MATCH(TRUE,COUNTIFS(Catálogo!$J$2:$J$648,"*"&$A16&"*",Catálogo!$I$2:$I$648,"<>ausente",Catálogo!$M$2:$M$648,"parcial",Catálogo!$L$2:$L$648,"*sexo*",Catálogo!$L$2:$L$648,"*edad*",Catálogo!$Q$2:$Q$648,{1,2,3,4,5,6,7,8,9})>0,0),0)>0,INDEX(Niveles!$C$2:$C$10,IFERROR(MATCH(TRUE,COUNTIFS(Catálogo!$J$2:$J$648,"*"&$A16&"*",Catálogo!$I$2:$I$648,"<>ausente",Catálogo!$M$2:$M$648,"parcial",Catálogo!$L$2:$L$648,"*sexo*",Catálogo!$L$2:$L$648,"*edad*",Catálogo!$Q$2:$Q$648,{1,2,3,4,5,6,7,8,9})>0,0),0))&" (parcial)","—")) -> Provincia | U16: =SUMIFS(Cifras!$J$2:$J$399,Cifras!$A$2:$A$399,$A16) -> 11 | V16: Núcleo completo | W16: Opcional: edades individuales por provincia y sexo (pág. 8, PDF ~14). El volumen no trae edad por comuna ni área × edad. | X16: Comuna × área × sexo con viviendas (cifras ajustadas, pág. 76) y provincia × sexo × edad quinquenal (cifras revisadas, pág. 332; coincide con los comparativos de 1952). Las dos series difieren por el ajuste de ~2,8 %.
A17: 1952 | B17: pub_1952 | C17: 2431 | D17: =COUNTIFS(Catálogo!$B$2:$B$648,$A17) -> 134 | E17: =COUNTIFS(Catálogo!$B$2:$B$648,$A17,Catálogo!$F$2:$F$648,"cuadro") -> 111 | F17: =COUNTIFS(Catálogo!$B$2:$B$648,$A17,Catálogo!$F$2:$F$648,"bloque") -> 15 | G17: =COUNTIFS(Catálogo!$B$2:$B$648,$A17,Catálogo!$F$2:$F$648,"texto") -> 8 | H17: =COUNTIFS(Catálogo!$B$2:$B$648,$A17,Catálogo!$I$2:$I$648,"verificada") -> 125 | I17: =COUNTIFS(Catálogo!$B$2:$B$648,$A17,Catálogo!$I$2:$I$648,"estimada") -> 8 | J17: =COUNTIFS(Catálogo!$B$2:$B$648,$A17,Catálogo!$I$2:$I$648,"desconocida")+COUNTIFS(Catálogo!$B$2:$B$648,$A17,Catálogo!$I$2:$I$648,"ausente") -> 1 | K17: =COUNTIFS(Catálogo!$B$2:$B$648,$A17,Catálogo!$O$2:$O$648,"transcrito") -> 8 | L17: =SUMIFS(Cifras!$H$2:$H$399,Cifras!$A$2:$A$399,$A17) -> 1896 | M17: =IF(COUNTIFS(Cifras!$A$2:$A$399,$A17,Cifras!$D$2:$D$399,"distrito")>0,"Distrito",IF(COUNTIFS(Cifras!$A$2:$A$399,$A17,Cifras!$D$2:$D$399,"comuna")>0,"Comuna",IF(COUNTIFS(Cifras!$A$2:$A$399,$A17,Cifras!$D$2:$D$399,"partido")>0,"Partido",IF(COUNTIFS(Cifras!$A$2:$A$399,$A17,Cifras!$D$2:$D$399,"departamento")>0,"Departamento",IF(COUNTIFS(Cifras!$A$2:$A$399,$A17,Cifras!$D$2:$D$399,"provincia")>0,"Provincia",IF(COUNTIFS(Cifras!$A$2:$A$399,$A17,Cifras!$D$2:$D$399,"region")>0,"Región",IF(COUNTIFS(Cifras!$A$2:$A$399,$A17,Cifras!$D$2:$D$399,"pais")>0,"País","—"))))))) -> Comuna | N17: =IF(IFERROR(MATCH(TRUE,COUNTIFS(Catálogo!$J$2:$J$648,"*"&$A17&"*",Catálogo!$I$2:$I$648,"<>ausente",Catálogo!$M$2:$M$648,"completa",Catálogo!$Q$2:$Q$648,{1,2,3,4,5,6,7,8,9})>0,0),0)>0,INDEX(Niveles!$C$2:$C$10,IFERROR(MATCH(TRUE,COUNTIFS(Catálogo!$J$2:$J$648,"*"&$A17&"*",Catálogo!$I$2:$I$648,"<>ausente",Catálogo!$M$2:$M$648,"completa",Catálogo!$Q$2:$Q$648,{1,2,3,4,5,6,7,8,9})>0,0),0))&IF(AND(IFERROR(MATCH(TRUE,COUNTIFS(Catálogo!$J$2:$J$648,"*"&$A17&"*",Catálogo!$I$2:$I$648,"<>ausente",Catálogo!$M$2:$M$648,"parcial",Catálogo!$Q$2:$Q$648,{1,2,3,4,5,6,7,8,9})>0,0),0)>0,IFERROR(MATCH(TRUE,COUNTIFS(Catálogo!$J$2:$J$648,"*"&$A17&"*",Catálogo!$I$2:$I$648,"<>ausente",Catálogo!$M$2:$M$648,"parcial",Catálogo!$Q$2:$Q$648,{1,2,3,4,5,6,7,8,9})>0,0),0)<IFERROR(MATCH(TRUE,COUNTIFS(Catálogo!$J$2:$J$648,"*"&$A17&"*",Catálogo!$I$2:$I$648,"<>ausente",Catálogo!$M$2:$M$648,"completa",Catálogo!$Q$2:$Q$648,{1,2,3,4,5,6,7,8,9})>0,0),0)),"; "&LOWER(INDEX(Niveles!$C$2:$C$10,IFERROR(MATCH(TRUE,COUNTIFS(Catálogo!$J$2:$J$648,"*"&$A17&"*",Catálogo!$I$2:$I$648,"<>ausente",Catálogo!$M$2:$M$648,"parcial",Catálogo!$Q$2:$Q$648,{1,2,3,4,5,6,7,8,9})>0,0),0)))&" (parcial)",""),IF(IFERROR(MATCH(TRUE,COUNTIFS(Catálogo!$J$2:$J$648,"*"&$A17&"*",Catálogo!$I$2:$I$648,"<>ausente",Catálogo!$M$2:$M$648,"parcial",Catálogo!$Q$2:$Q$648,{1,2,3,4,5,6,7,8,9})>0,0),0)>0,INDEX(Niveles!$C$2:$C$10,IFERROR(MATCH(TRUE,COUNTIFS(Catálogo!$J$2:$J$648,"*"&$A17&"*",Catálogo!$I$2:$I$648,"<>ausente",Catálogo!$M$2:$M$648,"parcial",Catálogo!$Q$2:$Q$648,{1,2,3,4,5,6,7,8,9})>0,0),0))&" (parcial)","—")) -> Comuna; entidad (parcial) | O17: =IF(COUNTIFS(Cifras!$A$2:$A$399,$A17,Cifras!$E$2:$E$399,"Sí",Cifras!$D$2:$D$399,"distrito")>0,"Distrito",IF(COUNTIFS(Cifras!$A$2:$A$399,$A17,Cifras!$E$2:$E$399,"Sí",Cifras!$D$2:$D$399,"comuna")>0,"Comuna",IF(COUNTIFS(Cifras!$A$2:$A$399,$A17,Cifras!$E$2:$E$399,"Sí",Cifras!$D$2:$D$399,"partido")>0,"Partido",IF(COUNTIFS(Cifras!$A$2:$A$399,$A17,Cifras!$E$2:$E$399,"Sí",Cifras!$D$2:$D$399,"departamento")>0,"Departamento",IF(COUNTIFS(Cifras!$A$2:$A$399,$A17,Cifras!$E$2:$E$399,"Sí",Cifras!$D$2:$D$399,"provincia")>0,"Provincia",IF(COUNTIFS(Cifras!$A$2:$A$399,$A17,Cifras!$E$2:$E$399,"Sí",Cifras!$D$2:$D$399,"region")>0,"Región",IF(COUNTIFS(Cifras!$A$2:$A$399,$A17,Cifras!$E$2:$E$399,"Sí",Cifras!$D$2:$D$399,"pais")>0,"País","—"))))))) -> Provincia | P17: =IF(IFERROR(MATCH(TRUE,COUNTIFS(Catálogo!$J$2:$J$648,"*"&$A17&"*",Catálogo!$I$2:$I$648,"<>ausente",Catálogo!$M$2:$M$648,"completa",Catálogo!$L$2:$L$648,"*area*",Catálogo!$Q$2:$Q$648,{1,2,3,4,5,6,7,8,9})>0,0),0)>0,INDEX(Niveles!$C$2:$C$10,IFERROR(MATCH(TRUE,COUNTIFS(Catálogo!$J$2:$J$648,"*"&$A17&"*",Catálogo!$I$2:$I$648,"<>ausente",Catálogo!$M$2:$M$648,"completa",Catálogo!$L$2:$L$648,"*area*",Catálogo!$Q$2:$Q$648,{1,2,3,4,5,6,7,8,9})>0,0),0))&IF(AND(IFERROR(MATCH(TRUE,COUNTIFS(Catálogo!$J$2:$J$648,"*"&$A17&"*",Catálogo!$I$2:$I$648,"<>ausente",Catálogo!$M$2:$M$648,"parcial",Catálogo!$L$2:$L$648,"*area*",Catálogo!$Q$2:$Q$648,{1,2,3,4,5,6,7,8,9})>0,0),0)>0,IFERROR(MATCH(TRUE,COUNTIFS(Catálogo!$J$2:$J$648,"*"&$A17&"*",Catálogo!$I$2:$I$648,"<>ausente",Catálogo!$M$2:$M$648,"parcial",Catálogo!$L$2:$L$648,"*area*",Catálogo!$Q$2:$Q$648,{1,2,3,4,5,6,7,8,9})>0,0),0)<IFERROR(MATCH(TRUE,COUNTIFS(Catálogo!$J$2:$J$648,"*"&$A17&"*",Catálogo!$I$2:$I$648,"<>ausente",Catálogo!$M$2:$M$648,"completa",Catálogo!$L$2:$L$648,"*area*",Catálogo!$Q$2:$Q$648,{1,2,3,4,5,6,7,8,9})>0,0),0)),"; "&LOWER(INDEX(Niveles!$C$2:$C$10,IFERROR(MATCH(TRUE,COUNTIFS(Catálogo!$J$2:$J$648,"*"&$A17&"*",Catálogo!$I$2:$I$648,"<>ausente",Catálogo!$M$2:$M$648,"parcial",Catálogo!$L$2:$L$648,"*area*",Catálogo!$Q$2:$Q$648,{1,2,3,4,5,6,7,8,9})>0,0),0)))&" (parcial)",""),IF(IFERROR(MATCH(TRUE,COUNTIFS(Catálogo!$J$2:$J$648,"*"&$A17&"*",Catálogo!$I$2:$I$648,"<>ausente",Catálogo!$M$2:$M$648,"parcial",Catálogo!$L$2:$L$648,"*area*",Catálogo!$Q$2:$Q$648,{1,2,3,4,5,6,7,8,9})>0,0),0)>0,INDEX(Niveles!$C$2:$C$10,IFERROR(MATCH(TRUE,COUNTIFS(Catálogo!$J$2:$J$648,"*"&$A17&"*",Catálogo!$I$2:$I$648,"<>ausente",Catálogo!$M$2:$M$648,"parcial",Catálogo!$L$2:$L$648,"*area*",Catálogo!$Q$2:$Q$648,{1,2,3,4,5,6,7,8,9})>0,0),0))&" (parcial)","—")) -> Provincia; comuna (parcial) | Q17: =IF(COUNTIFS(Cifras!$A$2:$A$399,$A17,Cifras!$E$2:$E$399,"Sí",Cifras!$F$2:$F$399,"Sí",Cifras!$D$2:$D$399,"distrito")>0,"Distrito",IF(COUNTIFS(Cifras!$A$2:$A$399,$A17,Cifras!$E$2:$E$399,"Sí",Cifras!$F$2:$F$399,"Sí",Cifras!$D$2:$D$399,"comuna")>0,"Comuna",IF(COUNTIFS(Cifras!$A$2:$A$399,$A17,Cifras!$E$2:$E$399,"Sí",Cifras!$F$2:$F$399,"Sí",Cifras!$D$2:$D$399,"partido")>0,"Partido",IF(COUNTIFS(Cifras!$A$2:$A$399,$A17,Cifras!$E$2:$E$399,"Sí",Cifras!$F$2:$F$399,"Sí",Cifras!$D$2:$D$399,"departamento")>0,"Departamento",IF(COUNTIFS(Cifras!$A$2:$A$399,$A17,Cifras!$E$2:$E$399,"Sí",Cifras!$F$2:$F$399,"Sí",Cifras!$D$2:$D$399,"provincia")>0,"Provincia",IF(COUNTIFS(Cifras!$A$2:$A$399,$A17,Cifras!$E$2:$E$399,"Sí",Cifras!$F$2:$F$399,"Sí",Cifras!$D$2:$D$399,"region")>0,"Región",IF(COUNTIFS(Cifras!$A$2:$A$399,$A17,Cifras!$E$2:$E$399,"Sí",Cifras!$F$2:$F$399,"Sí",Cifras!$D$2:$D$399,"pais")>0,"País","—"))))))) -> Provincia | R17: =IF(IFERROR(MATCH(TRUE,COUNTIFS(Catálogo!$J$2:$J$648,"*"&$A17&"*",Catálogo!$I$2:$I$648,"<>ausente",Catálogo!$M$2:$M$648,"completa",Catálogo!$L$2:$L$648,"*area*",Catálogo!$L$2:$L$648,"*sexo*",Catálogo!$Q$2:$Q$648,{1,2,3,4,5,6,7,8,9})>0,0),0)>0,INDEX(Niveles!$C$2:$C$10,IFERROR(MATCH(TRUE,COUNTIFS(Catálogo!$J$2:$J$648,"*"&$A17&"*",Catálogo!$I$2:$I$648,"<>ausente",Catálogo!$M$2:$M$648,"completa",Catálogo!$L$2:$L$648,"*area*",Catálogo!$L$2:$L$648,"*sexo*",Catálogo!$Q$2:$Q$648,{1,2,3,4,5,6,7,8,9})>0,0),0))&IF(AND(IFERROR(MATCH(TRUE,COUNTIFS(Catálogo!$J$2:$J$648,"*"&$A17&"*",Catálogo!$I$2:$I$648,"<>ausente",Catálogo!$M$2:$M$648,"parcial",Catálogo!$L$2:$L$648,"*area*",Catálogo!$L$2:$L$648,"*sexo*",Catálogo!$Q$2:$Q$648,{1,2,3,4,5,6,7,8,9})>0,0),0)>0,IFERROR(MATCH(TRUE,COUNTIFS(Catálogo!$J$2:$J$648,"*"&$A17&"*",Catálogo!$I$2:$I$648,"<>ausente",Catálogo!$M$2:$M$648,"parcial",Catálogo!$L$2:$L$648,"*area*",Catálogo!$L$2:$L$648,"*sexo*",Catálogo!$Q$2:$Q$648,{1,2,3,4,5,6,7,8,9})>0,0),0)<IFERROR(MATCH(TRUE,COUNTIFS(Catálogo!$J$2:$J$648,"*"&$A17&"*",Catálogo!$I$2:$I$648,"<>ausente",Catálogo!$M$2:$M$648,"completa",Catálogo!$L$2:$L$648,"*area*",Catálogo!$L$2:$L$648,"*sexo*",Catálogo!$Q$2:$Q$648,{1,2,3,4,5,6,7,8,9})>0,0),0)),"; "&LOWER(INDEX(Niveles!$C$2:$C$10,IFERROR(MATCH(TRUE,COUNTIFS(Catálogo!$J$2:$J$648,"*"&$A17&"*",Catálogo!$I$2:$I$648,"<>ausente",Catálogo!$M$2:$M$648,"parcial",Catálogo!$L$2:$L$648,"*area*",Catálogo!$L$2:$L$648,"*sexo*",Catálogo!$Q$2:$Q$648,{1,2,3,4,5,6,7,8,9})>0,0),0)))&" (parcial)",""),IF(IFERROR(MATCH(TRUE,COUNTIFS(Catálogo!$J$2:$J$648,"*"&$A17&"*",Catálogo!$I$2:$I$648,"<>ausente",Catálogo!$M$2:$M$648,"parcial",Catálogo!$L$2:$L$648,"*area*",Catálogo!$L$2:$L$648,"*sexo*",Catálogo!$Q$2:$Q$648,{1,2,3,4,5,6,7,8,9})>0,0),0)>0,INDEX(Niveles!$C$2:$C$10,IFERROR(MATCH(TRUE,COUNTIFS(Catálogo!$J$2:$J$648,"*"&$A17&"*",Catálogo!$I$2:$I$648,"<>ausente",Catálogo!$M$2:$M$648,"parcial",Catálogo!$L$2:$L$648,"*area*",Catálogo!$L$2:$L$648,"*sexo*",Catálogo!$Q$2:$Q$648,{1,2,3,4,5,6,7,8,9})>0,0),0))&" (parcial)","—")) -> Provincia; comuna (parcial) | S17: =IF(COUNTIFS(Cifras!$A$2:$A$399,$A17,Cifras!$F$2:$F$399,"Sí",Cifras!$G$2:$G$399,"Sí",Cifras!$D$2:$D$399,"distrito")>0,"Distrito",IF(COUNTIFS(Cifras!$A$2:$A$399,$A17,Cifras!$F$2:$F$399,"Sí",Cifras!$G$2:$G$399,"Sí",Cifras!$D$2:$D$399,"comuna")>0,"Comuna",IF(COUNTIFS(Cifras!$A$2:$A$399,$A17,Cifras!$F$2:$F$399,"Sí",Cifras!$G$2:$G$399,"Sí",Cifras!$D$2:$D$399,"partido")>0,"Partido",IF(COUNTIFS(Cifras!$A$2:$A$399,$A17,Cifras!$F$2:$F$399,"Sí",Cifras!$G$2:$G$399,"Sí",Cifras!$D$2:$D$399,"departamento")>0,"Departamento",IF(COUNTIFS(Cifras!$A$2:$A$399,$A17,Cifras!$F$2:$F$399,"Sí",Cifras!$G$2:$G$399,"Sí",Cifras!$D$2:$D$399,"provincia")>0,"Provincia",IF(COUNTIFS(Cifras!$A$2:$A$399,$A17,Cifras!$F$2:$F$399,"Sí",Cifras!$G$2:$G$399,"Sí",Cifras!$D$2:$D$399,"region")>0,"Región",IF(COUNTIFS(Cifras!$A$2:$A$399,$A17,Cifras!$F$2:$F$399,"Sí",Cifras!$G$2:$G$399,"Sí",Cifras!$D$2:$D$399,"pais")>0,"País","—"))))))) -> País | T17: =IF(IFERROR(MATCH(TRUE,COUNTIFS(Catálogo!$J$2:$J$648,"*"&$A17&"*",Catálogo!$I$2:$I$648,"<>ausente",Catálogo!$M$2:$M$648,"completa",Catálogo!$L$2:$L$648,"*sexo*",Catálogo!$L$2:$L$648,"*edad*",Catálogo!$Q$2:$Q$648,{1,2,3,4,5,6,7,8,9})>0,0),0)>0,INDEX(Niveles!$C$2:$C$10,IFERROR(MATCH(TRUE,COUNTIFS(Catálogo!$J$2:$J$648,"*"&$A17&"*",Catálogo!$I$2:$I$648,"<>ausente",Catálogo!$M$2:$M$648,"completa",Catálogo!$L$2:$L$648,"*sexo*",Catálogo!$L$2:$L$648,"*edad*",Catálogo!$Q$2:$Q$648,{1,2,3,4,5,6,7,8,9})>0,0),0))&IF(AND(IFERROR(MATCH(TRUE,COUNTIFS(Catálogo!$J$2:$J$648,"*"&$A17&"*",Catálogo!$I$2:$I$648,"<>ausente",Catálogo!$M$2:$M$648,"parcial",Catálogo!$L$2:$L$648,"*sexo*",Catálogo!$L$2:$L$648,"*edad*",Catálogo!$Q$2:$Q$648,{1,2,3,4,5,6,7,8,9})>0,0),0)>0,IFERROR(MATCH(TRUE,COUNTIFS(Catálogo!$J$2:$J$648,"*"&$A17&"*",Catálogo!$I$2:$I$648,"<>ausente",Catálogo!$M$2:$M$648,"parcial",Catálogo!$L$2:$L$648,"*sexo*",Catálogo!$L$2:$L$648,"*edad*",Catálogo!$Q$2:$Q$648,{1,2,3,4,5,6,7,8,9})>0,0),0)<IFERROR(MATCH(TRUE,COUNTIFS(Catálogo!$J$2:$J$648,"*"&$A17&"*",Catálogo!$I$2:$I$648,"<>ausente",Catálogo!$M$2:$M$648,"completa",Catálogo!$L$2:$L$648,"*sexo*",Catálogo!$L$2:$L$648,"*edad*",Catálogo!$Q$2:$Q$648,{1,2,3,4,5,6,7,8,9})>0,0),0)),"; "&LOWER(INDEX(Niveles!$C$2:$C$10,IFERROR(MATCH(TRUE,COUNTIFS(Catálogo!$J$2:$J$648,"*"&$A17&"*",Catálogo!$I$2:$I$648,"<>ausente",Catálogo!$M$2:$M$648,"parcial",Catálogo!$L$2:$L$648,"*sexo*",Catálogo!$L$2:$L$648,"*edad*",Catálogo!$Q$2:$Q$648,{1,2,3,4,5,6,7,8,9})>0,0),0)))&" (parcial)",""),IF(IFERROR(MATCH(TRUE,COUNTIFS(Catálogo!$J$2:$J$648,"*"&$A17&"*",Catálogo!$I$2:$I$648,"<>ausente",Catálogo!$M$2:$M$648,"parcial",Catálogo!$L$2:$L$648,"*sexo*",Catálogo!$L$2:$L$648,"*edad*",Catálogo!$Q$2:$Q$648,{1,2,3,4,5,6,7,8,9})>0,0),0)>0,INDEX(Niveles!$C$2:$C$10,IFERROR(MATCH(TRUE,COUNTIFS(Catálogo!$J$2:$J$648,"*"&$A17&"*",Catálogo!$I$2:$I$648,"<>ausente",Catálogo!$M$2:$M$648,"parcial",Catálogo!$L$2:$L$648,"*sexo*",Catálogo!$L$2:$L$648,"*edad*",Catálogo!$Q$2:$Q$648,{1,2,3,4,5,6,7,8,9})>0,0),0))&" (parcial)","—")) -> País; comuna (parcial) | U17: =SUMIFS(Cifras!$J$2:$J$399,Cifras!$A$2:$A$399,$A17) -> 4 | V17: Falta edad | W17: Edad bajo el país: comuna × área × sexo × edad solo para el Núcleo Central (Tomo II, Cuadro 1 de cada provincia: muy extenso). Sexo por comuna para 14 provincias en la división territorial (mecanografiada). | X17: Comuna (total, Cuadro Nacional 4: 271 comunas), provincia × área × sexo (Cuadro Nacional 2) y país × área × sexo × edad simple (Cuadro Nacional 1; quinquenios = Cuadro Nacional 7). Los cuadros nacionales 1 y 2 faltan en el escaneo del INE (págs. 85–116) y se leyeron en la copia de Memoria Chilena; coinciden con los comparativos 5 y 9. Errata: hombres rurales de 12 años.
A18: 1960 | B18: pub_1960 | C18: 474 | D18: =COUNTIFS(Catálogo!$B$2:$B$648,$A18) -> 97 | E18: =COUNTIFS(Catálogo!$B$2:$B$648,$A18,Catálogo!$F$2:$F$648,"cuadro") -> 68 | F18: =COUNTIFS(Catálogo!$B$2:$B$648,$A18,Catálogo!$F$2:$F$648,"bloque") -> 0 | G18: =COUNTIFS(Catálogo!$B$2:$B$648,$A18,Catálogo!$F$2:$F$648,"texto") -> 29 | H18: =COUNTIFS(Catálogo!$B$2:$B$648,$A18,Catálogo!$I$2:$I$648,"verificada") -> 5 | I18: =COUNTIFS(Catálogo!$B$2:$B$648,$A18,Catálogo!$I$2:$I$648,"estimada") -> 91 | J18: =COUNTIFS(Catálogo!$B$2:$B$648,$A18,Catálogo!$I$2:$I$648,"desconocida")+COUNTIFS(Catálogo!$B$2:$B$648,$A18,Catálogo!$I$2:$I$648,"ausente") -> 1 | K18: =COUNTIFS(Catálogo!$B$2:$B$648,$A18,Catálogo!$O$2:$O$648,"transcrito") -> 4 | L18: =SUMIFS(Cifras!$H$2:$H$399,Cifras!$A$2:$A$399,$A18) -> 1797 | M18: =IF(COUNTIFS(Cifras!$A$2:$A$399,$A18,Cifras!$D$2:$D$399,"distrito")>0,"Distrito",IF(COUNTIFS(Cifras!$A$2:$A$399,$A18,Cifras!$D$2:$D$399,"comuna")>0,"Comuna",IF(COUNTIFS(Cifras!$A$2:$A$399,$A18,Cifras!$D$2:$D$399,"partido")>0,"Partido",IF(COUNTIFS(Cifras!$A$2:$A$399,$A18,Cifras!$D$2:$D$399,"departamento")>0,"Departamento",IF(COUNTIFS(Cifras!$A$2:$A$399,$A18,Cifras!$D$2:$D$399,"provincia")>0,"Provincia",IF(COUNTIFS(Cifras!$A$2:$A$399,$A18,Cifras!$D$2:$D$399,"region")>0,"Región",IF(COUNTIFS(Cifras!$A$2:$A$399,$A18,Cifras!$D$2:$D$399,"pais")>0,"País","—"))))))) -> Provincia | N18: =IF(IFERROR(MATCH(TRUE,COUNTIFS(Catálogo!$J$2:$J$648,"*"&$A18&"*",Catálogo!$I$2:$I$648,"<>ausente",Catálogo!$M$2:$M$648,"completa",Catálogo!$Q$2:$Q$648,{1,2,3,4,5,6,7,8,9})>0,0),0)>0,INDEX(Niveles!$C$2:$C$10,IFERROR(MATCH(TRUE,COUNTIFS(Catálogo!$J$2:$J$648,"*"&$A18&"*",Catálogo!$I$2:$I$648,"<>ausente",Catálogo!$M$2:$M$648,"completa",Catálogo!$Q$2:$Q$648,{1,2,3,4,5,6,7,8,9})>0,0),0))&IF(AND(IFERROR(MATCH(TRUE,COUNTIFS(Catálogo!$J$2:$J$648,"*"&$A18&"*",Catálogo!$I$2:$I$648,"<>ausente",Catálogo!$M$2:$M$648,"parcial",Catálogo!$Q$2:$Q$648,{1,2,3,4,5,6,7,8,9})>0,0),0)>0,IFERROR(MATCH(TRUE,COUNTIFS(Catálogo!$J$2:$J$648,"*"&$A18&"*",Catálogo!$I$2:$I$648,"<>ausente",Catálogo!$M$2:$M$648,"parcial",Catálogo!$Q$2:$Q$648,{1,2,3,4,5,6,7,8,9})>0,0),0)<IFERROR(MATCH(TRUE,COUNTIFS(Catálogo!$J$2:$J$648,"*"&$A18&"*",Catálogo!$I$2:$I$648,"<>ausente",Catálogo!$M$2:$M$648,"completa",Catálogo!$Q$2:$Q$648,{1,2,3,4,5,6,7,8,9})>0,0),0)),"; "&LOWER(INDEX(Niveles!$C$2:$C$10,IFERROR(MATCH(TRUE,COUNTIFS(Catálogo!$J$2:$J$648,"*"&$A18&"*",Catálogo!$I$2:$I$648,"<>ausente",Catálogo!$M$2:$M$648,"parcial",Catálogo!$Q$2:$Q$648,{1,2,3,4,5,6,7,8,9})>0,0),0)))&" (parcial)",""),IF(IFERROR(MATCH(TRUE,COUNTIFS(Catálogo!$J$2:$J$648,"*"&$A18&"*",Catálogo!$I$2:$I$648,"<>ausente",Catálogo!$M$2:$M$648,"parcial",Catálogo!$Q$2:$Q$648,{1,2,3,4,5,6,7,8,9})>0,0),0)>0,INDEX(Niveles!$C$2:$C$10,IFERROR(MATCH(TRUE,COUNTIFS(Catálogo!$J$2:$J$648,"*"&$A18&"*",Catálogo!$I$2:$I$648,"<>ausente",Catálogo!$M$2:$M$648,"parcial",Catálogo!$Q$2:$Q$648,{1,2,3,4,5,6,7,8,9})>0,0),0))&" (parcial)","—")) -> Provincia; comuna (parcial) | O18: =IF(COUNTIFS(Cifras!$A$2:$A$399,$A18,Cifras!$E$2:$E$399,"Sí",Cifras!$D$2:$D$399,"distrito")>0,"Distrito",IF(COUNTIFS(Cifras!$A$2:$A$399,$A18,Cifras!$E$2:$E$399,"Sí",Cifras!$D$2:$D$399,"comuna")>0,"Comuna",IF(COUNTIFS(Cifras!$A$2:$A$399,$A18,Cifras!$E$2:$E$399,"Sí",Cifras!$D$2:$D$399,"partido")>0,"Partido",IF(COUNTIFS(Cifras!$A$2:$A$399,$A18,Cifras!$E$2:$E$399,"Sí",Cifras!$D$2:$D$399,"departamento")>0,"Departamento",IF(COUNTIFS(Cifras!$A$2:$A$399,$A18,Cifras!$E$2:$E$399,"Sí",Cifras!$D$2:$D$399,"provincia")>0,"Provincia",IF(COUNTIFS(Cifras!$A$2:$A$399,$A18,Cifras!$E$2:$E$399,"Sí",Cifras!$D$2:$D$399,"region")>0,"Región",IF(COUNTIFS(Cifras!$A$2:$A$399,$A18,Cifras!$E$2:$E$399,"Sí",Cifras!$D$2:$D$399,"pais")>0,"País","—"))))))) -> Provincia | P18: =IF(IFERROR(MATCH(TRUE,COUNTIFS(Catálogo!$J$2:$J$648,"*"&$A18&"*",Catálogo!$I$2:$I$648,"<>ausente",Catálogo!$M$2:$M$648,"completa",Catálogo!$L$2:$L$648,"*area*",Catálogo!$Q$2:$Q$648,{1,2,3,4,5,6,7,8,9})>0,0),0)>0,INDEX(Niveles!$C$2:$C$10,IFERROR(MATCH(TRUE,COUNTIFS(Catálogo!$J$2:$J$648,"*"&$A18&"*",Catálogo!$I$2:$I$648,"<>ausente",Catálogo!$M$2:$M$648,"completa",Catálogo!$L$2:$L$648,"*area*",Catálogo!$Q$2:$Q$648,{1,2,3,4,5,6,7,8,9})>0,0),0))&IF(AND(IFERROR(MATCH(TRUE,COUNTIFS(Catálogo!$J$2:$J$648,"*"&$A18&"*",Catálogo!$I$2:$I$648,"<>ausente",Catálogo!$M$2:$M$648,"parcial",Catálogo!$L$2:$L$648,"*area*",Catálogo!$Q$2:$Q$648,{1,2,3,4,5,6,7,8,9})>0,0),0)>0,IFERROR(MATCH(TRUE,COUNTIFS(Catálogo!$J$2:$J$648,"*"&$A18&"*",Catálogo!$I$2:$I$648,"<>ausente",Catálogo!$M$2:$M$648,"parcial",Catálogo!$L$2:$L$648,"*area*",Catálogo!$Q$2:$Q$648,{1,2,3,4,5,6,7,8,9})>0,0),0)<IFERROR(MATCH(TRUE,COUNTIFS(Catálogo!$J$2:$J$648,"*"&$A18&"*",Catálogo!$I$2:$I$648,"<>ausente",Catálogo!$M$2:$M$648,"completa",Catálogo!$L$2:$L$648,"*area*",Catálogo!$Q$2:$Q$648,{1,2,3,4,5,6,7,8,9})>0,0),0)),"; "&LOWER(INDEX(Niveles!$C$2:$C$10,IFERROR(MATCH(TRUE,COUNTIFS(Catálogo!$J$2:$J$648,"*"&$A18&"*",Catálogo!$I$2:$I$648,"<>ausente",Catálogo!$M$2:$M$648,"parcial",Catálogo!$L$2:$L$648,"*area*",Catálogo!$Q$2:$Q$648,{1,2,3,4,5,6,7,8,9})>0,0),0)))&" (parcial)",""),IF(IFERROR(MATCH(TRUE,COUNTIFS(Catálogo!$J$2:$J$648,"*"&$A18&"*",Catálogo!$I$2:$I$648,"<>ausente",Catálogo!$M$2:$M$648,"parcial",Catálogo!$L$2:$L$648,"*area*",Catálogo!$Q$2:$Q$648,{1,2,3,4,5,6,7,8,9})>0,0),0)>0,INDEX(Niveles!$C$2:$C$10,IFERROR(MATCH(TRUE,COUNTIFS(Catálogo!$J$2:$J$648,"*"&$A18&"*",Catálogo!$I$2:$I$648,"<>ausente",Catálogo!$M$2:$M$648,"parcial",Catálogo!$L$2:$L$648,"*area*",Catálogo!$Q$2:$Q$648,{1,2,3,4,5,6,7,8,9})>0,0),0))&" (parcial)","—")) -> Provincia | Q18: =IF(COUNTIFS(Cifras!$A$2:$A$399,$A18,Cifras!$E$2:$E$399,"Sí",Cifras!$F$2:$F$399,"Sí",Cifras!$D$2:$D$399,"distrito")>0,"Distrito",IF(COUNTIFS(Cifras!$A$2:$A$399,$A18,Cifras!$E$2:$E$399,"Sí",Cifras!$F$2:$F$399,"Sí",Cifras!$D$2:$D$399,"comuna")>0,"Comuna",IF(COUNTIFS(Cifras!$A$2:$A$399,$A18,Cifras!$E$2:$E$399,"Sí",Cifras!$F$2:$F$399,"Sí",Cifras!$D$2:$D$399,"partido")>0,"Partido",IF(COUNTIFS(Cifras!$A$2:$A$399,$A18,Cifras!$E$2:$E$399,"Sí",Cifras!$F$2:$F$399,"Sí",Cifras!$D$2:$D$399,"departamento")>0,"Departamento",IF(COUNTIFS(Cifras!$A$2:$A$399,$A18,Cifras!$E$2:$E$399,"Sí",Cifras!$F$2:$F$399,"Sí",Cifras!$D$2:$D$399,"provincia")>0,"Provincia",IF(COUNTIFS(Cifras!$A$2:$A$399,$A18,Cifras!$E$2:$E$399,"Sí",Cifras!$F$2:$F$399,"Sí",Cifras!$D$2:$D$399,"region")>0,"Región",IF(COUNTIFS(Cifras!$A$2:$A$399,$A18,Cifras!$E$2:$E$399,"Sí",Cifras!$F$2:$F$399,"Sí",Cifras!$D$2:$D$399,"pais")>0,"País","—"))))))) -> Provincia | R18: =IF(IFERROR(MATCH(TRUE,COUNTIFS(Catálogo!$J$2:$J$648,"*"&$A18&"*",Catálogo!$I$2:$I$648,"<>ausente",Catálogo!$M$2:$M$648,"completa",Catálogo!$L$2:$L$648,"*area*",Catálogo!$L$2:$L$648,"*sexo*",Catálogo!$Q$2:$Q$648,{1,2,3,4,5,6,7,8,9})>0,0),0)>0,INDEX(Niveles!$C$2:$C$10,IFERROR(MATCH(TRUE,COUNTIFS(Catálogo!$J$2:$J$648,"*"&$A18&"*",Catálogo!$I$2:$I$648,"<>ausente",Catálogo!$M$2:$M$648,"completa",Catálogo!$L$2:$L$648,"*area*",Catálogo!$L$2:$L$648,"*sexo*",Catálogo!$Q$2:$Q$648,{1,2,3,4,5,6,7,8,9})>0,0),0))&IF(AND(IFERROR(MATCH(TRUE,COUNTIFS(Catálogo!$J$2:$J$648,"*"&$A18&"*",Catálogo!$I$2:$I$648,"<>ausente",Catálogo!$M$2:$M$648,"parcial",Catálogo!$L$2:$L$648,"*area*",Catálogo!$L$2:$L$648,"*sexo*",Catálogo!$Q$2:$Q$648,{1,2,3,4,5,6,7,8,9})>0,0),0)>0,IFERROR(MATCH(TRUE,COUNTIFS(Catálogo!$J$2:$J$648,"*"&$A18&"*",Catálogo!$I$2:$I$648,"<>ausente",Catálogo!$M$2:$M$648,"parcial",Catálogo!$L$2:$L$648,"*area*",Catálogo!$L$2:$L$648,"*sexo*",Catálogo!$Q$2:$Q$648,{1,2,3,4,5,6,7,8,9})>0,0),0)<IFERROR(MATCH(TRUE,COUNTIFS(Catálogo!$J$2:$J$648,"*"&$A18&"*",Catálogo!$I$2:$I$648,"<>ausente",Catálogo!$M$2:$M$648,"completa",Catálogo!$L$2:$L$648,"*area*",Catálogo!$L$2:$L$648,"*sexo*",Catálogo!$Q$2:$Q$648,{1,2,3,4,5,6,7,8,9})>0,0),0)),"; "&LOWER(INDEX(Niveles!$C$2:$C$10,IFERROR(MATCH(TRUE,COUNTIFS(Catálogo!$J$2:$J$648,"*"&$A18&"*",Catálogo!$I$2:$I$648,"<>ausente",Catálogo!$M$2:$M$648,"parcial",Catálogo!$L$2:$L$648,"*area*",Catálogo!$L$2:$L$648,"*sexo*",Catálogo!$Q$2:$Q$648,{1,2,3,4,5,6,7,8,9})>0,0),0)))&" (parcial)",""),IF(IFERROR(MATCH(TRUE,COUNTIFS(Catálogo!$J$2:$J$648,"*"&$A18&"*",Catálogo!$I$2:$I$648,"<>ausente",Catálogo!$M$2:$M$648,"parcial",Catálogo!$L$2:$L$648,"*area*",Catálogo!$L$2:$L$648,"*sexo*",Catálogo!$Q$2:$Q$648,{1,2,3,4,5,6,7,8,9})>0,0),0)>0,INDEX(Niveles!$C$2:$C$10,IFERROR(MATCH(TRUE,COUNTIFS(Catálogo!$J$2:$J$648,"*"&$A18&"*",Catálogo!$I$2:$I$648,"<>ausente",Catálogo!$M$2:$M$648,"parcial",Catálogo!$L$2:$L$648,"*area*",Catálogo!$L$2:$L$648,"*sexo*",Catálogo!$Q$2:$Q$648,{1,2,3,4,5,6,7,8,9})>0,0),0))&" (parcial)","—")) -> Provincia | S18: =IF(COUNTIFS(Cifras!$A$2:$A$399,$A18,Cifras!$F$2:$F$399,"Sí",Cifras!$G$2:$G$399,"Sí",Cifras!$D$2:$D$399,"distrito")>0,"Distrito",IF(COUNTIFS(Cifras!$A$2:$A$399,$A18,Cifras!$F$2:$F$399,"Sí",Cifras!$G$2:$G$399,"Sí",Cifras!$D$2:$D$399,"comuna")>0,"Comuna",IF(COUNTIFS(Cifras!$A$2:$A$399,$A18,Cifras!$F$2:$F$399,"Sí",Cifras!$G$2:$G$399,"Sí",Cifras!$D$2:$D$399,"partido")>0,"Partido",IF(COUNTIFS(Cifras!$A$2:$A$399,$A18,Cifras!$F$2:$F$399,"Sí",Cifras!$G$2:$G$399,"Sí",Cifras!$D$2:$D$399,"departamento")>0,"Departamento",IF(COUNTIFS(Cifras!$A$2:$A$399,$A18,Cifras!$F$2:$F$399,"Sí",Cifras!$G$2:$G$399,"Sí",Cifras!$D$2:$D$399,"provincia")>0,"Provincia",IF(COUNTIFS(Cifras!$A$2:$A$399,$A18,Cifras!$F$2:$F$399,"Sí",Cifras!$G$2:$G$399,"Sí",Cifras!$D$2:$D$399,"region")>0,"Región",IF(COUNTIFS(Cifras!$A$2:$A$399,$A18,Cifras!$F$2:$F$399,"Sí",Cifras!$G$2:$G$399,"Sí",Cifras!$D$2:$D$399,"pais")>0,"País","—"))))))) -> País | T18: =IF(IFERROR(MATCH(TRUE,COUNTIFS(Catálogo!$J$2:$J$648,"*"&$A18&"*",Catálogo!$I$2:$I$648,"<>ausente",Catálogo!$M$2:$M$648,"completa",Catálogo!$L$2:$L$648,"*sexo*",Catálogo!$L$2:$L$648,"*edad*",Catálogo!$Q$2:$Q$648,{1,2,3,4,5,6,7,8,9})>0,0),0)>0,INDEX(Niveles!$C$2:$C$10,IFERROR(MATCH(TRUE,COUNTIFS(Catálogo!$J$2:$J$648,"*"&$A18&"*",Catálogo!$I$2:$I$648,"<>ausente",Catálogo!$M$2:$M$648,"completa",Catálogo!$L$2:$L$648,"*sexo*",Catálogo!$L$2:$L$648,"*edad*",Catálogo!$Q$2:$Q$648,{1,2,3,4,5,6,7,8,9})>0,0),0))&IF(AND(IFERROR(MATCH(TRUE,COUNTIFS(Catálogo!$J$2:$J$648,"*"&$A18&"*",Catálogo!$I$2:$I$648,"<>ausente",Catálogo!$M$2:$M$648,"parcial",Catálogo!$L$2:$L$648,"*sexo*",Catálogo!$L$2:$L$648,"*edad*",Catálogo!$Q$2:$Q$648,{1,2,3,4,5,6,7,8,9})>0,0),0)>0,IFERROR(MATCH(TRUE,COUNTIFS(Catálogo!$J$2:$J$648,"*"&$A18&"*",Catálogo!$I$2:$I$648,"<>ausente",Catálogo!$M$2:$M$648,"parcial",Catálogo!$L$2:$L$648,"*sexo*",Catálogo!$L$2:$L$648,"*edad*",Catálogo!$Q$2:$Q$648,{1,2,3,4,5,6,7,8,9})>0,0),0)<IFERROR(MATCH(TRUE,COUNTIFS(Catálogo!$J$2:$J$648,"*"&$A18&"*",Catálogo!$I$2:$I$648,"<>ausente",Catálogo!$M$2:$M$648,"completa",Catálogo!$L$2:$L$648,"*sexo*",Catálogo!$L$2:$L$648,"*edad*",Catálogo!$Q$2:$Q$648,{1,2,3,4,5,6,7,8,9})>0,0),0)),"; "&LOWER(INDEX(Niveles!$C$2:$C$10,IFERROR(MATCH(TRUE,COUNTIFS(Catálogo!$J$2:$J$648,"*"&$A18&"*",Catálogo!$I$2:$I$648,"<>ausente",Catálogo!$M$2:$M$648,"parcial",Catálogo!$L$2:$L$648,"*sexo*",Catálogo!$L$2:$L$648,"*edad*",Catálogo!$Q$2:$Q$648,{1,2,3,4,5,6,7,8,9})>0,0),0)))&" (parcial)",""),IF(IFERROR(MATCH(TRUE,COUNTIFS(Catálogo!$J$2:$J$648,"*"&$A18&"*",Catálogo!$I$2:$I$648,"<>ausente",Catálogo!$M$2:$M$648,"parcial",Catálogo!$L$2:$L$648,"*sexo*",Catálogo!$L$2:$L$648,"*edad*",Catálogo!$Q$2:$Q$648,{1,2,3,4,5,6,7,8,9})>0,0),0)>0,INDEX(Niveles!$C$2:$C$10,IFERROR(MATCH(TRUE,COUNTIFS(Catálogo!$J$2:$J$648,"*"&$A18&"*",Catálogo!$I$2:$I$648,"<>ausente",Catálogo!$M$2:$M$648,"parcial",Catálogo!$L$2:$L$648,"*sexo*",Catálogo!$L$2:$L$648,"*edad*",Catálogo!$Q$2:$Q$648,{1,2,3,4,5,6,7,8,9})>0,0),0))&" (parcial)","—")) -> País; comuna (parcial) | U18: =SUMIFS(Cifras!$J$2:$J$399,Cifras!$A$2:$A$399,$A18) -> 0 | V18: Núcleo completo | W18: Opcional: 1.2.2 (comunas cabeceras de provincia por edad y sexo, PDF ~146). El volumen no trae sexo × edad por provincia ni datos por comuna para todo el país. | X18: Provincia × área × sexo (1.2), provincia × edad en 17 grupos (1.2.1) y país × área × sexo × edad simple, con meses bajo 1 año (1.3). Todas las sumas cuadran; los totales en negrita se fijaron con las sumas.
A19: 1970 | B19: pub_1970 | C19: 169 | D19: =COUNTIFS(Catálogo!$B$2:$B$648,$A19) -> 37 | E19: =COUNTIFS(Catálogo!$B$2:$B$648,$A19,Catálogo!$F$2:$F$648,"cuadro") -> 36 | F19: =COUNTIFS(Catálogo!$B$2:$B$648,$A19,Catálogo!$F$2:$F$648,"bloque") -> 0 | G19: =COUNTIFS(Catálogo!$B$2:$B$648,$A19,Catálogo!$F$2:$F$648,"texto") -> 1 | H19: =COUNTIFS(Catálogo!$B$2:$B$648,$A19,Catálogo!$I$2:$I$648,"verificada") -> 1 | I19: =COUNTIFS(Catálogo!$B$2:$B$648,$A19,Catálogo!$I$2:$I$648,"estimada") -> 35 | J19: =COUNTIFS(Catálogo!$B$2:$B$648,$A19,Catálogo!$I$2:$I$648,"desconocida")+COUNTIFS(Catálogo!$B$2:$B$648,$A19,Catálogo!$I$2:$I$648,"ausente") -> 1 | K19: =COUNTIFS(Catálogo!$B$2:$B$648,$A19,Catálogo!$O$2:$O$648,"transcrito") -> 2 | L19: =SUMIFS(Cifras!$H$2:$H$399,Cifras!$A$2:$A$399,$A19) -> 962 | M19: =IF(COUNTIFS(Cifras!$A$2:$A$399,$A19,Cifras!$D$2:$D$399,"distrito")>0,"Distrito",IF(COUNTIFS(Cifras!$A$2:$A$399,$A19,Cifras!$D$2:$D$399,"comuna")>0,"Comuna",IF(COUNTIFS(Cifras!$A$2:$A$399,$A19,Cifras!$D$2:$D$399,"partido")>0,"Partido",IF(COUNTIFS(Cifras!$A$2:$A$399,$A19,Cifras!$D$2:$D$399,"departamento")>0,"Departamento",IF(COUNTIFS(Cifras!$A$2:$A$399,$A19,Cifras!$D$2:$D$399,"provincia")>0,"Provincia",IF(COUNTIFS(Cifras!$A$2:$A$399,$A19,Cifras!$D$2:$D$399,"region")>0,"Región",IF(COUNTIFS(Cifras!$A$2:$A$399,$A19,Cifras!$D$2:$D$399,"pais")>0,"País","—"))))))) -> Provincia | N19: =IF(IFERROR(MATCH(TRUE,COUNTIFS(Catálogo!$J$2:$J$648,"*"&$A19&"*",Catálogo!$I$2:$I$648,"<>ausente",Catálogo!$M$2:$M$648,"completa",Catálogo!$Q$2:$Q$648,{1,2,3,4,5,6,7,8,9})>0,0),0)>0,INDEX(Niveles!$C$2:$C$10,IFERROR(MATCH(TRUE,COUNTIFS(Catálogo!$J$2:$J$648,"*"&$A19&"*",Catálogo!$I$2:$I$648,"<>ausente",Catálogo!$M$2:$M$648,"completa",Catálogo!$Q$2:$Q$648,{1,2,3,4,5,6,7,8,9})>0,0),0))&IF(AND(IFERROR(MATCH(TRUE,COUNTIFS(Catálogo!$J$2:$J$648,"*"&$A19&"*",Catálogo!$I$2:$I$648,"<>ausente",Catálogo!$M$2:$M$648,"parcial",Catálogo!$Q$2:$Q$648,{1,2,3,4,5,6,7,8,9})>0,0),0)>0,IFERROR(MATCH(TRUE,COUNTIFS(Catálogo!$J$2:$J$648,"*"&$A19&"*",Catálogo!$I$2:$I$648,"<>ausente",Catálogo!$M$2:$M$648,"parcial",Catálogo!$Q$2:$Q$648,{1,2,3,4,5,6,7,8,9})>0,0),0)<IFERROR(MATCH(TRUE,COUNTIFS(Catálogo!$J$2:$J$648,"*"&$A19&"*",Catálogo!$I$2:$I$648,"<>ausente",Catálogo!$M$2:$M$648,"completa",Catálogo!$Q$2:$Q$648,{1,2,3,4,5,6,7,8,9})>0,0),0)),"; "&LOWER(INDEX(Niveles!$C$2:$C$10,IFERROR(MATCH(TRUE,COUNTIFS(Catálogo!$J$2:$J$648,"*"&$A19&"*",Catálogo!$I$2:$I$648,"<>ausente",Catálogo!$M$2:$M$648,"parcial",Catálogo!$Q$2:$Q$648,{1,2,3,4,5,6,7,8,9})>0,0),0)))&" (parcial)",""),IF(IFERROR(MATCH(TRUE,COUNTIFS(Catálogo!$J$2:$J$648,"*"&$A19&"*",Catálogo!$I$2:$I$648,"<>ausente",Catálogo!$M$2:$M$648,"parcial",Catálogo!$Q$2:$Q$648,{1,2,3,4,5,6,7,8,9})>0,0),0)>0,INDEX(Niveles!$C$2:$C$10,IFERROR(MATCH(TRUE,COUNTIFS(Catálogo!$J$2:$J$648,"*"&$A19&"*",Catálogo!$I$2:$I$648,"<>ausente",Catálogo!$M$2:$M$648,"parcial",Catálogo!$Q$2:$Q$648,{1,2,3,4,5,6,7,8,9})>0,0),0))&" (parcial)","—")) -> Provincia | O19: =IF(COUNTIFS(Cifras!$A$2:$A$399,$A19,Cifras!$E$2:$E$399,"Sí",Cifras!$D$2:$D$399,"distrito")>0,"Distrito",IF(COUNTIFS(Cifras!$A$2:$A$399,$A19,Cifras!$E$2:$E$399,"Sí",Cifras!$D$2:$D$399,"comuna")>0,"Comuna",IF(COUNTIFS(Cifras!$A$2:$A$399,$A19,Cifras!$E$2:$E$399,"Sí",Cifras!$D$2:$D$399,"partido")>0,"Partido",IF(COUNTIFS(Cifras!$A$2:$A$399,$A19,Cifras!$E$2:$E$399,"Sí",Cifras!$D$2:$D$399,"departamento")>0,"Departamento",IF(COUNTIFS(Cifras!$A$2:$A$399,$A19,Cifras!$E$2:$E$399,"Sí",Cifras!$D$2:$D$399,"provincia")>0,"Provincia",IF(COUNTIFS(Cifras!$A$2:$A$399,$A19,Cifras!$E$2:$E$399,"Sí",Cifras!$D$2:$D$399,"region")>0,"Región",IF(COUNTIFS(Cifras!$A$2:$A$399,$A19,Cifras!$E$2:$E$399,"Sí",Cifras!$D$2:$D$399,"pais")>0,"País","—"))))))) -> País | P19: =IF(IFERROR(MATCH(TRUE,COUNTIFS(Catálogo!$J$2:$J$648,"*"&$A19&"*",Catálogo!$I$2:$I$648,"<>ausente",Catálogo!$M$2:$M$648,"completa",Catálogo!$L$2:$L$648,"*area*",Catálogo!$Q$2:$Q$648,{1,2,3,4,5,6,7,8,9})>0,0),0)>0,INDEX(Niveles!$C$2:$C$10,IFERROR(MATCH(TRUE,COUNTIFS(Catálogo!$J$2:$J$648,"*"&$A19&"*",Catálogo!$I$2:$I$648,"<>ausente",Catálogo!$M$2:$M$648,"completa",Catálogo!$L$2:$L$648,"*area*",Catálogo!$Q$2:$Q$648,{1,2,3,4,5,6,7,8,9})>0,0),0))&IF(AND(IFERROR(MATCH(TRUE,COUNTIFS(Catálogo!$J$2:$J$648,"*"&$A19&"*",Catálogo!$I$2:$I$648,"<>ausente",Catálogo!$M$2:$M$648,"parcial",Catálogo!$L$2:$L$648,"*area*",Catálogo!$Q$2:$Q$648,{1,2,3,4,5,6,7,8,9})>0,0),0)>0,IFERROR(MATCH(TRUE,COUNTIFS(Catálogo!$J$2:$J$648,"*"&$A19&"*",Catálogo!$I$2:$I$648,"<>ausente",Catálogo!$M$2:$M$648,"parcial",Catálogo!$L$2:$L$648,"*area*",Catálogo!$Q$2:$Q$648,{1,2,3,4,5,6,7,8,9})>0,0),0)<IFERROR(MATCH(TRUE,COUNTIFS(Catálogo!$J$2:$J$648,"*"&$A19&"*",Catálogo!$I$2:$I$648,"<>ausente",Catálogo!$M$2:$M$648,"completa",Catálogo!$L$2:$L$648,"*area*",Catálogo!$Q$2:$Q$648,{1,2,3,4,5,6,7,8,9})>0,0),0)),"; "&LOWER(INDEX(Niveles!$C$2:$C$10,IFERROR(MATCH(TRUE,COUNTIFS(Catálogo!$J$2:$J$648,"*"&$A19&"*",Catálogo!$I$2:$I$648,"<>ausente",Catálogo!$M$2:$M$648,"parcial",Catálogo!$L$2:$L$648,"*area*",Catálogo!$Q$2:$Q$648,{1,2,3,4,5,6,7,8,9})>0,0),0)))&" (parcial)",""),IF(IFERROR(MATCH(TRUE,COUNTIFS(Catálogo!$J$2:$J$648,"*"&$A19&"*",Catálogo!$I$2:$I$648,"<>ausente",Catálogo!$M$2:$M$648,"parcial",Catálogo!$L$2:$L$648,"*area*",Catálogo!$Q$2:$Q$648,{1,2,3,4,5,6,7,8,9})>0,0),0)>0,INDEX(Niveles!$C$2:$C$10,IFERROR(MATCH(TRUE,COUNTIFS(Catálogo!$J$2:$J$648,"*"&$A19&"*",Catálogo!$I$2:$I$648,"<>ausente",Catálogo!$M$2:$M$648,"parcial",Catálogo!$L$2:$L$648,"*area*",Catálogo!$Q$2:$Q$648,{1,2,3,4,5,6,7,8,9})>0,0),0))&" (parcial)","—")) -> País | Q19: =IF(COUNTIFS(Cifras!$A$2:$A$399,$A19,Cifras!$E$2:$E$399,"Sí",Cifras!$F$2:$F$399,"Sí",Cifras!$D$2:$D$399,"distrito")>0,"Distrito",IF(COUNTIFS(Cifras!$A$2:$A$399,$A19,Cifras!$E$2:$E$399,"Sí",Cifras!$F$2:$F$399,"Sí",Cifras!$D$2:$D$399,"comuna")>0,"Comuna",IF(COUNTIFS(Cifras!$A$2:$A$399,$A19,Cifras!$E$2:$E$399,"Sí",Cifras!$F$2:$F$399,"Sí",Cifras!$D$2:$D$399,"partido")>0,"Partido",IF(COUNTIFS(Cifras!$A$2:$A$399,$A19,Cifras!$E$2:$E$399,"Sí",Cifras!$F$2:$F$399,"Sí",Cifras!$D$2:$D$399,"departamento")>0,"Departamento",IF(COUNTIFS(Cifras!$A$2:$A$399,$A19,Cifras!$E$2:$E$399,"Sí",Cifras!$F$2:$F$399,"Sí",Cifras!$D$2:$D$399,"provincia")>0,"Provincia",IF(COUNTIFS(Cifras!$A$2:$A$399,$A19,Cifras!$E$2:$E$399,"Sí",Cifras!$F$2:$F$399,"Sí",Cifras!$D$2:$D$399,"region")>0,"Región",IF(COUNTIFS(Cifras!$A$2:$A$399,$A19,Cifras!$E$2:$E$399,"Sí",Cifras!$F$2:$F$399,"Sí",Cifras!$D$2:$D$399,"pais")>0,"País","—"))))))) -> País | R19: =IF(IFERROR(MATCH(TRUE,COUNTIFS(Catálogo!$J$2:$J$648,"*"&$A19&"*",Catálogo!$I$2:$I$648,"<>ausente",Catálogo!$M$2:$M$648,"completa",Catálogo!$L$2:$L$648,"*area*",Catálogo!$L$2:$L$648,"*sexo*",Catálogo!$Q$2:$Q$648,{1,2,3,4,5,6,7,8,9})>0,0),0)>0,INDEX(Niveles!$C$2:$C$10,IFERROR(MATCH(TRUE,COUNTIFS(Catálogo!$J$2:$J$648,"*"&$A19&"*",Catálogo!$I$2:$I$648,"<>ausente",Catálogo!$M$2:$M$648,"completa",Catálogo!$L$2:$L$648,"*area*",Catálogo!$L$2:$L$648,"*sexo*",Catálogo!$Q$2:$Q$648,{1,2,3,4,5,6,7,8,9})>0,0),0))&IF(AND(IFERROR(MATCH(TRUE,COUNTIFS(Catálogo!$J$2:$J$648,"*"&$A19&"*",Catálogo!$I$2:$I$648,"<>ausente",Catálogo!$M$2:$M$648,"parcial",Catálogo!$L$2:$L$648,"*area*",Catálogo!$L$2:$L$648,"*sexo*",Catálogo!$Q$2:$Q$648,{1,2,3,4,5,6,7,8,9})>0,0),0)>0,IFERROR(MATCH(TRUE,COUNTIFS(Catálogo!$J$2:$J$648,"*"&$A19&"*",Catálogo!$I$2:$I$648,"<>ausente",Catálogo!$M$2:$M$648,"parcial",Catálogo!$L$2:$L$648,"*area*",Catálogo!$L$2:$L$648,"*sexo*",Catálogo!$Q$2:$Q$648,{1,2,3,4,5,6,7,8,9})>0,0),0)<IFERROR(MATCH(TRUE,COUNTIFS(Catálogo!$J$2:$J$648,"*"&$A19&"*",Catálogo!$I$2:$I$648,"<>ausente",Catálogo!$M$2:$M$648,"completa",Catálogo!$L$2:$L$648,"*area*",Catálogo!$L$2:$L$648,"*sexo*",Catálogo!$Q$2:$Q$648,{1,2,3,4,5,6,7,8,9})>0,0),0)),"; "&LOWER(INDEX(Niveles!$C$2:$C$10,IFERROR(MATCH(TRUE,COUNTIFS(Catálogo!$J$2:$J$648,"*"&$A19&"*",Catálogo!$I$2:$I$648,"<>ausente",Catálogo!$M$2:$M$648,"parcial",Catálogo!$L$2:$L$648,"*area*",Catálogo!$L$2:$L$648,"*sexo*",Catálogo!$Q$2:$Q$648,{1,2,3,4,5,6,7,8,9})>0,0),0)))&" (parcial)",""),IF(IFERROR(MATCH(TRUE,COUNTIFS(Catálogo!$J$2:$J$648,"*"&$A19&"*",Catálogo!$I$2:$I$648,"<>ausente",Catálogo!$M$2:$M$648,"parcial",Catálogo!$L$2:$L$648,"*area*",Catálogo!$L$2:$L$648,"*sexo*",Catálogo!$Q$2:$Q$648,{1,2,3,4,5,6,7,8,9})>0,0),0)>0,INDEX(Niveles!$C$2:$C$10,IFERROR(MATCH(TRUE,COUNTIFS(Catálogo!$J$2:$J$648,"*"&$A19&"*",Catálogo!$I$2:$I$648,"<>ausente",Catálogo!$M$2:$M$648,"parcial",Catálogo!$L$2:$L$648,"*area*",Catálogo!$L$2:$L$648,"*sexo*",Catálogo!$Q$2:$Q$648,{1,2,3,4,5,6,7,8,9})>0,0),0))&" (parcial)","—")) -> País | S19: =IF(COUNTIFS(Cifras!$A$2:$A$399,$A19,Cifras!$F$2:$F$399,"Sí",Cifras!$G$2:$G$399,"Sí",Cifras!$D$2:$D$399,"distrito")>0,"Distrito",IF(COUNTIFS(Cifras!$A$2:$A$399,$A19,Cifras!$F$2:$F$399,"Sí",Cifras!$G$2:$G$399,"Sí",Cifras!$D$2:$D$399,"comuna")>0,"Comuna",IF(COUNTIFS(Cifras!$A$2:$A$399,$A19,Cifras!$F$2:$F$399,"Sí",Cifras!$G$2:$G$399,"Sí",Cifras!$D$2:$D$399,"partido")>0,"Partido",IF(COUNTIFS(Cifras!$A$2:$A$399,$A19,Cifras!$F$2:$F$399,"Sí",Cifras!$G$2:$G$399,"Sí",Cifras!$D$2:$D$399,"departamento")>0,"Departamento",IF(COUNTIFS(Cifras!$A$2:$A$399,$A19,Cifras!$F$2:$F$399,"Sí",Cifras!$G$2:$G$399,"Sí",Cifras!$D$2:$D$399,"provincia")>0,"Provincia",IF(COUNTIFS(Cifras!$A$2:$A$399,$A19,Cifras!$F$2:$F$399,"Sí",Cifras!$G$2:$G$399,"Sí",Cifras!$D$2:$D$399,"region")>0,"Región",IF(COUNTIFS(Cifras!$A$2:$A$399,$A19,Cifras!$F$2:$F$399,"Sí",Cifras!$G$2:$G$399,"Sí",Cifras!$D$2:$D$399,"pais")>0,"País","—"))))))) -> País | T19: =IF(IFERROR(MATCH(TRUE,COUNTIFS(Catálogo!$J$2:$J$648,"*"&$A19&"*",Catálogo!$I$2:$I$648,"<>ausente",Catálogo!$M$2:$M$648,"completa",Catálogo!$L$2:$L$648,"*sexo*",Catálogo!$L$2:$L$648,"*edad*",Catálogo!$Q$2:$Q$648,{1,2,3,4,5,6,7,8,9})>0,0),0)>0,INDEX(Niveles!$C$2:$C$10,IFERROR(MATCH(TRUE,COUNTIFS(Catálogo!$J$2:$J$648,"*"&$A19&"*",Catálogo!$I$2:$I$648,"<>ausente",Catálogo!$M$2:$M$648,"completa",Catálogo!$L$2:$L$648,"*sexo*",Catálogo!$L$2:$L$648,"*edad*",Catálogo!$Q$2:$Q$648,{1,2,3,4,5,6,7,8,9})>0,0),0))&IF(AND(IFERROR(MATCH(TRUE,COUNTIFS(Catálogo!$J$2:$J$648,"*"&$A19&"*",Catálogo!$I$2:$I$648,"<>ausente",Catálogo!$M$2:$M$648,"parcial",Catálogo!$L$2:$L$648,"*sexo*",Catálogo!$L$2:$L$648,"*edad*",Catálogo!$Q$2:$Q$648,{1,2,3,4,5,6,7,8,9})>0,0),0)>0,IFERROR(MATCH(TRUE,COUNTIFS(Catálogo!$J$2:$J$648,"*"&$A19&"*",Catálogo!$I$2:$I$648,"<>ausente",Catálogo!$M$2:$M$648,"parcial",Catálogo!$L$2:$L$648,"*sexo*",Catálogo!$L$2:$L$648,"*edad*",Catálogo!$Q$2:$Q$648,{1,2,3,4,5,6,7,8,9})>0,0),0)<IFERROR(MATCH(TRUE,COUNTIFS(Catálogo!$J$2:$J$648,"*"&$A19&"*",Catálogo!$I$2:$I$648,"<>ausente",Catálogo!$M$2:$M$648,"completa",Catálogo!$L$2:$L$648,"*sexo*",Catálogo!$L$2:$L$648,"*edad*",Catálogo!$Q$2:$Q$648,{1,2,3,4,5,6,7,8,9})>0,0),0)),"; "&LOWER(INDEX(Niveles!$C$2:$C$10,IFERROR(MATCH(TRUE,COUNTIFS(Catálogo!$J$2:$J$648,"*"&$A19&"*",Catálogo!$I$2:$I$648,"<>ausente",Catálogo!$M$2:$M$648,"parcial",Catálogo!$L$2:$L$648,"*sexo*",Catálogo!$L$2:$L$648,"*edad*",Catálogo!$Q$2:$Q$648,{1,2,3,4,5,6,7,8,9})>0,0),0)))&" (parcial)",""),IF(IFERROR(MATCH(TRUE,COUNTIFS(Catálogo!$J$2:$J$648,"*"&$A19&"*",Catálogo!$I$2:$I$648,"<>ausente",Catálogo!$M$2:$M$648,"parcial",Catálogo!$L$2:$L$648,"*sexo*",Catálogo!$L$2:$L$648,"*edad*",Catálogo!$Q$2:$Q$648,{1,2,3,4,5,6,7,8,9})>0,0),0)>0,INDEX(Niveles!$C$2:$C$10,IFERROR(MATCH(TRUE,COUNTIFS(Catálogo!$J$2:$J$648,"*"&$A19&"*",Catálogo!$I$2:$I$648,"<>ausente",Catálogo!$M$2:$M$648,"parcial",Catálogo!$L$2:$L$648,"*sexo*",Catálogo!$L$2:$L$648,"*edad*",Catálogo!$Q$2:$Q$648,{1,2,3,4,5,6,7,8,9})>0,0),0))&" (parcial)","—")) -> País | U19: =SUMIFS(Cifras!$J$2:$J$399,Cifras!$A$2:$A$399,$A19) -> 0 | V19: Núcleo completo | W19: Nada más en el volumen «Total País». Buscar los volúmenes provinciales de 1970 (área, sexo y edad por provincia y comuna). | X19: País × área × sexo × edad simple (Cuadro 3, 936 cifras, todas cuadran) y población total por provincia (Cuadro 5). El volumen disponible no trae área, sexo ni edad por provincia.
A20: 1982 | B20: pub_1982_v1, pub_1982_v2, pub_1982_v3 | C20: 1034 | D20: =COUNTIFS(Catálogo!$B$2:$B$648,$A20) -> 76 | E20: =COUNTIFS(Catálogo!$B$2:$B$648,$A20,Catálogo!$F$2:$F$648,"cuadro") -> 68 | F20: =COUNTIFS(Catálogo!$B$2:$B$648,$A20,Catálogo!$F$2:$F$648,"bloque") -> 0 | G20: =COUNTIFS(Catálogo!$B$2:$B$648,$A20,Catálogo!$F$2:$F$648,"texto") -> 8 | H20: =COUNTIFS(Catálogo!$B$2:$B$648,$A20,Catálogo!$I$2:$I$648,"verificada") -> 6 | I20: =COUNTIFS(Catálogo!$B$2:$B$648,$A20,Catálogo!$I$2:$I$648,"estimada") -> 62 | J20: =COUNTIFS(Catálogo!$B$2:$B$648,$A20,Catálogo!$I$2:$I$648,"desconocida")+COUNTIFS(Catálogo!$B$2:$B$648,$A20,Catálogo!$I$2:$I$648,"ausente") -> 8 | K20: =COUNTIFS(Catálogo!$B$2:$B$648,$A20,Catálogo!$O$2:$O$648,"transcrito") -> 2 | L20: =SUMIFS(Cifras!$H$2:$H$399,Cifras!$A$2:$A$399,$A20) -> 4587 | M20: =IF(COUNTIFS(Cifras!$A$2:$A$399,$A20,Cifras!$D$2:$D$399,"distrito")>0,"Distrito",IF(COUNTIFS(Cifras!$A$2:$A$399,$A20,Cifras!$D$2:$D$399,"comuna")>0,"Comuna",IF(COUNTIFS(Cifras!$A$2:$A$399,$A20,Cifras!$D$2:$D$399,"partido")>0,"Partido",IF(COUNTIFS(Cifras!$A$2:$A$399,$A20,Cifras!$D$2:$D$399,"departamento")>0,"Departamento",IF(COUNTIFS(Cifras!$A$2:$A$399,$A20,Cifras!$D$2:$D$399,"provincia")>0,"Provincia",IF(COUNTIFS(Cifras!$A$2:$A$399,$A20,Cifras!$D$2:$D$399,"region")>0,"Región",IF(COUNTIFS(Cifras!$A$2:$A$399,$A20,Cifras!$D$2:$D$399,"pais")>0,"País","—"))))))) -> Comuna | N20: =IF(IFERROR(MATCH(TRUE,COUNTIFS(Catálogo!$J$2:$J$648,"*"&$A20&"*",Catálogo!$I$2:$I$648,"<>ausente",Catálogo!$M$2:$M$648,"completa",Catálogo!$Q$2:$Q$648,{1,2,3,4,5,6,7,8,9})>0,0),0)>0,INDEX(Niveles!$C$2:$C$10,IFERROR(MATCH(TRUE,COUNTIFS(Catálogo!$J$2:$J$648,"*"&$A20&"*",Catálogo!$I$2:$I$648,"<>ausente",Catálogo!$M$2:$M$648,"completa",Catálogo!$Q$2:$Q$648,{1,2,3,4,5,6,7,8,9})>0,0),0))&IF(AND(IFERROR(MATCH(TRUE,COUNTIFS(Catálogo!$J$2:$J$648,"*"&$A20&"*",Catálogo!$I$2:$I$648,"<>ausente",Catálogo!$M$2:$M$648,"parcial",Catálogo!$Q$2:$Q$648,{1,2,3,4,5,6,7,8,9})>0,0),0)>0,IFERROR(MATCH(TRUE,COUNTIFS(Catálogo!$J$2:$J$648,"*"&$A20&"*",Catálogo!$I$2:$I$648,"<>ausente",Catálogo!$M$2:$M$648,"parcial",Catálogo!$Q$2:$Q$648,{1,2,3,4,5,6,7,8,9})>0,0),0)<IFERROR(MATCH(TRUE,COUNTIFS(Catálogo!$J$2:$J$648,"*"&$A20&"*",Catálogo!$I$2:$I$648,"<>ausente",Catálogo!$M$2:$M$648,"completa",Catálogo!$Q$2:$Q$648,{1,2,3,4,5,6,7,8,9})>0,0),0)),"; "&LOWER(INDEX(Niveles!$C$2:$C$10,IFERROR(MATCH(TRUE,COUNTIFS(Catálogo!$J$2:$J$648,"*"&$A20&"*",Catálogo!$I$2:$I$648,"<>ausente",Catálogo!$M$2:$M$648,"parcial",Catálogo!$Q$2:$Q$648,{1,2,3,4,5,6,7,8,9})>0,0),0)))&" (parcial)",""),IF(IFERROR(MATCH(TRUE,COUNTIFS(Catálogo!$J$2:$J$648,"*"&$A20&"*",Catálogo!$I$2:$I$648,"<>ausente",Catálogo!$M$2:$M$648,"parcial",Catálogo!$Q$2:$Q$648,{1,2,3,4,5,6,7,8,9})>0,0),0)>0,INDEX(Niveles!$C$2:$C$10,IFERROR(MATCH(TRUE,COUNTIFS(Catálogo!$J$2:$J$648,"*"&$A20&"*",Catálogo!$I$2:$I$648,"<>ausente",Catálogo!$M$2:$M$648,"parcial",Catálogo!$Q$2:$Q$648,{1,2,3,4,5,6,7,8,9})>0,0),0))&" (parcial)","—")) -> Comuna | O20: =IF(COUNTIFS(Cifras!$A$2:$A$399,$A20,Cifras!$E$2:$E$399,"Sí",Cifras!$D$2:$D$399,"distrito")>0,"Distrito",IF(COUNTIFS(Cifras!$A$2:$A$399,$A20,Cifras!$E$2:$E$399,"Sí",Cifras!$D$2:$D$399,"comuna")>0,"Comuna",IF(COUNTIFS(Cifras!$A$2:$A$399,$A20,Cifras!$E$2:$E$399,"Sí",Cifras!$D$2:$D$399,"partido")>0,"Partido",IF(COUNTIFS(Cifras!$A$2:$A$399,$A20,Cifras!$E$2:$E$399,"Sí",Cifras!$D$2:$D$399,"departamento")>0,"Departamento",IF(COUNTIFS(Cifras!$A$2:$A$399,$A20,Cifras!$E$2:$E$399,"Sí",Cifras!$D$2:$D$399,"provincia")>0,"Provincia",IF(COUNTIFS(Cifras!$A$2:$A$399,$A20,Cifras!$E$2:$E$399,"Sí",Cifras!$D$2:$D$399,"region")>0,"Región",IF(COUNTIFS(Cifras!$A$2:$A$399,$A20,Cifras!$E$2:$E$399,"Sí",Cifras!$D$2:$D$399,"pais")>0,"País","—"))))))) -> Comuna | P20: =IF(IFERROR(MATCH(TRUE,COUNTIFS(Catálogo!$J$2:$J$648,"*"&$A20&"*",Catálogo!$I$2:$I$648,"<>ausente",Catálogo!$M$2:$M$648,"completa",Catálogo!$L$2:$L$648,"*area*",Catálogo!$Q$2:$Q$648,{1,2,3,4,5,6,7,8,9})>0,0),0)>0,INDEX(Niveles!$C$2:$C$10,IFERROR(MATCH(TRUE,COUNTIFS(Catálogo!$J$2:$J$648,"*"&$A20&"*",Catálogo!$I$2:$I$648,"<>ausente",Catálogo!$M$2:$M$648,"completa",Catálogo!$L$2:$L$648,"*area*",Catálogo!$Q$2:$Q$648,{1,2,3,4,5,6,7,8,9})>0,0),0))&IF(AND(IFERROR(MATCH(TRUE,COUNTIFS(Catálogo!$J$2:$J$648,"*"&$A20&"*",Catálogo!$I$2:$I$648,"<>ausente",Catálogo!$M$2:$M$648,"parcial",Catálogo!$L$2:$L$648,"*area*",Catálogo!$Q$2:$Q$648,{1,2,3,4,5,6,7,8,9})>0,0),0)>0,IFERROR(MATCH(TRUE,COUNTIFS(Catálogo!$J$2:$J$648,"*"&$A20&"*",Catálogo!$I$2:$I$648,"<>ausente",Catálogo!$M$2:$M$648,"parcial",Catálogo!$L$2:$L$648,"*area*",Catálogo!$Q$2:$Q$648,{1,2,3,4,5,6,7,8,9})>0,0),0)<IFERROR(MATCH(TRUE,COUNTIFS(Catálogo!$J$2:$J$648,"*"&$A20&"*",Catálogo!$I$2:$I$648,"<>ausente",Catálogo!$M$2:$M$648,"completa",Catálogo!$L$2:$L$648,"*area*",Catálogo!$Q$2:$Q$648,{1,2,3,4,5,6,7,8,9})>0,0),0)),"; "&LOWER(INDEX(Niveles!$C$2:$C$10,IFERROR(MATCH(TRUE,COUNTIFS(Catálogo!$J$2:$J$648,"*"&$A20&"*",Catálogo!$I$2:$I$648,"<>ausente",Catálogo!$M$2:$M$648,"parcial",Catálogo!$L$2:$L$648,"*area*",Catálogo!$Q$2:$Q$648,{1,2,3,4,5,6,7,8,9})>0,0),0)))&" (parcial)",""),IF(IFERROR(MATCH(TRUE,COUNTIFS(Catálogo!$J$2:$J$648,"*"&$A20&"*",Catálogo!$I$2:$I$648,"<>ausente",Catálogo!$M$2:$M$648,"parcial",Catálogo!$L$2:$L$648,"*area*",Catálogo!$Q$2:$Q$648,{1,2,3,4,5,6,7,8,9})>0,0),0)>0,INDEX(Niveles!$C$2:$C$10,IFERROR(MATCH(TRUE,COUNTIFS(Catálogo!$J$2:$J$648,"*"&$A20&"*",Catálogo!$I$2:$I$648,"<>ausente",Catálogo!$M$2:$M$648,"parcial",Catálogo!$L$2:$L$648,"*area*",Catálogo!$Q$2:$Q$648,{1,2,3,4,5,6,7,8,9})>0,0),0))&" (parcial)","—")) -> Comuna | Q20: =IF(COUNTIFS(Cifras!$A$2:$A$399,$A20,Cifras!$E$2:$E$399,"Sí",Cifras!$F$2:$F$399,"Sí",Cifras!$D$2:$D$399,"distrito")>0,"Distrito",IF(COUNTIFS(Cifras!$A$2:$A$399,$A20,Cifras!$E$2:$E$399,"Sí",Cifras!$F$2:$F$399,"Sí",Cifras!$D$2:$D$399,"comuna")>0,"Comuna",IF(COUNTIFS(Cifras!$A$2:$A$399,$A20,Cifras!$E$2:$E$399,"Sí",Cifras!$F$2:$F$399,"Sí",Cifras!$D$2:$D$399,"partido")>0,"Partido",IF(COUNTIFS(Cifras!$A$2:$A$399,$A20,Cifras!$E$2:$E$399,"Sí",Cifras!$F$2:$F$399,"Sí",Cifras!$D$2:$D$399,"departamento")>0,"Departamento",IF(COUNTIFS(Cifras!$A$2:$A$399,$A20,Cifras!$E$2:$E$399,"Sí",Cifras!$F$2:$F$399,"Sí",Cifras!$D$2:$D$399,"provincia")>0,"Provincia",IF(COUNTIFS(Cifras!$A$2:$A$399,$A20,Cifras!$E$2:$E$399,"Sí",Cifras!$F$2:$F$399,"Sí",Cifras!$D$2:$D$399,"region")>0,"Región",IF(COUNTIFS(Cifras!$A$2:$A$399,$A20,Cifras!$E$2:$E$399,"Sí",Cifras!$F$2:$F$399,"Sí",Cifras!$D$2:$D$399,"pais")>0,"País","—"))))))) -> Comuna | R20: =IF(IFERROR(MATCH(TRUE,COUNTIFS(Catálogo!$J$2:$J$648,"*"&$A20&"*",Catálogo!$I$2:$I$648,"<>ausente",Catálogo!$M$2:$M$648,"completa",Catálogo!$L$2:$L$648,"*area*",Catálogo!$L$2:$L$648,"*sexo*",Catálogo!$Q$2:$Q$648,{1,2,3,4,5,6,7,8,9})>0,0),0)>0,INDEX(Niveles!$C$2:$C$10,IFERROR(MATCH(TRUE,COUNTIFS(Catálogo!$J$2:$J$648,"*"&$A20&"*",Catálogo!$I$2:$I$648,"<>ausente",Catálogo!$M$2:$M$648,"completa",Catálogo!$L$2:$L$648,"*area*",Catálogo!$L$2:$L$648,"*sexo*",Catálogo!$Q$2:$Q$648,{1,2,3,4,5,6,7,8,9})>0,0),0))&IF(AND(IFERROR(MATCH(TRUE,COUNTIFS(Catálogo!$J$2:$J$648,"*"&$A20&"*",Catálogo!$I$2:$I$648,"<>ausente",Catálogo!$M$2:$M$648,"parcial",Catálogo!$L$2:$L$648,"*area*",Catálogo!$L$2:$L$648,"*sexo*",Catálogo!$Q$2:$Q$648,{1,2,3,4,5,6,7,8,9})>0,0),0)>0,IFERROR(MATCH(TRUE,COUNTIFS(Catálogo!$J$2:$J$648,"*"&$A20&"*",Catálogo!$I$2:$I$648,"<>ausente",Catálogo!$M$2:$M$648,"parcial",Catálogo!$L$2:$L$648,"*area*",Catálogo!$L$2:$L$648,"*sexo*",Catálogo!$Q$2:$Q$648,{1,2,3,4,5,6,7,8,9})>0,0),0)<IFERROR(MATCH(TRUE,COUNTIFS(Catálogo!$J$2:$J$648,"*"&$A20&"*",Catálogo!$I$2:$I$648,"<>ausente",Catálogo!$M$2:$M$648,"completa",Catálogo!$L$2:$L$648,"*area*",Catálogo!$L$2:$L$648,"*sexo*",Catálogo!$Q$2:$Q$648,{1,2,3,4,5,6,7,8,9})>0,0),0)),"; "&LOWER(INDEX(Niveles!$C$2:$C$10,IFERROR(MATCH(TRUE,COUNTIFS(Catálogo!$J$2:$J$648,"*"&$A20&"*",Catálogo!$I$2:$I$648,"<>ausente",Catálogo!$M$2:$M$648,"parcial",Catálogo!$L$2:$L$648,"*area*",Catálogo!$L$2:$L$648,"*sexo*",Catálogo!$Q$2:$Q$648,{1,2,3,4,5,6,7,8,9})>0,0),0)))&" (parcial)",""),IF(IFERROR(MATCH(TRUE,COUNTIFS(Catálogo!$J$2:$J$648,"*"&$A20&"*",Catálogo!$I$2:$I$648,"<>ausente",Catálogo!$M$2:$M$648,"parcial",Catálogo!$L$2:$L$648,"*area*",Catálogo!$L$2:$L$648,"*sexo*",Catálogo!$Q$2:$Q$648,{1,2,3,4,5,6,7,8,9})>0,0),0)>0,INDEX(Niveles!$C$2:$C$10,IFERROR(MATCH(TRUE,COUNTIFS(Catálogo!$J$2:$J$648,"*"&$A20&"*",Catálogo!$I$2:$I$648,"<>ausente",Catálogo!$M$2:$M$648,"parcial",Catálogo!$L$2:$L$648,"*area*",Catálogo!$L$2:$L$648,"*sexo*",Catálogo!$Q$2:$Q$648,{1,2,3,4,5,6,7,8,9})>0,0),0))&" (parcial)","—")) -> Comuna | S20: =IF(COUNTIFS(Cifras!$A$2:$A$399,$A20,Cifras!$F$2:$F$399,"Sí",Cifras!$G$2:$G$399,"Sí",Cifras!$D$2:$D$399,"distrito")>0,"Distrito",IF(COUNTIFS(Cifras!$A$2:$A$399,$A20,Cifras!$F$2:$F$399,"Sí",Cifras!$G$2:$G$399,"Sí",Cifras!$D$2:$D$399,"comuna")>0,"Comuna",IF(COUNTIFS(Cifras!$A$2:$A$399,$A20,Cifras!$F$2:$F$399,"Sí",Cifras!$G$2:$G$399,"Sí",Cifras!$D$2:$D$399,"partido")>0,"Partido",IF(COUNTIFS(Cifras!$A$2:$A$399,$A20,Cifras!$F$2:$F$399,"Sí",Cifras!$G$2:$G$399,"Sí",Cifras!$D$2:$D$399,"departamento")>0,"Departamento",IF(COUNTIFS(Cifras!$A$2:$A$399,$A20,Cifras!$F$2:$F$399,"Sí",Cifras!$G$2:$G$399,"Sí",Cifras!$D$2:$D$399,"provincia")>0,"Provincia",IF(COUNTIFS(Cifras!$A$2:$A$399,$A20,Cifras!$F$2:$F$399,"Sí",Cifras!$G$2:$G$399,"Sí",Cifras!$D$2:$D$399,"region")>0,"Región",IF(COUNTIFS(Cifras!$A$2:$A$399,$A20,Cifras!$F$2:$F$399,"Sí",Cifras!$G$2:$G$399,"Sí",Cifras!$D$2:$D$399,"pais")>0,"País","—"))))))) -> País | T20: =IF(IFERROR(MATCH(TRUE,COUNTIFS(Catálogo!$J$2:$J$648,"*"&$A20&"*",Catálogo!$I$2:$I$648,"<>ausente",Catálogo!$M$2:$M$648,"completa",Catálogo!$L$2:$L$648,"*sexo*",Catálogo!$L$2:$L$648,"*edad*",Catálogo!$Q$2:$Q$648,{1,2,3,4,5,6,7,8,9})>0,0),0)>0,INDEX(Niveles!$C$2:$C$10,IFERROR(MATCH(TRUE,COUNTIFS(Catálogo!$J$2:$J$648,"*"&$A20&"*",Catálogo!$I$2:$I$648,"<>ausente",Catálogo!$M$2:$M$648,"completa",Catálogo!$L$2:$L$648,"*sexo*",Catálogo!$L$2:$L$648,"*edad*",Catálogo!$Q$2:$Q$648,{1,2,3,4,5,6,7,8,9})>0,0),0))&IF(AND(IFERROR(MATCH(TRUE,COUNTIFS(Catálogo!$J$2:$J$648,"*"&$A20&"*",Catálogo!$I$2:$I$648,"<>ausente",Catálogo!$M$2:$M$648,"parcial",Catálogo!$L$2:$L$648,"*sexo*",Catálogo!$L$2:$L$648,"*edad*",Catálogo!$Q$2:$Q$648,{1,2,3,4,5,6,7,8,9})>0,0),0)>0,IFERROR(MATCH(TRUE,COUNTIFS(Catálogo!$J$2:$J$648,"*"&$A20&"*",Catálogo!$I$2:$I$648,"<>ausente",Catálogo!$M$2:$M$648,"parcial",Catálogo!$L$2:$L$648,"*sexo*",Catálogo!$L$2:$L$648,"*edad*",Catálogo!$Q$2:$Q$648,{1,2,3,4,5,6,7,8,9})>0,0),0)<IFERROR(MATCH(TRUE,COUNTIFS(Catálogo!$J$2:$J$648,"*"&$A20&"*",Catálogo!$I$2:$I$648,"<>ausente",Catálogo!$M$2:$M$648,"completa",Catálogo!$L$2:$L$648,"*sexo*",Catálogo!$L$2:$L$648,"*edad*",Catálogo!$Q$2:$Q$648,{1,2,3,4,5,6,7,8,9})>0,0),0)),"; "&LOWER(INDEX(Niveles!$C$2:$C$10,IFERROR(MATCH(TRUE,COUNTIFS(Catálogo!$J$2:$J$648,"*"&$A20&"*",Catálogo!$I$2:$I$648,"<>ausente",Catálogo!$M$2:$M$648,"parcial",Catálogo!$L$2:$L$648,"*sexo*",Catálogo!$L$2:$L$648,"*edad*",Catálogo!$Q$2:$Q$648,{1,2,3,4,5,6,7,8,9})>0,0),0)))&" (parcial)",""),IF(IFERROR(MATCH(TRUE,COUNTIFS(Catálogo!$J$2:$J$648,"*"&$A20&"*",Catálogo!$I$2:$I$648,"<>ausente",Catálogo!$M$2:$M$648,"parcial",Catálogo!$L$2:$L$648,"*sexo*",Catálogo!$L$2:$L$648,"*edad*",Catálogo!$Q$2:$Q$648,{1,2,3,4,5,6,7,8,9})>0,0),0)>0,INDEX(Niveles!$C$2:$C$10,IFERROR(MATCH(TRUE,COUNTIFS(Catálogo!$J$2:$J$648,"*"&$A20&"*",Catálogo!$I$2:$I$648,"<>ausente",Catálogo!$M$2:$M$648,"parcial",Catálogo!$L$2:$L$648,"*sexo*",Catálogo!$L$2:$L$648,"*edad*",Catálogo!$Q$2:$Q$648,{1,2,3,4,5,6,7,8,9})>0,0),0))&" (parcial)","—")) -> País | U20: =SUMIFS(Cifras!$J$2:$J$399,Cifras!$A$2:$A$399,$A20) -> 0 | V20: Núcleo completo | W20: Nada más para el núcleo en los volúmenes publicados (la edad solo viene para el país). Tomos II y III: ocupación, educación, vivienda, hogar y familia (módulos temáticos). | X20: Región, provincia y comuna × área × sexo (Cuadro 1.01); país × área × sexo × edad simple (Cuadro 1.03, 1.089 cifras, todas las sumas cuadran). Los volúmenes no traen edad bajo el nivel país.
A21: Total | C21: =SUM(C5:C20) -> 12342 | D21: =SUM(D5:D20) -> 638 | E21: =SUM(E5:E20) -> 427 | F21: =SUM(F5:F20) -> 133 | G21: =SUM(G5:G20) -> 78 | H21: =SUM(H5:H20) -> 224 | I21: =SUM(I5:I20) -> 393 | J21: =SUM(J5:J20) -> 21 | ... L21: =SUM(L5:L20) -> 54465 | U21: =SUM(U5:U20) -> 132
A22: Las cifras se cuentan por el censo al que se refieren, aunque vengan de la publicación de otro censo: p. ej., 1865 tiene cifras de 1920 C1 y 1952 C9 sin tener cuadros transcritos de su propia publicación. El catálogo de 1992 (9 entradas) no se incluye.
A23: «Transcrito»: nivel más fino ya digitalizado. «En los PDF»: nivel más fino que traen las publicaciones según el catálogo (incluidos los cuadros comparativos de censos posteriores); «(parcial)» = solo para parte del país; si para parte del país hay un nivel más fino que para el país completo, se muestran ambos.
A24: Estados
A25: Núcleo completo | D25: Población por territorio × área × sexo × edad transcrita al nivel más fino que traen los PDF.
A26: Falta edad | D26: Población por territorio × área × sexo transcrita; falta la edad.
A27: Parcial | D27: Hay cifras por territorio y área, pero falta sexo (salvo para el país) o falta bajar de provincia.
A28: Serie desde otros censos | D28: Cifras tomadas de cuadros comparativos de censos posteriores; la publicación propia aún no se transcribe.
A29: Catalogado | D29: Cuadros catalogados; sin cifras transcritas.
A30: Sin publicación | D30: No hay publicación digitalizada.

Sheet Cifras
A1: Censo | B1: Publicación | C1: Cuadro | D1: Nivel territorial | E1: Con área | F1: Con sexo | G1: Con edad | H1: Cifras | I1: Con valor | J1: Inconsistentes
A2: 1813 | B2: pub_1813 | C2: censo_provincia | D2: partido | E2: No | F2: No | G2: No | H2: 14 | I2: 14 | J2: 0
A3: 1813 | B3: pub_1813 | C3: censo_provincia | D3: partido | E3: No | F3: Sí | G3: No | H3: 112 | I3: 112 | J3: 0
A4: 1813 | B4: pub_1813 | C4: censo_provincia | D4: partido | E4: No | F4: Sí | G4: Sí | H4: 140 | I4: 140 | J4: 0
A5: 1813 | B5: pub_1813 | C5: censo_provincia_distritos | D5: distrito | E5: No | F5: Sí | G5: No | H5: 302 | I5: 302 | J5: 0
A6: 1813 | B6: pub_1813 | C6: censo_provincia_distritos | D6: partido | E6: No | F6: Sí | G6: No | H6: 28 | I6: 28 | J6: 0
A7: 1835 | B7: pub_1835 | C7: art34_42 | D7: departamento | E7: No | F7: No | G7: No | H7: 50 | I7: 50 | J7: 1
A8: 1835 | B8: pub_1835 | C8: art34_42 | D8: departamento | E8: No | F8: Sí | G8: No | H8: 200 | I8: 196 | J8: 0
A9: 1835 | B9: pub_1835 | C9: art34_42 | D9: provincia | E9: No | F9: No | G9: No | H9: 9 | I9: 9 | J9: 1
A10: 1835 | B10: pub_1835 | C10: art34_42 | D10: provincia | E10: No | F10: Sí | G10: No | H10: 36 | I10: 0 | J10: 0
A11: 1835 | B11: pub_1865 | C11: p392 | D11: departamento | E11: No | F11: No | G11: No | H11: 53 | I11: 44 | J11: 0
A12: 1835 | B12: pub_1865 | C12: p392 | D12: pais | E12: No | F12: No | G12: No | H12: 2 | I12: 2 | J12: 0
A13: 1835 | B13: pub_1865 | C13: p392 | D13: provincia | E13: No | F13: No | G13: No | H13: 9 | I13: 9 | J13: 0
... A399: 1982 | B399: pub_1982_v1 | C399: 1.03 | D399: pais | E399: Sí | F399: Sí | G399: Sí | H399: 480 | I399: 480 | J399: 0

Sheet Catálogo
A1: fuente_id | B1: censo | C1: seccion | D1: cuadro | E1: titulo | F1: tipo | G1: pagina_impresa | H1: pagina_pdf | I1: pagina_pdf_estado | J1: censos_datos | K1: nivel_territorial | L1: variables | M1: cobertura | N1: desagregacion_fuente | O1: estado | P1: nota | Q1: nivel_orden
A2: pub_1813 | B2: 1813 | C2: Preliminares | E2: Introducción (empadronamientos coloniales y antecedentes del censo de 1813) | F2: texto | H2: 4 | I2: verificada | O2: pendiente | P2: Págs. romanas, PDF 4-17 aprox. | Q2: =IFERROR(MATCH(K2,Niveles!$B$2:$B$10,0),"")
A3: pub_1813 | B3: 1813 | C3: Preliminares | E3: Documentos del censo (instrucciones de la Junta de Gobierno y oficios) | F3: texto | H3: 18 | I3: verificada | O3: pendiente | P3: Págs. 1-16 aprox., PDF 18-32. | Q3: =IFERROR(MATCH(K3,Niveles!$B$2:$B$10,0),"")
A4: pub_1813 | B4: 1813 | C4: Partido de Copiapó | E4: Partido de Copiapó: censo de territorio por distrito | F4: bloque | H4: 33 | I4: verificada | J4: 1813 | K4: distrito | L4: sexo+edad | M4: parcial | N4: verificada | O4: pendiente | P4: PDF 33-61. Cuadros 'Censo de territorio' por distrito (casados, solteros y viudos por sexo, total de hombres, mujeres y almas; edades; clases). | Q4: =IFERROR(MATCH(K4,Niveles!$B$2:$B$10,0),"") -> 2
A5: pub_1813 | B5: 1813 | C5: Partido de Copiapó | E5: Partido de Copiapó: censo de provincia, total de su población (estado civil por sexo y edades del total) | F5: cuadro | H5: 62 | I5: verificada | J5: 1813 | K5: departamento | L5: sexo+edad | M5: parcial | N5: verificada | O5: transcrito | P5: Transcrito en digitalizacion/1813/pub_1813_provincias.csv (edad × sexo, estado civil, totales) y pub_1813_distritos.csv (distritos × sexo). | Q5: =IFERROR(MATCH(K5,Niveles!$B$2:$B$10,0),"") -> 6
A6: pub_1813 | B6: 1813 | C6: Villa de Huasco | E6: Villa de Huasco: censo de territorio por distrito | F6: bloque | H6: 63 | I6: verificada | J6: 1813 | K6: distrito | L6: sexo+edad | M6: parcial | N6: verificada | O6: pendiente | P6: PDF 63-63. Cuadros 'Censo de territorio' por distrito (casados, solteros y viudos por sexo, total de hombres, mujeres y almas; edades; clases). | Q6: =IFERROR(MATCH(K6,Niveles!$B$2:$B$10,0),"") -> 2
A7: pub_1813 | B7: 1813 | C7: Villa de Huasco | E7: Villa de Huasco: censo de provincia, total de su población (estado civil por sexo y edades del total) | F7: cuadro | H7: 64 | I7: verificada | J7: 1813 | K7: departamento | L7: sexo+edad | M7: parcial | N7: verificada | O7: transcrito | P7: Transcrito en digitalizacion/1813/pub_1813_provincias.csv (edad × sexo, estado civil, totales) y pub_1813_distritos.csv (distritos × sexo). | Q7: =IFERROR(MATCH(K7,Niveles!$B$2:$B$10,0),"") -> 6
A8: pub_1813 | B8: 1813 | C8: Ciudad de La Serena | E8: Ciudad de La Serena: censo de territorio por distrito | F8: bloque | H8: 66 | I8: verificada | J8: 1813 | K8: distrito | L8: sexo+edad | M8: parcial | N8: verificada | O8: pendiente | P8: PDF 66-88. Cuadros 'Censo de territorio' por distrito (casados, solteros y viudos por sexo, total de hombres, mujeres y almas; edades; clases). Incluye cuerpos veteranos, rentas de conventos y objetos públicos (PDF 67, 71, 74, 84). | Q8: =IFERROR(MATCH(K8,Niveles!$B$2:$B$10,0),"") -> 2
A9: pub_1813 | B9: 1813 | C9: Ciudad de La Serena | E9: Ciudad de La Serena: censo de provincia, total de su población (estado civil por sexo y edades del total) | F9: cuadro | H9: 89 | I9: verificada | J9: 1813 | K9: departamento | L9: sexo+edad | M9: parcial | N9: verificada | O9: transcrito | P9: Transcrito en digitalizacion/1813/pub_1813_provincias.csv (edad × sexo, estado civil, totales) y pub_1813_distritos.csv (distritos × sexo). | Q9: =IFERROR(MATCH(K9,Niveles!$B$2:$B$10,0),"") -> 6
A10: pub_1813 | B10: 1813 | C10: Provincia de Petorca | E10: Petorca: censo de territorio por distrito | F10: bloque | H10: 93 | I10: verificada | J10: 1813 | K10: distrito | L10: sexo+edad | M10: parcial | N10: verificada | O10: pendiente | P10: PDF 93-98. Cuadros 'Censo de territorio' por distrito (casados, solteros y viudos por sexo, total de hombres, mujeres y almas; edades; clases). | Q10: =IFERROR(MATCH(K10,Niveles!$B$2:$B$10,0),"") -> 2
A11: pub_1813 | B11: 1813 | C11: Provincia de Petorca | E11: Petorca: censo de provincia, total de su población (estado civil por sexo y edades del total) | F11: cuadro | H11: 99 | I11: verificada | J11: 1813 | K11: departamento | L11: sexo+edad | M11: parcial | N11: verificada | O11: transcrito | P11: Transcrito en digitalizacion/1813/pub_1813_provincias.csv (edad × sexo, estado civil, totales) y pub_1813_distritos.csv (distritos × sexo). | Q11: =IFERROR(MATCH(K11,Niveles!$B$2:$B$10,0),"") -> 6
